Workbook
Name \0: #REF!
Name \d: #REF!
Name \l: #REF!
Name \r: #REF!
Name __FDS_USED_FOR_REUSING_RANGE_IDS_RECYCLE: {1,1,1,1,1,1,1,1,1,1,1,1,1,1,1,1,1,1,1,1,1,1,1,1,1,1,1,1,1,1}
Name _2_DC_Power_Transistors: #REF!
Name _2_Total_Power_Discrete: #REF!
Name _3_DC_Power_Diodes: #REF!
Name _3_Power_Transistors_Breakout: #REF!
Name _4_RF_Power_Discrete: #REF!
Name _4_Total_RF_Discrete: #REF!
Name _5_Small_Signal_Discrete: #REF!
Name _5_Total_Small_Signal_Discrete: #REF!
Name _6_End_Market_Overview: #REF!
Name _7_Glossary_of_Terms: #REF!
Name africaCountries: #REF!
Name Amort: #REF!
Name Arial: #REF!
Name asiaPacificExJapanCountries: #REF!
Name asiaPacificStates: #REF!
Name Asset_turns: #REF!
Name Assets: #REF!
Name b: #REF!
Name c_: #REF!
Name Case: #REF!
Name CaseCount: #REF!
Name CASH: #REF!
Name cd: #REF!
Name centralEasternEuropeCountries: #REF!
Name CF_OP_GR: "'=BackSheet!$D$239:$AG$239"
Name CF_PR_DV: "'=BackSheet!$D$241:$AG$241"
Name Choices_Wrapper: #REF!
Name CompanyList: #REF!
Name CompanyName: #REF!
Name CompanyPicked: #REF!
Name CompList11: #REF!
Name consumerDemandExposure: #REF!
Name consumersExposure: #REF!
Name CONT: #REF!
Name Conv_mark: 1
Name CurrentYear: #REF!
Name datalength: COUNTA(#REF!)
Name dataseries_minus_space_2: OFFSET(#REF!,0,0,COUNTIF(#REF!,">""")+1,1)
Name dataseries1: OFFSET(#REF!,0,0,COUNTA(#REF!),1)
Name DCYear: #REF!
Name Debt: #REF!
Name Debt_95: #REF!
Name Debt_96: #REF!
Name Debt_97: #REF!
Name Debt_Cap: #REF!
Name Def: #REF!
Name Definitions: #REF!
Name Dep: #REF!
Name developedEuropeExUKCountries: #REF!
Name DEVELOPMENT: 5
Name DevTotCon: #REF!
Name domesticAndForeignExposure: #REF!
Name domesticCostExposure: #REF!
Name DPYear: #REF!
Name Dropdown_lookup: #REF!

Sheet CircularReferenceAlert
B2: This workbook contains formulas which intentionally use circular reference calculation. These calculations can be resolved as intended by the originating analyst by applying the following settings in the File >> Options >> Formulas:
B5: 1) Select the Enable iterative calculation check box
B6: 2) Set Maximum Iterations = 100
B7: 3) Set Maximum Change = 0.001
B9: Failure to apply these settings can result in incorrect calculation or unexpected termination of your Microsoft Excel session.

Sheet ImportantDisclosures
A2: 20 Bank Street, Canary Wharf
A3: London E14 4AD
A4: United Kingdom
A5: Tel: +44 (0)20 7425 8000
A7: Authors: Lee Simpson,Terence Tsui,Nigel van Putten,Amelia Scicluna
A8: Date: 16 Apr 2026
A10: Ticker: ASML.AS
A11: Stock Rating: Overweight
A12: Industry: Technology - European Semiconductors
A13: Industry View: In-Line
A14: Price as of 16 Apr 2026: 1230.00
A15: Target Price: 1400.00
... A123: Equal-weight and Not-Rated to hold and Underweight to sell recommendations, respectively.
B125: Coverage Universe | D125: Investment Banking Clients (IBC) | G125: Other Material Investment Services Clients (MISC)
A126: Stock Rating Category | B126: Count | C126: % of Total | D126: Count | E126: % of Total IBC | F126: % of Rating Category | G126: Count | H126: % of Total Other MISC
A127: Overweight/Buy | B127: 1534 | C127: 0.42 | D127: 461 | E127: 0.5 | F127: 0.3 | G127: 698 | H127: 0.43
A128: Equal-weight/Hold | B128: 1573 | C128: 0.43 | D128: 372 | E128: 0.4 | F128: 0.24 | G128: 716 | H128: 0.44
A129: Not-Rated/Hold | B129: 4 | C129: 0 | D129: 1 | E129: 0 | F129: 0.25 | G129: 1 | H129: 0
A130: Underweight/Sell | B130: 568 | C130: 0.15 | D130: 89 | E130: 0.1 | F130: 0.16 | G130: 209 | H130: 0.13
A131: Total | B131: 3679 | D131: 923 | G131: 1624
A133: Data include common stock and ADRs currently assigned ratings. Investment Banking Clients are companies
A134: from whom Morgan Stanley received investment banking compensation in the last 12 months. Due to rounding
A135: off of decimals, the percentages provided in the "% of total" column may not add up to exactly 100
A136: percent.
A138: Analyst Stock Ratings
A140: Overweight (O). The stock's total return is expected to exceed the average total return of the analyst's
A141: industry (or industry team's) coverage universe, on a risk-adjusted basis, over the next 12-18 months.
A143: Equal-weight (E). The stock's total return is expected to be in line with the average total return of
A144: the analyst's industry (or industry team's) coverage universe, on a risk-adjusted basis, over the next
A145: 12-18 months.
A147: Not-Rated (NR). Currently the analyst does not have adequate conviction about the stock's total return
A148: relative to the average total return of the analyst's industry (or industry team's) coverage universe,
... A424: © Copyright 2026 Morgan Stanley

Sheet Cover
C3: Morgan Stanley Equity Research Europe
C4: European Technology | I4: Analyst | J4: Lee Simpson
C5: Sector | E5: Semiconductors | I5: Email | J5: lee.simpson@morganstanley.com
C6: Last updated | E6: =TODAY() -> 46128 | I6: Tel. | J6: +44 (0)20 7425 3378
C11: Company Details | I11: Company Description: Dutch-based (Veldhoven) ASML Holdings NV is the dominant supplier (75% share) of lithography equipment to the global semiconductor industry. ASML designs, develops, integrates, markets and services lithography systems, which are essential for the fabrication of semiconductor chips. The company retains a focus on next-gen R&D and marketing whilst outsourcing c.85% of its production to third-party system assemblers. Tools based on immersion technology form the rump of ASML’s order book which includes next generation, Extreme Ultraviolet (EUV) toolsets. Formerly part of Philips, ASML was spun off in 1984 (renamed 'Philips Labs'), with the parent keeping a 50% stake and ASM International acquiring the other half. By 1988, ASMI pulled out of the venture and Philips Labs was renamed as ASML and floated on the Amsterdam and New York exchanges. Today, ASML has a c. 80% free float.
C12: Name | E12: ASML Holdings NV
C13: Ticker | E13: ASML.AS
C14: Fiscal Year End | E14: 44926
C15: Accounting GAAP | E15: US GAAP
C16: Currency - Report | E16: EUR
C17: Currency - Quote | E17: EUR
C23: Equity Details | I23: Contact Details
C24: Company Name | E24: =$E$12 -> ASML Holdings NV | I24: Website | K24: www.asml.com | N24: Address | O24: ASML Netherlands B.V.
C25: Main Ticker | E25: =E13 -> ASML.AS | I25: Founded | K25: 1984 | O25: De Run 6501
C26: Share Price | E26: {=_xll.FDS("ASML-NL","P_PRICE(0)")} -> 1263.4 | I26: Country of Incorp. | K26: Netherlands | O26: 5504 DR Veldhoven
I27: Listed Exchange | K27: Amsterdam (Listed AEX) | O27: The Netherlands
N28: Tel. | O28: +31 40 268 3000
I30: Management Details
I31: CEO | K31: Peter Wennink
I32: CFO | K32: Roger Dassen
I33: Investor Relations | K33: Skip Miller (Global), Pete Convertito (US), Peter Cheang (Asia)
C38: Sources for data in this workbook include:
C39: Morgan Stanley estimates
C40: Company reports

Sheet Sales
A1: =Cover!$E$12 -> ASML Holdings NV | EG1: =EG10 -> 8766.5 | EH1: =EH10 -> 8339.4 | EI1: =EI10 -> 10142.5 | EJ1: =EJ10 -> 10425.195 | EK1: =EK10 -> 37673.595 | EL1: =EL10 -> 48011.948
A2: Sales, Units, Bookings & Backlog | ER2: i | ES2: o | ET2: u | EU2: aa | EV2: ag | EW2: am | EX2: as | EY2: ay | EZ2: be | FA2: bk | FB2: bq | FC2: bw | FD2: cc | FE2: ci | FF2: co | FG2: cu | FH2: da | FI2: dg | FJ2: dm | FK2: ds | FL2: dy | FM2: ee | FN2: ek | FO2: el
A3: EURm unless otherwise stated | E3: 1Q04 | F3: 2Q04 | G3: 3Q04 | H3: 4Q04 | I3: 2004 | K3: 1Q05 | L3: 2Q05 | M3: 3Q05 | N3: 4Q05 | O3: 2005 | Q3: 1Q06 | R3: 2Q06 | S3: 3Q06 | T3: 4Q06 | U3: 2006 | W3: 1Q07 | X3: 2Q07 | Y3: 3Q07 | Z3: 4Q07 | AA3: 2007 | AC3: 1Q08 | AD3: 2Q08 | AE3: 3Q08 | AF3: 4Q08 | AG3: 2008 | AI3: 1Q09 | AJ3: 2Q09 | AK3: 3Q09 | AL3: 4Q09 | AM3: 2009 | AO3: 1Q10 | AP3: 2Q10 | AQ3: 3Q10 | AR3: 4Q10 | AS3: 2010 | AU3: 1Q11 | AV3: 2Q11 | AW3: 3Q11 | AX3: 4Q11 | AY3: 2011 | BA3: 1Q12 | BB3: 2Q12 | BC3: 3Q12 | BD3: 4Q12 | BE3: 2012 | BG3: 1Q13 | BH3: 2Q13 | BI3: 3Q13 | BJ3: 4Q13 | BK3: 2013 | BM3: 1Q14 | BN3: 2Q14 | BO3: 3Q14 | BP3: 4Q14 | BQ3: 2014 | BS3: 1Q15 | BT3: 2Q15 | BU3: 3Q15 | BV3: 4Q15 | BW3: 2015 | BY3: 1Q16 | BZ3: 2Q16 | CA3: 3Q16 | CB3: 4Q16 | CC3: 2016 | CE3: 1Q17 | CF3: 2Q17 | CG3: 3Q17 | CH3: 4Q17 | CI3: 2017 | CK3: 1Q18 | CL3: 2Q18 | CM3: 3Q18 | CN3: 4Q18 | CO3: 2018 | CQ3: 1Q19 | CR3: 2Q19 | CS3: 3Q19 | CT3: 4Q19 | CU3: 2019 | CW3: 1Q20 | CX3: 2Q20 | CY3: 3Q20 | CZ3: 4Q20 | DA3: 2020 | DC3: 1Q21 | DD3: 2Q21 | DE3: 3Q21 | DF3: 4Q21 | DG3: 2021 | DI3: 1Q22 | DJ3: 2Q22 | DK3: 3Q22 | DL3: 4Q22 | DM3: 2022 | DO3: 1Q23 | DP3: 2Q23 | DQ3: 3Q23 | DR3: 4Q23 | DS3: 2023 | DU3: 1Q24 | DV3: 2Q24 | DW3: 3Q24 | DX3: 4Q24 | DY3: 2024 | EA3: 1Q25 | EB3: 2Q25 | EC3: 3Q25 | ED3: 4Q25 | EE3: 2025 | EG3: 1Q26 | EH3: 2Q26e | EI3: 3Q26e | EJ3: 4Q26e | EK3: 2026e | EL3: 2027e | EN3: Notes | ER3: 2004 | ES3: 2005 | ET3: 2006 | EU3: 2007 | EV3: 2008 | EW3: 2009 | EX3: 2010 | EY3: 2011 | EZ3: 2012 | FA3: 2013 | FB3: 2014 | FC3: 2015 | FD3: 2016 | FE3: 2017 | FF3: 2018 | FG3: 2019 | FH3: 2020 | FI3: 2021 | FJ3: 2022 | FK3: 2023 | FL3: 2024 | FM3: 2025e | FN3: 2026e | FO3: 2027e | FP3: 2028e | FQ3: 2029e | FR3: 2030e
A6: REVENUE SUMMARY | ER6: =ER$3 -> 2004 | ES6: =ES$3 -> 2005 | ET6: =ET$3 -> 2006 | EU6: =EU$3 -> 2007 | EV6: =EV$3 -> 2008 | EW6: =EW$3 -> 2009 | EX6: =EX$3 -> 2010 | EY6: =EY$3 -> 2011 | ... FD6: =FD$3 -> 2016
B8: Net System Sales | H8: 709.839 | I8: 2174.908 | K8: 632.135 | L8: 680.534 | M8: 458.992 | N8: =O8-M8-L8-K8 -> 456.017 | O8: 2227.678 | Q8: 553.101 | R8: 840.817 | S8: 856.556 | T8: =U8-S8-R8-Q8 -> 978.591 | U8: 3229.065 | W8: 858.948 | X8: 825.817 | Y8: 843.232 | Z8: 852.824 | AA8: 3380.821 | AC8: 819.986 | AD8: 725.586 | AE8: 590.723 | AF8: 380.466 | AG8: =AC8+AD8+AE8+AF8 -> 2516.761 | AI8: 101.1 | AJ8: 183.259 | AK8: 458.691 | AL8: 431.808 | AM8: =AI8+AJ8+AK8+AL8 -> 1174.858 | AO8: 631.6 | AP8: 923 | AQ8: 1027 | AR8: 1313.1 | AS8: =AO8+AP8+AQ8+AR8 -> 3894.7 | AU8: 1284.4 | AV8: 1333.6 | AW8: 1273.2 | AX8: 992.7 | AY8: =AU8+AV8+AW8+AX8 -> 4883.9 | BA8: 1050 | BB8: 984.8 | BC8: 1000.3 | BD8: 766.5 | BE8: =BA8+BB8+BC8+BD8 -> 3801.6 | BG8: 676.9 | BH8: 915.5 | BI8: 959.5 | BJ8: 1441.2 | BK8: =BG8+BH8+BI8+BJ8 -> 3993.1 | BM8: 1030 | BN8: 1243 | BO8: 884.5 | BP8: 1085.3 | BQ8: =BM8+BN8+BO8+BP8 -> 4242.8 | BS8: 1246.5 | BT8: 1134.5 | BU8: 975.3 | BV8: 880.9 | BW8: =BS8+BT8+BU8+BV8 -> 4237.2 | BY8: 859.8 | BZ8: 1265.4 | CA8: 1257.7 | CB8: 1289.1 | CC8: =BY8+BZ8+CA8+CB8 -> 4672 | CE8: 1215.8 | CF8: 1384.1 | CG8: 1818.9 | CH8: 1954.9 | CI8: =CE8+CF8+CG8+CH8 -> 6373.7 | CK8: 1667.7 | CL8: 2086.5 | CM8: 2080.6 | CN8: 2424.3 | CO8: =CK8+CL8+CM8+CN8 -> 8259.1 | CQ8: 1689 | CR8: 1850.8 | CS8: 2325.6 | CT8: 3130.7 | CU8: =CQ8+CR8+CS8+CT8 -> 8996.1 | CW8: 1584 | CX8: 2438.6 | CY8: 3095.6 | CZ8: 3198.3 | DA8: =CW8+CX8+CY8+CZ8 -> 10316.5 | DC8: 3128.8 | DD8: 2949.6 | DE8: 4111.1 | DF8: 3463.2 | DG8: =DC8+DD8+DE8+DF8 -> 13652.7 | DI8: 2287.2 | DJ8: 4140.5 | DK8: 4254.7 | DL8: 4747.9 | DM8: =SUM(DI8:DL8) -> 15430.3 | DO8: 5341.8 | DP8: 5606.1 | DQ8: 5308.2 | DR8: 5682.5 | DS8: =SUM(DO8:DR8) -> 21938.6 | DU8: 3965.9 | DV8: 4760.9 | DW8: 5926 | DX8: 7115.9 | DY8: =DU8+DV8+DW8+DX8 -> 21768.7 | EA8: 5740.4 | EB8: 5596.1 | EC8: 5553.8 | ED8: 7584 | EE8: =EA8+EB8+EC8+ED8 -> 24474.3 | EG8: 6279 | EH8: 5870 | EI8: 7930 | EJ8: 8297.995 | EK8: =EG8+EH8+EI8+EJ8 -> 28376.995 | EL8: =EL55 -> 37458.148 | ER8: =I8 -> 2174.908 | ES8: =O8 -> 2227.678 | ET8: =U8 -> 3229.065 | EU8: =AA8 -> 3380.821 | EV8: =AG8 -> 2516.761 | EW8: =AM8 -> 1174.858 | EX8: =AS8 -> 3894.7 | EY8: =AY8 -> 4883.9 | EZ8: =BE8 -> 3801.6 | FA8: =BK8 -> 3993.1 | FB8: =BQ8 -> 4242.8 | FC8: =BW8 -> 4237.2 | FD8: =CC8 -> 4672 | FE8: =CI8 -> 6373.7 | FF8: =CO8 -> 8259.1 | FG8: =CU8 -> 8996.1 | FH8: =DA8 -> 10316.5 | FI8: =DG8 -> 13652.7 | FJ8: =DM8 -> 15430.3 | FK8: =DS8 -> 21938.6 | FL8: =DY8 -> 21768.7 | FM8: =EE8 -> 24474.3 | FN8: =EK8 -> 28376.995 | FO8: =EL8 -> 37458.148 | FP8: =FP55 -> 30338.833 | FQ8: =FQ55 -> 21030 | FR8: =FR55 -> 25940
B9: Net Service & Field Option sales | H9: 75.323 | I9: 290.469 | K9: 52.545 | L9: 82.731 | M9: 74.161 | N9: =O9-M9-L9-K9 -> 91.852 | O9: 301.289 | Q9: 76.289 | R9: 100.937 | S9: 101.877 | T9: =U9-S9-R9-Q9 -> 88.936 | U9: 368.039 | W9: 101.295 | X9: 104.405 | Y9: 91.142 | Z9: 120.063 | AA9: 416.905 | AC9: 99.222 | AD9: 118.571 | AE9: 105.77 | AF9: 113.354 | AG9: =AC9+AD9+AE9+AF9 -> 436.917 | AI9: 82.525 | AJ9: 93.341 | AK9: 96.581 | AL9: 148.758 | AM9: =AI9+AJ9+AK9+AL9 -> 421.205 | AO9: 110.2 | AP9: 145.7 | AQ9: 149 | AR9: 208.3 | AS9: =AO9+AP9+AQ9+AR9 -> 613.2 | AU9: 167.8 | AV9: 195.8 | AW9: 185.3 | AX9: 218.2 | AY9: =AU9+AV9+AW9+AX9 -> 767.1 | BA9: 201.9 | BB9: 242.9 | BC9: 228.5 | BD9: 256.6 | BE9: =BA9+BB9+BC9+BD9 -> 929.9 | BG9: 215.2 | BH9: 271.2 | BI9: 358.7 | BJ9: 407.1 | BK9: =BG9+BH9+BI9+BJ9 -> 1252.2 | BM9: 366.5 | BN9: 400.6 | BO9: 437.7 | BP9: 408.7 | BQ9: =BM9+BN9+BO9+BP9 -> 1613.5 | BS9: 403.4 | BT9: 519.6 | BU9: 573.9 | BV9: 553.3 | BW9: =BS9+BT9+BU9+BV9 -> 2050.2 | BY9: 473.4 | BZ9: 474.2 | CA9: 556.9 | CB9: 618.3 | CC9: =BY9+BZ9+CA9+CB9 -> 2122.8 | CE9: 727.8 | CF9: 717.3 | CG9: 628.5 | CH9: 605.5 | CI9: =CE9+CF9+CG9+CH9 -> 2679.1 | CK9: 617.3 | CL9: 653.9 | CM9: 695.5 | CN9: 718.2 | CO9: =CK9+CL9+CM9+CN9 -> 2684.9 | CQ9: 540.1 | CR9: 717.1 | CS9: 660.9 | CT9: 905.7 | CU9: =CQ9+CR9+CS9+CT9 -> 2823.8 | CW9: 856.6 | CX9: 887.1 | CY9: 862.4 | CZ9: 1055.8 | DA9: =CW9+CX9+CY9+CZ9 -> 3661.9 | DC9: 1235.1 | DD9: 1070.6 | DE9: 1130.2 | DF9: 1522.4 | DG9: =DC9+DD9+DE9+DF9 -> 4958.3 | DI9: 1247.2 | DJ9: 1290 | DK9: 1523.6 | DL9: 1682.3 | DM9: =DI9+DJ9+DK9+DL9 -> 5743.1 | DO9: 1404.4 | DP9: 1296.2 | DQ9: 1364.8 | DR9: 1554.5 | DS9: =DO9+DP9+DQ9+DR9 -> 5619.9 | DU9: 1324.1 | DV9: 1481.9 | DW9: 1541.3 | DX9: 2146.9 | DY9: =DU9+DV9+DW9+DX9 -> 6494.2 | EA9: 2001.1 | EB9: 2095.6 | EC9: 1962.2 | ED9: 2134 | EE9: =EA9+EB9+EC9+ED9 -> 8192.9 | EG9: 2487.5 | EH9: 2469.4 | EI9: 2212.5 | EJ9: 2127.2 | EK9: =EG9+EH9+EI9+EJ9 -> 9296.6 | EL9: =EL37 -> 10553.8 | ER9: =I9 -> 290.469 | ES9: =O9 -> 301.289 | ET9: =U9 -> 368.039 | EU9: =AA9 -> 416.905 | EV9: =AG9 -> 436.917 | EW9: =AM9 -> 421.205 | EX9: =AS9 -> 613.2 | EY9: =AY9 -> 767.1 | EZ9: =BE9 -> 929.9 | FA9: =BK9 -> 1252.2 | FB9: =BQ9 -> 1613.5 | FC9: =BW9 -> 2050.2 | FD9: =CC9 -> 2122.8 | FE9: =CI9 -> 2679.1 | FF9: =CO9 -> 2684.9 | FG9: =CU9 -> 2823.8 | FH9: =DA9 -> 3661.9 | FI9: =DG9 -> 4958.3 | FJ9: =DM9 -> 5743.1 | FK9: =DS9 -> 5619.9 | FL9: =DY9 -> 6494.2 | FM9: =EE9 -> 8192.9 | FN9: =EK9 -> 9296.6 | FO9: =EL9 -> 10553.8 | FP9: =FP37 -> 10957.588 | FQ9: =FQ37 -> 1107.5 | FR9: =FR37 -> 0
B10: Net Sales | E10: 453.485 | F10: 616.258 | G10: 610.472 | H10: =H8+H9 -> 785.162 | I10: =I8+I9 -> 2465.377 | K10: =K8+K9 -> 684.68 | L10: =L8+L9 -> 763.265 | M10: =M8+M9 -> 533.153 | N10: =N8+N9 -> 547.869 | O10: =O8+O9 -> 2528.967 | Q10: =Q8+Q9 -> 629.39 | R10: =R8+R9 -> 941.754 | S10: =S8+S9 -> 958.433 | T10: =T8+T9 -> 1067.527 | U10: =U8+U9 -> 3597.104 | W10: =W8+W9 -> 960.243 | X10: =X8+X9 -> 930.222 | Y10: =Y8+Y9 -> 934.374 | Z10: =Z8+Z9 -> 972.887 | AA10: =AA8+AA9 -> 3797.726 | AC10: =AC8+AC9 -> 919.208 | AD10: =AD8+AD9 -> 844.157 | AE10: =AE8+AE9 -> 696.493 | AF10: =AF8+AF9 -> 493.82 | AG10: =AG8+AG9 -> 2953.678 | AI10: =AI8+AI9 -> 183.625 | AJ10: =AJ8+AJ9 -> 276.6 | AK10: =AK8+AK9 -> 555.272 | AL10: =AL8+AL9 -> 580.566 | AM10: =AM8+AM9 -> 1596.063 | AO10: =AO8+AO9 -> 741.8 | AP10: =AP8+AP9 -> 1068.7 | AQ10: =AQ8+AQ9 -> 1176 | AR10: =AR8+AR9 -> 1521.4 | AS10: =AS8+AS9 -> 4507.9 | AU10: =AU8+AU9 -> 1452.2 | AV10: =AV8+AV9 -> 1529.4 | AW10: =AW8+AW9 -> 1458.5 | AX10: =AX8+AX9 -> 1210.9 | AY10: =AY8+AY9 -> 5651 | BA10: =BA8+BA9 -> 1251.9 | BB10: =BB8+BB9 -> 1227.7 | BC10: =BC8+BC9 -> 1228.8 | BD10: =BD8+BD9 -> 1023.1 | BE10: =BE8+BE9 -> 4731.5 | BG10: =BG8+BG9 -> 892.1 | BH10: =BH8+BH9+BH11 -> 1218.7 | BI10: =BI8+BI9+BI11 -> 1392.2 | BJ10: =BJ8+BJ9+BJ11 -> 1922.3 | BK10: =BK8+BK9+BK11 -> 5425.3 | BM10: =BM8+BM9+BM11 -> 1396.5 | BN10: =BN8+BN9+BN11 -> 1643.6 | BO10: =BO8+BO9+BO11 -> 1322.2 | BP10: =BP8+BP9+BP11 -> 1494 | BQ10: =BQ8+BQ9+BQ11 -> 5856.3 | BS10: =BS8+BS9+BS11 -> 1649.9 | BT10: =BT8+BT9+BT11 -> 1654.1 | BU10: =BU8+BU9+BU11 -> 1549.2 | BV10: =BV8+BV9+BV11 -> 1434.2 | BW10: =BW8+BW9+BW11 -> 6287.4 | BY10: =BY8+BY9 -> 1333.2 | BZ10: =BZ8+BZ9 -> 1739.6 | CA10: =CA8+CA9 -> 1814.6 | CB10: =CB8+CB9 -> 1907.4 | CC10: =CC8+CC9 -> 6794.8 | CE10: =CE8+CE9 -> 1943.6 | CF10: =CF8+CF9 -> 2101.4 | CG10: =CG8+CG9 -> 2447.4 | CH10: =CH8+CH9 -> 2560.4 | CI10: =CI8+CI9 -> 9052.8 | CK10: =CK8+CK9 -> 2285 | CL10: =CL8+CL9 -> 2740.4 | CM10: =CM8+CM9 -> 2776.1 | CN10: =CN8+CN9 -> 3142.5 | CO10: =CO8+CO9 -> 10944 | CQ10: =CQ8+CQ9 -> 2229.1 | CR10: =CR8+CR9 -> 2567.9 | CS10: =CS8+CS9 -> 2986.5 | CT10: =CT8+CT9 -> 4036.4 | CU10: =CU8+CU9 -> 11819.9 | CW10: =CW8+CW9 -> 2440.6 | CX10: =CX8+CX9 -> 3325.7 | CY10: =CY8+CY9 -> 3958 | CZ10: =CZ8+CZ9 -> 4254.1 | DA10: =DA8+DA9 -> 13978.4 | DC10: =DC8+DC9 -> 4363.9 | DD10: =DD8+DD9 -> 4020.2 | DE10: =DE8+DE9 -> 5241.3 | DF10: =DF8+DF9 -> 4985.6 | DG10: =DG8+DG9 -> 18611 | DI10: =DI8+DI9 -> 3534.4 | DJ10: =DJ8+DJ9 -> 5430.5 | DK10: =DK8+DK9 -> 5778.3 | DL10: =DL8+DL9 -> 6430.2 | DM10: =DM8+DM9 -> 21173.4 | DO10: =SUM(DO8:DO9) -> 6746.2 | DP10: =SUM(DP8:DP9) -> 6902.3 | DQ10: =SUM(DQ8:DQ9) -> 6673 | DR10: =SUM(DR8:DR9) -> 7237 | DS10: =DS8+DS9 -> 27558.5 | DU10: =DU8+DU9 -> 5290 | DV10: =DV8+DV9 -> 6242.8 | DW10: =DW8+DW9 -> 7467.3 | DX10: =DX8+DX9 -> 9262.8 | DY10: =DY8+DY9 -> 28262.9 | EA10: =EA8+EA9 -> 7741.5 | EB10: =EB8+EB9 -> 7691.7 | EC10: =EC8+EC9 -> 7516 | ED10: =ED8+ED9 -> 9718 | EE10: =EE8+EE9 -> 32667.2 | EG10: =EG8+EG9 -> 8766.5 | EH10: =EH8+EH9 -> 8339.4 | EI10: =EI8+EI9 -> 10142.5 | EJ10: =EJ8+EJ9 -> 10425.195 | EK10: =EK8+EK9 -> 37673.595 | EL10: =SUM(EL9,EL8) -> 48011.948 | ER10: =SUM(ER9,ER8) -> 2465.377 | ES10: =SUM(ES9,ES8) -> 2528.967 | ET10: =SUM(ET9,ET8) -> 3597.104 | EU10: =SUM(EU9,EU8) -> 3797.726 | EV10: =SUM(EV9,EV8) -> 2953.678 | EW10: =SUM(EW9,EW8) -> 1596.063 | EX10: =SUM(EX9,EX8) -> 4507.9 | EY10: =SUM(EY9,EY8) -> 5651 | ... FR10: =SUM(FR9,FR8) -> 25940
BH11: 32 | BI11: 74 | BJ11: =($BK$11-$BH$11)/2 -> 74 | BK11: 180
B12: Growth q/q
B13: System sales | K13: =K8/H8-1 -> -0.10946708 | L13: =L8/K8-1 -> 0.076564341 | M13: =M8/L8-1 -> -0.32554141 | N13: =N8/M8-1 -> -0.0064815945 | Q13: =Q8/N8-1 -> 0.21289557 | R13: =R8/Q8-1 -> 0.52018709 | S13: =S8/R8-1 -> 0.018718699 | T13: =T8/S8-1 -> 0.14247171 | W13: =W8/T8-1 -> -0.12226047 | X13: =X8/W8-1 -> -0.038571602 | Y13: =Y8/X8-1 -> 0.021088207 | Z13: =Z8/Y8-1 -> 0.01137528 | AC13: =AC8/Z8-1 -> -0.038505014 | AD13: =AD8/AC8-1 -> -0.11512392 | AE13: =AE8/AD8-1 -> -0.1858677 | AF13: =AF8/AE8-1 -> -0.35593163 | AI13: =AI8/AF8-1 -> -0.73427323 | AJ13: =AJ8/AI8-1 -> 0.81265084 | AK13: =AK8/AJ8-1 -> 1.5029657 | AL13: =AL8/AK8-1 -> -0.058608083 | AO13: =AO8/AL8-1 -> 0.46268712 | AP13: =AP8/AO8-1 -> 0.46136795 | AQ13: =AQ8/AP8-1 -> 0.11267606 | AR13: =AR8/AQ8-1 -> 0.27857838 | AU13: =AU8/AR8-1 -> -0.021856675 | AV13: =AV8/AU8-1 -> 0.038305824 | AW13: =AW8/AV8-1 -> -0.045290942 | AX13: =AX8/AW8-1 -> -0.22031103 | BA13: =BA8/AX8-1 -> 0.057721366 | BB13: =BB8/BA8-1 -> -0.062095238 | BC13: =BC8/BB8-1 -> 0.015739236 | BD13: =BD8/BC8-1 -> -0.23372988 | BG13: =BG8/BD8-1 -> -0.11689498 | BH13: =BH8/BG8-1 -> 0.35248929 | BI13: =BI8/BH8-1 -> 0.048061169 | BJ13: =BJ8/BI8-1 -> 0.50203231 | BM13: =BM8/BJ8-1 -> -0.28531779 | BN13: =BN8/BM8-1 -> 0.20679612 | BO13: =BO8/BN8-1 -> -0.28841512 | BP13: =BP8/BO8-1 -> 0.22702092 | BS13: =BS8/BP8-1 -> 0.14853036 | BT13: =BT8/BS8-1 -> -0.089851584 | BU13: =BU8/BT8-1 -> -0.14032613 | BV13: =BV8/BU8-1 -> -0.096790731 | BY13: =BY8/BV8-1 -> -0.023952776 | BZ13: =BZ8/BY8-1 -> 0.47173761 | CA13: =CA8/BZ8-1 -> -0.0060850324 | CB13: =CB8/CA8-1 -> 0.024966208 | CE13: =CE8/CB8-1 -> -0.056861376 | CF13: =CF8/CE8-1 -> 0.13842737 | CG13: =CG8/CF8-1 -> 0.31413915 | CH13: =CH8/CG8-1 -> 0.074770466 | CK13: =CK8/CH8-1 -> -0.14691289 | CL13: =CL8/CK8-1 -> 0.2511243 | CM13: =CM8/CL8-1 -> -0.0028277019 | CN13: =CN8/CM8-1 -> 0.16519273 | CQ13: =CQ8/CN8-1 -> -0.30330405 | CR13: =CR8/CQ8-1 -> 0.095796329 | CS13: =CS8/CR8-1 -> 0.25653771 | CT13: =CT8/CS8-1 -> 0.34619023 | CW13: =CW8/CT8-1 -> -0.49404287 | CX13: =CX8/CW8-1 -> 0.5395202 | CY13: =CY8/CX8-1 -> 0.26941688 | CZ13: =CZ8/CY8-1 -> 0.033176121 | DC13: =DC8/CZ8-1 -> -0.021730294 | DD13: =DD8/DC8-1 -> -0.057274354 | DE13: =DE8/DD8-1 -> 0.39378221 | DF13: =DF8/DE8-1 -> -0.15759772 | DI13: =DI8/DF8-1 -> -0.33957034 | DJ13: =DJ8/DI8-1 -> 0.81029206 | DK13: =DK8/DJ8-1 -> 0.02758121 | DL13: =DL8/DK8-1 -> 0.11591887 | DO13: =DO8/DL8-1 -> 0.12508688 | DP13: =DP8/DO8-1 -> 0.049477704 | DQ13: =DQ8/DP8-1 -> -0.053138546 | DR13: =DR8/DQ8-1 -> 0.070513545 | DU13: =DU8/DR8-1 -> -0.30208535 | DV13: =DV8/DS8-1 -> -0.7829898 | DW13: =DW8/DV8-1 -> 0.24472264 | DX13: =DX8/DW8-1 -> 0.20079312 | EA13: =EA8/DX8-1 -> -0.19329951 | EB13: =EB8/DY8-1 -> -0.74292907 | EC13: =EC8/EB8-1 -> -0.0075588356 | ED13: =ED8/EC8-1 -> 0.36555151 | EG13: =EG8/ED8-1 -> -0.17207278 | EH13: =EH8/EG8-1 -> -0.065137761 | EI13: =EI8/EH8-1 -> 0.35093697 | EJ13: =EJ8/EI8-1 -> 0.046405422
B14: Field option and service sales | K14: =K9/H9-1 -> -0.30240431 | L14: =L9/K9-1 -> 0.57447902 | M14: =M9/L9-1 -> -0.10358874 | N14: =N9/M9-1 -> 0.23854856 | Q14: =Q9/N9-1 -> -0.16943561 | R14: =R9/Q9-1 -> 0.32308721 | S14: =S9/R9-1 -> 0.0093127396 | T14: =T9/S9-1 -> -0.12702573 | W14: =W9/T9-1 -> 0.1389651 | X14: =X9/W9-1 -> 0.030702404 | Y14: =Y9/X9-1 -> -0.12703415 | Z14: =Z9/Y9-1 -> 0.31731803 | AC14: =AC9/Z9-1 -> -0.17358387 | AD14: =AD9/AC9-1 -> 0.19500716 | AE14: =AE9/AD9-1 -> -0.10796063 | AF14: =AF9/AE9-1 -> 0.071702751 | AI14: =AI9/AF9-1 -> -0.27197099 | AJ14: =AJ9/AI9-1 -> 0.13106331 | AK14: =AK9/AJ9-1 -> 0.034711434 | AL14: =AL9/AK9-1 -> 0.54024083 | AO14: =AO9/AL9-1 -> -0.25919951 | AP14: =AP9/AO9-1 -> 0.32214156 | AQ14: =AQ9/AP9-1 -> 0.022649279 | AR14: =AR9/AQ9-1 -> 0.39798658 | AU14: =AU9/AR9-1 -> -0.19443111 | AV14: =AV9/AU9-1 -> 0.16686532 | AW14: =AW9/AV9-1 -> -0.053626149 | AX14: =AX9/AW9-1 -> 0.17754992 | BA14: =BA9/AX9-1 -> -0.074702108 | BB14: =BB9/BA9-1 -> 0.20307083 | BC14: =BC9/BB9-1 -> -0.059283656 | BD14: =BD9/BC9-1 -> 0.12297593 | BG14: =BG9/BD9-1 -> -0.16134061 | BH14: =BH9/BG9-1 -> 0.26022305 | BI14: =BI9/BH9-1 -> 0.32264012 | BJ14: =BJ9/BI9-1 -> 0.1349317 | BM14: =BM9/BJ9-1 -> -0.099729796 | BN14: =BN9/BM9-1 -> 0.093042292 | BO14: =BO9/BN9-1 -> 0.092611083 | BP14: =BP9/BO9-1 -> -0.066255426 | BS14: =BS9/BP9-1 -> -0.012967947 | BT14: =BT9/BS9-1 -> 0.28805156 | BU14: =BU9/BT9-1 -> 0.10450346 | BV14: =BV9/BU9-1 -> -0.035894755 | BY14: =BY9/BV9-1 -> -0.14440629 | BZ14: =BZ9/BY9-1 -> 0.0016899028 | CA14: =CA9/BZ9-1 -> 0.17439899 | CB14: =CB9/CA9-1 -> 0.11025319 | CE14: =CE9/CB9-1 -> 0.1770985 | CF14: =CF9/CE9-1 -> -0.01442704 | CG14: =CG9/CF9-1 -> -0.12379757 | CH14: =CH9/CG9-1 -> -0.036595068 | CK14: =CK9/CH9-1 -> 0.019488026 | CL14: =CL9/CK9-1 -> 0.059290458 | CM14: =CM9/CL9-1 -> 0.06361829 | CN14: =CN9/CM9-1 -> 0.03263839 | CQ14: =CQ9/CN9-1 -> -0.24798106 | CR14: =CR9/CQ9-1 -> 0.32771709 | CS14: =CS9/CR9-1 -> -0.078371217 | CT14: =CT9/CS9-1 -> 0.37040399 | CW14: =CW9/CT9-1 -> -0.054212212 | CX14: =CX9/CW9-1 -> 0.035605884 | CY14: =CY9/CX9-1 -> -0.027843535 | CZ14: =CZ9/CY9-1 -> 0.22425788 | DC14: =DC9/CZ9-1 -> 0.16982383 | DD14: =DD9/DC9-1 -> -0.1331876 | DE14: =DE9/DD9-1 -> 0.055669718 | DF14: =DF9/DE9-1 -> 0.34701823 | DI14: =DI9/DF9-1 -> -0.18076721 | DJ14: =DJ9/DI9-1 -> 0.03431687 | DK14: =DK9/DJ9-1 -> 0.18108527 | DL14: =DL9/DK9-1 -> 0.1041612 | DO14: =DO9/DL9-1 -> -0.16519051 | DP14: =DP9/DO9-1 -> -0.077043577 | DQ14: =DQ9/DP9-1 -> 0.052923931 | DR14: =DR9/DQ9-1 -> 0.13899472 | DU14: =DU9/DR9-1 -> -0.14821486 | DV14: =DV9/DS9-1 -> -0.73631203 | DW14: =DW9/DV9-1 -> 0.040083676 | DX14: =DX9/DW9-1 -> 0.39291507 | EA14: =EA9/DX9-1 -> -0.067911873 | EB14: =EB9/DY9-1 -> -0.67731206 | EC14: =EC9/EB9-1 -> -0.063657186 | ED14: =ED9/EC9-1 -> 0.087554785 | EG14: =EG9/ED9-1 -> 0.16565136 | EH14: =EH9/EG9-1 -> -0.0072763819 | EI14: =EI9/EH9-1 -> -0.10403337 | EJ14: =EJ9/EI9-1 -> -0.038553672
B15: Total q/q | K15: =K10/H10-1 -> -0.12797614 | L15: =L10/K10-1 -> 0.11477625 | M15: =M10/L10-1 -> -0.30148376 | N15: =N10/M10-1 -> 0.027601833 | Q15: =Q10/N10-1 -> 0.14879652 | R15: =R10/Q10-1 -> 0.49629641 | S15: =S10/R10-1 -> 0.01771057 | T15: =T10/S10-1 -> 0.11382538 | W15: =W10/T10-1 -> -0.10049769 | X15: =X10/W10-1 -> -0.031263961 | Y15: =Y10/X10-1 -> 0.0044634507 | Z15: =Z10/Y10-1 -> 0.041217971 | AC15: =AC10/Z10-1 -> -0.055174959 | AD15: =AD10/AC10-1 -> -0.081647462 | AE15: =AE10/AD10-1 -> -0.17492481 | AF15: =AF10/AE10-1 -> -0.29099072 | AI15: =AI10/AF10-1 -> -0.62815398 | AJ15: =AJ10/AI10-1 -> 0.50633084 | AK15: =AK10/AJ10-1 -> 1.007491 | AL15: =AL10/AK10-1 -> 0.04555245 | AO15: =AO10/AL10-1 -> 0.27771864 | AP15: =AP10/AO10-1 -> 0.44068482 | AQ15: =AQ10/AP10-1 -> 0.10040236 | AR15: =AR10/AQ10-1 -> 0.29370748 | AU15: =AU10/AR10-1 -> -0.045484422 | AV15: =AV10/AU10-1 -> 0.053160722 | AW15: =AW10/AV10-1 -> -0.046358049 | AX15: =AX10/AW10-1 -> -0.16976346 | BA15: =BA10/AX10-1 -> 0.033859113 | BB15: =BB10/BA10-1 -> -0.019330617 | BC15: =BC10/BB10-1 -> 0.00089598436 | BD15: =BD10/BC10-1 -> -0.16739909 | BG15: =BG10/BD10-1 -> -0.12804222 | BH15: =BH10/BG10-1 -> 0.36610245 | BI15: =BI10/BH10-1 -> 0.14236481 | BJ15: =BJ10/BI10-1 -> 0.38076426 | BM15: =BM10/BJ10-1 -> -0.2735265 | BN15: =BN10/BM10-1 -> 0.17694236 | BO15: =BO10/BN10-1 -> -0.19554636 | BP15: =BP10/BO10-1 -> 0.12993496 | BS15: =BS10/BP10-1 -> 0.10435074 | BT15: =BT10/BS10-1 -> 0.0025456088 | BU15: =BU10/BT10-1 -> -0.063418173 | BV15: =BV10/BU10-1 -> -0.074231862 | BY15: =BY10/BV10-1 -> -0.070422535 | BZ15: =BZ10/BY10-1 -> 0.30483048 | CA15: =CA10/BZ10-1 -> 0.043113359 | CB15: =CB10/CA10-1 -> 0.051140747 | CE15: =CE10/CB10-1 -> 0.018978714 | CF15: =CF10/CE10-1 -> 0.081189545 | CG15: =CG10/CF10-1 -> 0.16465214 | CH15: =CH10/CG10-1 -> 0.046171447 | CK15: =CK10/CH10-1 -> -0.10756132 | CL15: =CL10/CK10-1 -> 0.19929978 | CM15: =CM10/CL10-1 -> 0.013027295 | CN15: =CN10/CM10-1 -> 0.13198372 | CQ15: =CQ10/CN10-1 -> -0.2906603 | CR15: =CR10/CQ10-1 -> 0.15198959 | CS15: =CS10/CR10-1 -> 0.16301258 | CT15: =CT10/CS10-1 -> 0.35154864 | CW15: =CW10/CT10-1 -> -0.39535229 | CX15: =CX10/CW10-1 -> 0.36265672 | CY15: =CY10/CX10-1 -> 0.19012539 | CZ15: =CZ10/CY10-1 -> 0.07481051 | DC15: =DC10/CZ10-1 -> 0.025810395 | DD15: =DD10/DC10-1 -> -0.078759825 | DE15: =DE10/DD10-1 -> 0.30374111 | DF15: =DF10/DE10-1 -> -0.048785607 | DI15: =DI10/DF10-1 -> -0.29107831 | DJ15: =DJ10/DI10-1 -> 0.53647012 | DK15: =DK10/DJ10-1 -> 0.064045668 | DL15: =DL10/DK10-1 -> 0.11281865 | DO15: =DO10/DL10-1 -> 0.049143106 | DP15: =DP10/DO10-1 -> 0.023138952 | DQ15: =DQ10/DP10-1 -> -0.03322081 | DR15: =DR10/DQ10-1 -> 0.084519706 | DU15: =DU10/DR10-1 -> -0.26903413 | DV15: =DV10/DS10-1 -> -0.77347098 | DW15: =DW10/DV10-1 -> 0.19614596 | DX15: =DX10/DW10-1 -> 0.24044835 | EA15: =EA10/DX10-1 -> -0.1642376 | EB15: =EB10/DY10-1 -> -0.72785171 | EC15: =EC10/EB10-1 -> -0.022842805 | ED15: =ED10/EC10-1 -> 0.29297499 | EG15: =EG10/ED10-1 -> -0.097911093 | EH15: =EH10/EG10-1 -> -0.048719557 | EI15: =EI10/EH10-1 -> 0.2162146 | EJ15: =EJ10/EI10-1 -> 0.027872319
B17: Growth y/y
B18: System sales | N18: =N8/H8-1 -> -0.35757686 | O18: =O8/I8-1 -> 0.024263095 | Q18: =Q8/K8-1 -> -0.12502709 | R18: =R8/L8-1 -> 0.23552534 | S18: =S8/M8-1 -> 0.8661676 | T18: =T8/N8-1 -> 1.1459529 | U18: =U8/O8-1 -> 0.44952053 | W18: =W8/Q8-1 -> 0.55296772 | X18: =X8/R8-1 -> -0.017839792 | Y18: =Y8/S8-1 -> -0.015555317 | Z18: =Z8/T8-1 -> -0.12851845 | AA18: =AA8/U8-1 -> 0.046996886 | AC18: =AC8/W8-1 -> -0.045360138 | AD18: =AD8/X8-1 -> -0.12137193 | AE18: =AE8/Y8-1 -> -0.29945377 | AF18: =AF8/Z8-1 -> -0.55387513 | AG18: =AG8/AA8-1 -> -0.25557697 | AI18: =AI8/AC8-1 -> -0.87670521 | AJ18: =AJ8/AD8-1 -> -0.74743311 | AK18: =AK8/AE8-1 -> -0.22350916 | AL18: =AL8/AF8-1 -> 0.13494504 | AM18: =AM8/AG8-1 -> -0.5331865 | AO18: =AO8/AI8-1 -> 5.2472799 | AP18: =AP8/AJ8-1 -> 4.0365876 | AQ18: =AQ8/AK8-1 -> 1.2389801 | AR18: =AR8/AL8-1 -> 2.0409349 | AS18: =AS8/AM8-1 -> 2.3150389 | AU18: =AU8/AO8-1 -> 1.0335655 | AV18: =AV8/AP8-1 -> 0.44485374 | AW18: =AW8/AQ8-1 -> 0.23972736 | AX18: =AX8/AR8-1 -> -0.24400274 | AY18: =AY8/AS8-1 -> 0.25398619 | BA18: =BA8/AU8-1 -> -0.18249766 | BB18: =BB8/AV8-1 -> -0.26154769 | BC18: =BC8/AW8-1 -> -0.21434182 | BD18: =BD8/AX8-1 -> -0.2278634 | BE18: =BE8/AY8-1 -> -0.22160568 | BG18: =BG8/BA8-1 -> -0.35533333 | BH18: =BH8/BB8-1 -> -0.070369618 | BI18: =BI8/BC8-1 -> -0.040787764 | BJ18: =BJ8/BD8-1 -> 0.88023483 | BK18: =BK8/BE8-1 -> 0.050373527 | BM18: =BM8/BG8-1 -> 0.52164278 | BN18: =BN8/BH8-1 -> 0.35772802 | BO18: =BO8/BI8-1 -> -0.078165711 | BP18: =BP8/BJ8-1 -> -0.24694699 | BQ18: =BQ8/BK8-1 -> 0.062532869 | BS18: =BS8/BM8-1 -> 0.21019417 | BT18: =BT8/BN8-1 -> -0.087288817 | BU18: =BU8/BO8-1 -> 0.10265687 | BV18: =BV8/BP8-1 -> -0.18833502 | BW18: =BW8/BQ8-1 -> -0.0013198831 | BY18: =BY8/BS8-1 -> -0.31022864 | BZ18: =BZ8/BT8-1 -> 0.11538123 | CA18: =CA8/BU8-1 -> 0.28955193 | CB18: =CB8/BV8-1 -> 0.46338972 | CC18: =CC8/BW8-1 -> 0.10261493 | CE18: =CE8/BY8-1 -> 0.41404978 | CF18: =CF8/BZ8-1 -> 0.093804331 | CG18: =CG8/CA8-1 -> 0.44621134 | CH18: =CH8/CB8-1 -> 0.51648437 | CI18: =CI8/CC8-1 -> 0.36423373 | CK18: =CK8/CE8-1 -> 0.37168942 | CL18: =CL8/CF8-1 -> 0.50747778 | CM18: =CM8/CG8-1 -> 0.14387817 | CN18: =CN8/CH8-1 -> 0.24011458 | CO18: =CO8/CI8-1 -> 0.29580934 | CQ18: =CQ8/CK8-1 -> 0.012772081 | CR18: =CR8/CL8-1 -> -0.11296429 | CS18: =CS8/CM8-1 -> 0.11775449 | CT18: =CT8/CN8-1 -> 0.29138308 | CU18: =CU8/CO8-1 -> 0.089234905 | CW18: =CW8/CQ8-1 -> -0.062166963 | CX18: =CX8/CR8-1 -> 0.31759239 | CY18: =CY8/CS8-1 -> 0.33109735 | CZ18: =CZ8/CT8-1 -> 0.021592615 | DA18: =DA8/CU8-1 -> 0.14677471 | DC18: =DC8/CW8-1 -> 0.97525253 | DD18: =DD8/CX8-1 -> 0.20954646 | DE18: =DE8/CY8-1 -> 0.32804626 | DF18: =DF8/CZ8-1 -> 0.082825251 | DG18: =DG8/DA8-1 -> 0.32338487 | DI18: =DI8/DC8-1 -> -0.26898491 | DJ18: =DJ8/DD8-1 -> 0.40374966 | DK18: =DK8/DE8-1 -> 0.034929824 | DL18: =DL8/DF8-1 -> 0.3709575 | DM18: =DM8/DG8-1 -> 0.13020135 | DO18: =DO8/DI8-1 -> 1.3355194 | DP18: =DP8/DJ8-1 -> 0.35396691 | DQ18: =DQ8/DK8-1 -> 0.24760853 | DR18: =DR8/DL8-1 -> 0.19684492 | DS18: =DS8/DM8-1 -> 0.421787 | DU18: =DU8/DO8-1 -> -0.25757235 | DV18: =DV8/DP8-1 -> -0.15076435 | DW18: =DW8/DQ8-1 -> 0.11638597 | DX18: =DX8/DR8-1 -> 0.25224813 | DY18: =DY8/DS8-1 -> -0.007744341 | EA18: =EA8/DU8-1 -> 0.44743942 | EB18: =EB8/DV8-1 -> 0.17542902 | EC18: =EC8/DW8-1 -> -0.062807965 | ED18: =ED8/DX8-1 -> 0.065782262 | EE18: =EE8/DY8-1 -> 0.12428854 | EG18: =EG8/EA8-1 -> 0.093826214 | EH18: =EH8/EB8-1 -> 0.048944801 | EI18: =EI8/EC8-1 -> 0.4278512 | EJ18: =EJ8/ED8-1 -> 0.09414491 | EK18: =EK8/EE8-1 -> 0.15946094 | EL18: =EL8/FN8-1 -> 0.32001812 | ES18: =ES8/ER8-1 -> 0.024263095 | ET18: =ET8/ES8-1 -> 0.44952053 | EU18: =EU8/ET8-1 -> 0.046996886 | EV18: =EV8/EU8-1 -> -0.25557697 | EW18: =EW8/EV8-1 -> -0.5331865 | EX18: =EX8/EW8-1 -> 2.3150389 | EY18: =EY8/EX8-1 -> 0.25398619 | EZ18: =EZ8/EY8-1 -> -0.22160568 | ... FR18: =FR8/FQ8-1 -> 0.23347599
B19: Field option and service sales | N19: =N9/H9-1 -> 0.2194416 | O19: =O9/I9-1 -> 0.037250102 | Q19: =Q9/K9-1 -> 0.45187934 | R19: =R9/L9-1 -> 0.22006261 | S19: =S9/M9-1 -> 0.37372743 | T19: =T9/N9-1 -> -0.031746723 | U19: =U9/O9-1 -> 0.22154808 | W19: =W9/Q9-1 -> 0.32777989 | X19: =X9/R9-1 -> 0.034358065 | Y19: =Y9/S9-1 -> -0.10537216 | Z19: =Z9/T9-1 -> 0.34999325 | AA19: =AA9/U9-1 -> 0.13277397 | AC19: =AC9/W9-1 -> -0.020464979 | AD19: =AD9/X9-1 -> 0.13568316 | AE19: =AE9/Y9-1 -> 0.16049681 | AF19: =AF9/Z9-1 -> -0.055878997 | AG19: =AG9/AA9-1 -> 0.048001343 | AI19: =AI9/AC9-1 -> -0.16827921 | AJ19: =AJ9/AD9-1 -> -0.2127839 | AK19: =AK9/AE9-1 -> -0.086877186 | AL19: =AL9/AF9-1 -> 0.31233128 | AM19: =AM9/AG9-1 -> -0.035961064 | AO19: =AO9/AI9-1 -> 0.33535292 | AP19: =AP9/AJ9-1 -> 0.56094321 | AQ19: =AQ9/AK9-1 -> 0.5427465 | AR19: =AR9/AL9-1 -> 0.40026083 | AS19: =AS9/AM9-1 -> 0.45582317 | AU19: =AU9/AO9-1 -> 0.52268603 | AV19: =AV9/AP9-1 -> 0.34385724 | AW19: =AW9/AQ9-1 -> 0.24362416 | AX19: =AX9/AR9-1 -> 0.047527604 | AY19: =AY9/AS9-1 -> 0.25097847 | BA19: =BA9/AU9-1 -> 0.20321812 | BB19: =BB9/AV9-1 -> 0.24055158 | BC19: =BC9/AW9-1 -> 0.23313546 | BD19: =BD9/AX9-1 -> 0.17598533 | BE19: =BE9/AY9-1 -> 0.21222787 | BG19: =BG9/BA9-1 -> 0.065874195 | BH19: =BH9/BB9-1 -> 0.11650885 | BI19: =BI9/BC9-1 -> 0.56980306 | BJ19: =BJ9/BD9-1 -> 0.58651598 | BK19: =BK9/BE9-1 -> 0.34659641 | BM19: =BM9/BG9-1 -> 0.70306691 | BN19: =BN9/BH9-1 -> 0.47713864 | BO19: =BO9/BI9-1 -> 0.22023975 | BP19: =BP9/BJ9-1 -> 0.0039302383 | BQ19: =BQ9/BK9-1 -> 0.28853218 | BS19: =BS9/BM9-1 -> 0.10068213 | BT19: =BT9/BN9-1 -> 0.29705442 | BU19: =BU9/BO9-1 -> 0.31117204 | BV19: =BV9/BP9-1 -> 0.35380475 | BW19: =BW9/BQ9-1 -> 0.27065386 | BY19: =BY9/BS9-1 -> 0.17352504 | BZ19: =BZ9/BT9-1 -> -0.087374904 | CA19: =CA9/BU9-1 -> -0.029621885 | CB19: =CB9/BV9-1 -> 0.11747696 | CC19: =CC9/BW9-1 -> 0.035411179 | CE19: =CE9/BY9-1 -> 0.5373891 | CF19: =CF9/BZ9-1 -> 0.51265289 | CG19: =CG9/CA9-1 -> 0.12856886 | CH19: =CH9/CB9-1 -> -0.020701925 | CI19: =CI9/CC9-1 -> 0.26205954 | CK19: =CK9/CE9-1 -> -0.15182743 | CL19: =CL9/CF9-1 -> -0.088387007 | CM19: =CM9/CG9-1 -> 0.10660302 | CN19: =CN9/CH9-1 -> 0.18612717 | CO19: =CO9/CI9-1 -> 0.0021649061 | CQ19: =CQ9/CK9-1 -> -0.12506075 | CR19: =CR9/CL9-1 -> 0.096650864 | CS19: =CS9/CM9-1 -> -0.049748382 | CT19: =CT9/CN9-1 -> 0.26106934 | CU19: =CU9/CO9-1 -> 0.05173377 | CW19: =CW9/CQ9-1 -> 0.58600259 | CX19: =CX9/CR9-1 -> 0.23706596 | CY19: =CY9/CS9-1 -> 0.30488727 | CZ19: =CZ9/CT9-1 -> 0.16572817 | DA19: =DA9/CU9-1 -> 0.29679864 | DC19: =DC9/CW9-1 -> 0.44186318 | DD19: =DD9/CX9-1 -> 0.20685379 | DE19: =DE9/CY9-1 -> 0.31052876 | DF19: =DF9/CZ9-1 -> 0.44193976 | DG19: =DG9/DA9-1 -> 0.35402387 | DI19: =DI9/DC9-1 -> 0.0097967776 | DJ19: =DJ9/DD9-1 -> 0.20493181 | DK19: =DK9/DE9-1 -> 0.34807999 | DL19: =DL9/DF9-1 -> 0.10503153 | DM19: =DM9/DG9-1 -> 0.15828006 | DO19: =DO9/DI9-1 -> 0.12604233 | DP19: =DP9/DJ9-1 -> 0.0048062016 | DQ19: =DQ9/DK9-1 -> -0.10422683 | DR19: =DR9/DL9-1 -> -0.075967426 | DS19: =DS9/DM9-1 -> -0.021451829 | DU19: =DU9/DO9-1 -> -0.057177442 | DV19: =DV9/DP9-1 -> 0.14326493 | DW19: =DW9/DQ9-1 -> 0.12932298 | DX19: =DX9/DR9-1 -> 0.38108717 | DY19: =DY9/DS9-1 -> 0.15557216 | EA19: =EA9/DU9-1 -> 0.51129069 | EB19: =EB9/DV9-1 -> 0.41413051 | EC19: =EC9/DW9-1 -> 0.27308117 | ED19: =ED9/DX9-1 -> -0.0060086637 | EE19: =EE9/DY9-1 -> 0.26157186 | EG19: =EG9/EA9-1 -> 0.24306631 | EH19: =EH9/EB9-1 -> 0.17837374 | EI19: =EI9/EC9-1 -> 0.1275609 | EJ19: =EJ9/ED9-1 -> -0.0031865042 | EK19: =EK9/EE9-1 -> 0.1347142 | EL19: =EL9/FN9-1 -> 0.13523224 | ES19: =ES9/ER9-1 -> 0.037250102 | ET19: =ET9/ES9-1 -> 0.22154808 | EU19: =EU9/ET9-1 -> 0.13277397 | EV19: =EV9/EU9-1 -> 0.048001343 | EW19: =EW9/EV9-1 -> -0.035961064 | EX19: =EX9/EW9-1 -> 0.45582317 | EY19: =EY9/EX9-1 -> 0.25097847 | EZ19: =EZ9/EY9-1 -> 0.21222787 | ... FR19: =FR9/FQ9-1 -> -1
B20: Total y/y | K20: =K10/E10-1 -> 0.50981841 | L20: =L10/F10-1 -> 0.23854782 | M20: =M10/G10-1 -> -0.12665446 | N20: =N10/H10-1 -> -0.30222171 | O20: =O10/I10-1 -> 0.025793215 | Q20: =Q10/K10-1 -> -0.080753053 | R20: =R10/L10-1 -> 0.23384932 | S20: =S10/M10-1 -> 0.79766971 | T20: =T10/N10-1 -> 0.94850776 | U20: =U10/O10-1 -> 0.42236099 | W20: =W10/Q10-1 -> 0.52567248 | X20: =X10/R10-1 -> -0.012245236 | Y20: =Y10/S10-1 -> -0.025102433 | Z20: =Z10/T10-1 -> -0.088653495 | AA20: =AA10/U10-1 -> 0.0557732 | AC20: =AC10/W10-1 -> -0.042733975 | AD20: =AD10/X10-1 -> -0.092520925 | AE20: =AE10/Y10-1 -> -0.25458863 | AF20: =AF10/Z10-1 -> -0.49241793 | AG20: =AG10/AA10-1 -> -0.22225089 | AI20: =AI10/AC10-1 -> -0.80023564 | AJ20: =AJ10/AD10-1 -> -0.67233583 | AK20: =AK10/AE10-1 -> -0.20276011 | AL20: =AL10/AF10-1 -> 0.1756632 | AM20: =AM10/AG10-1 -> -0.45963541 | AO20: =AO10/AI10-1 -> 3.0397549 | AP20: =AP10/AJ10-1 -> 2.8637021 | AQ20: =AQ10/AK10-1 -> 1.117881 | AR20: =AR10/AL10-1 -> 1.6205462 | AS20: =AS10/AM10-1 -> 1.8243873 | AU20: =AU10/AO10-1 -> 0.95767053 | AV20: =AV10/AP10-1 -> 0.4310845 | AW20: =AW10/AQ10-1 -> 0.24022109 | AX20: =AX10/AR10-1 -> -0.20408834 | AY20: =AY10/AS10-1 -> 0.25357705 | BA20: =BA10/AU10-1 -> -0.13792866 | BB20: =BB10/AV10-1 -> -0.1972669 | BC20: =BC10/AW10-1 -> -0.15749057 | BD20: =BD10/AX10-1 -> -0.15509125 | BE20: =BE10/AY10-1 -> -0.16271456 | BG20: =BG10/BA10-1 -> -0.28740315 | BH20: =BH10/BB10-1 -> -0.0073307811 | BI20: =BI10/BC10-1 -> 0.13297526 | BJ20: =BJ10/BD10-1 -> 0.87889747 | BK20: =BK10/BE10-1 -> 0.14663426 | BM20: =BM10/BG10-1 -> 0.56540747 | BN20: =BN10/BH10-1 -> 0.3486502 | BO20: =BO10/BI10-1 -> -0.050280132 | BP20: =BP10/BJ10-1 -> -0.22280601 | BQ20: =BQ10/BK10-1 -> 0.079442611 | BS20: =BS10/BM10-1 -> 0.18145363 | BT20: =BT10/BN10-1 -> 0.0063884157 | BU20: =BU10/BO10-1 -> 0.17168356 | BV20: =BV10/BP10-1 -> -0.040026774 | BW20: =BW10/BQ10-1 -> 0.073613032 | BY20: =BY10/BS10-1 -> -0.19195103 | BZ20: =BZ10/BT10-1 -> 0.051689741 | CA20: =CA10/BU10-1 -> 0.17131423 | CB20: =CB10/BV10-1 -> 0.32994004 | CC20: =CC10/BW10-1 -> 0.080701085 | CE20: =CE10/BY10-1 -> 0.45784578 | CF20: =CF10/BZ10-1 -> 0.20797885 | CG20: =CG10/CA10-1 -> 0.34872699 | CH20: =CH10/CB10-1 -> 0.34235084 | CI20: =CI10/CC10-1 -> 0.33231295 | CK20: =CK10/CE10-1 -> 0.17565343 | CL20: =CL10/CF10-1 -> 0.30408299 | CM20: =CM10/CG10-1 -> 0.13430579 | CN20: =CN10/CH10-1 -> 0.22734729 | CO20: =CO10/CI10-1 -> 0.20890774 | CQ20: =CQ10/CK10-1 -> -0.024463895 | CR20: =CR10/CL10-1 -> -0.062947015 | CS20: =CS10/CM10-1 -> 0.075789777 | CT20: =CT10/CN10-1 -> 0.28445505 | CU20: =CU10/CO10-1 -> 0.080034722 | CW20: =CW10/CQ10-1 -> 0.094881342 | CX20: =CX10/CR10-1 -> 0.29510495 | CY20: =CY10/CS10-1 -> 0.32529717 | CZ20: =CZ10/CT10-1 -> 0.053934199 | DA20: =DA10/CU10-1 -> 0.18261576 | DC20: =DC10/CW10-1 -> 0.78804392 | DD20: =DD10/CX10-1 -> 0.20882822 | DE20: =DE10/CY10-1 -> 0.32422941 | DF20: =DF10/CZ10-1 -> 0.17195176 | DG20: =DG10/DA10-1 -> 0.33141132 | DI20: =DI10/DC10-1 -> -0.19008227 | DJ20: =DJ10/DD10-1 -> 0.35080344 | DK20: =DK10/DE10-1 -> 0.1024555 | DL20: =DL10/DF10-1 -> 0.28975449 | DM20: =DM10/DG10-1 -> 0.13768202 | DO20: =DO10/DI10-1 -> 0.90872567 | DP20: =DP10/DJ10-1 -> 0.27102477 | DQ20: =DQ10/DK10-1 -> 0.15483793 | DR20: =DR10/DL10-1 -> 0.12547044 | DS20: =DS10/DM10-1 -> 0.30156234 | DU20: =DU10/DO10-1 -> -0.21585485 | DV20: =DV10/DP10-1 -> -0.095547861 | DW20: =DW10/DQ10-1 -> 0.11903192 | DX20: =DX10/DR10-1 -> 0.27992262 | DY20: =DY10/DS10-1 -> 0.025560172 | EA20: =EA10/DU10-1 -> 0.46342155 | EB20: =EB10/DV10-1 -> 0.23209137 | EC20: =EC10/DW10-1 -> 0.0065217682 | ED20: =ED10/DX10-1 -> 0.049142808 | EE20: =EE10/DY10-1 -> 0.15583327 | EG20: =EG10/EA10-1 -> 0.13240328 | EH20: =EH10/EB10-1 -> 0.084207652 | EI20: =EI10/EC10-1 -> 0.3494545 | EJ20: =EJ10/ED10-1 -> 0.072771661 | EK20: =EK10/EE10-1 -> 0.15325449 | EL20: =EL10/FN10-1 -> 0.27441906 | EZ20: =EZ10/EY10-1 -> -0.16271456 | FA20: =FA10/EZ10-1 -> 0.10859136 | FB20: =FB10/FA10-1 -> 0.11648523 | FC20: =FC10/FB10-1 -> 0.073613032 | FD20: =FD10/FC10-1 -> 0.080701085 | FE20: =FE10/FD10-1 -> 0.33231295 | FF20: =FF10/FE10-1 -> 0.20890774 | FG20: =FG10/FF10-1 -> 0.080034722 | ... FR20: =FR10/FQ10-1 -> 0.17176736
A22: INSTALLED BASE MANAGEMENT | E22: =E$3 -> 1Q04 | F22: =F$3 -> 2Q04 | G22: =G$3 -> 3Q04 | H22: =H$3 -> 4Q04 | I22: =I$3 -> 2004 | K22: =K$3 -> 1Q05 | L22: =L$3 -> 2Q05 | M22: =M$3 -> 3Q05 | N22: =N$3 -> 4Q05 | O22: =O$3 -> 2005 | Q22: =Q$3 -> 1Q06 | R22: =R$3 -> 2Q06 | S22: =S$3 -> 3Q06 | T22: =T$3 -> 4Q06 | U22: =U$3 -> 2006 | W22: =W$3 -> 1Q07 | X22: =X$3 -> 2Q07 | Y22: =Y$3 -> 3Q07 | Z22: =Z$3 -> 4Q07 | AA22: =AA$3 -> 2007 | AC22: =AC$3 -> 1Q08 | AD22: =AD$3 -> 2Q08 | AE22: =AE$3 -> 3Q08 | AF22: =AF$3 -> 4Q08 | AG22: =AG$3 -> 2008 | AI22: =AI$3 -> 1Q09 | AJ22: =AJ$3 -> 2Q09 | AK22: =AK$3 -> 3Q09 | AL22: =AL$3 -> 4Q09 | AM22: =AM$3 -> 2009 | AO22: =AO$3 -> 1Q10 | AP22: =AP$3 -> 2Q10 | AQ22: =AQ$3 -> 3Q10 | AR22: =AR$3 -> 4Q10 | AS22: =AS$3 -> 2010 | AU22: =AU$3 -> 1Q11 | AV22: =AV$3 -> 2Q11 | AW22: =AW$3 -> 3Q11 | AX22: =AX$3 -> 4Q11 | AY22: =AY$3 -> 2011 | BA22: =BA$3 -> 1Q12 | BB22: =BB$3 -> 2Q12 | BC22: =BC$3 -> 3Q12 | BD22: =BD$3 -> 4Q12 | BE22: =BE$3 -> 2012 | BG22: =BG$3 -> 1Q13 | BH22: =BH$3 -> 2Q13 | BI22: =BI$3 -> 3Q13 | BJ22: =BJ$3 -> 4Q13 | BK22: =BK$3 -> 2013 | BM22: =BM$3 -> 1Q14 | BN22: =BN$3 -> 2Q14 | BO22: =BO$3 -> 3Q14 | BP22: =BP$3 -> 4Q14 | BQ22: =BQ$3 -> 2014 | BS22: =BS$3 -> 1Q15 | BT22: =BT$3 -> 2Q15 | BU22: =BU$3 -> 3Q15 | BV22: =BV$3 -> 4Q15 | BW22: =BW$3 -> 2015 | BY22: =BY$3 -> 1Q16 | BZ22: =BZ$3 -> 2Q16 | CA22: =CA$3 -> 3Q16 | CB22: =CB$3 -> 4Q16 | CC22: =CC$3 -> 2016 | CE22: =CE$3 -> 1Q17 | CF22: =CF$3 -> 2Q17 | CG22: =CG$3 -> 3Q17 | CH22: =CH$3 -> 4Q17 | CI22: =CI$3 -> 2017 | CK22: =CK$3 -> 1Q18 | CL22: =CL$3 -> 2Q18 | CM22: =CM$3 -> 3Q18 | CN22: =CN$3 -> 4Q18 | CO22: =CO$3 -> 2018
B24: High NA - installled units | DU24: 0 | DV24: 0 | DW24: 0 | DX24: 0 | DY24: =DX24 -> 0 | EA24: 0 | EB24: 0 | EC24: =EB24+EC73 -> 1 | ED24: =EC24+ED73 -> 3 | EE24: =ED24 -> 3 | EG24: =ED24+EG73 -> 5 | EH24: =EG24+EH73 -> 5 | EI24: =EH24+EI73 -> 7 | EJ24: =EI24+EJ73 -> 9 | EK24: =EJ24 -> 9 | EL24: =EK24+EL73 -> 15 | FE24: =CI24 -> 0 | FF24: =CO24 -> 0 | FG24: =CU24 -> 0 | FH24: =DA24 -> 0 | FI24: =DG24 -> 0 | FJ24: =DM24 -> 0 | FK24: =DS24 -> 0 | FL24: =DY24 -> 0 | FM24: =EE24 -> 3 | FN24: =EK24 -> 9 | FO24: =EL24 -> 15 | FP24: =FO24+FP73 -> 23 | FQ24: =EN24 -> 0 | FR24: =EO24 -> 0
B25: Low NA - installled units | CE25: =BQ74+BW74+CC74+BK74+CE74 -> 11 | CF25: =CE25+CF74 -> 13 | CG25: =CF25+CG74 -> 17 | CH25: =CG25+CH74 -> 22 | CI25: =CH25 -> 22 | CK25: =CH25+CK74 -> 23 | CL25: =CK25+CL74 -> 30 | CM25: =CL25+CM74 -> 35 | CN25: =CM25+CN74 -> 40 | CO25: =CN25 -> 40 | CQ25: =CN25+CQ74 -> 44 | CR25: =CQ25+CR74 -> 51 | CS25: =CR25+CS74 -> 58 | CT25: =CS25+CT74 -> 66 | CU25: =CT25 -> 66 | CW25: =CT25+CW74 -> 68 | CX25: =CW25+CX74 -> 75 | CY25: =CX25+CY74 -> 89 | CZ25: =CY25+CZ74 -> 97 | DA25: =CZ25 -> 97 | DC25: =CZ25+DC74 -> 104 | DD25: =DC25+DD74 -> 113 | DE25: =DD25+DE74 -> 128 | DF25: =DE25+DF74 -> 139 | DG25: =DF25 -> 139 | DI25: =DF25+DI74 -> 142 | DJ25: =DI25+DJ74 -> 154 | DK25: =DJ25+DK74 -> 166 | DL25: =DK25+DL74 -> 179 | DM25: =DL25 -> 179 | DO25: =DL25+DO74 -> 196 | DP25: =DO25+DP74 -> 208 | DQ25: =DP25+DQ74 -> 219 | DR25: =DQ25+DR74 -> 232 | DS25: =DR25 -> 232 | DU25: =DR25+DU74 -> 243 | DV25: =DS25+DV74 -> 240 | DW25: =DV25+DW74 -> 251 | DX25: =DW25+DX74 -> 263 | DY25: =DX25 -> 263 | EA25: =DX25+EA74 -> 277 | EB25: =DY25+EB74 -> 273 | EC25: =EB25+EC74 -> 281 | ED25: =EC25+ED74 -> 293 | EE25: =ED25 -> 293 | EG25: =ED25+EG74 -> 307 | EH25: =EG25+EH74 -> 321 | EI25: =EH25+EI74 -> 338 | EJ25: =EI25+EJ74 -> 356 | EK25: =EJ25 -> 356 | EL25: =FN25+EL74 -> 440 | FE25: =CI25 -> 22 | FF25: =CO25 -> 40 | FG25: =CU25 -> 66 | FH25: =DA25 -> 97 | FI25: =DG25 -> 139 | FJ25: =DM25 -> 179 | FK25: =DS25 -> 232 | FL25: =DY25 -> 263 | FM25: =EE25 -> 293 | FN25: =EK25 -> 356 | FO25: =EL25 -> 440 | FP25: =GR25+FP74 -> 61 | FQ25: =EN25 -> 0 | FR25: =EO25 -> 0
B26: ArF - installled units | CE26: =31+57+31+94+101+72+77+BQ76+BW76+CC76+BK76+CE76 -> 771 | CF26: =CE26+CF76 -> 787 | CG26: =CF26+CG76 -> 809 | CH26: =CG26+CH76 -> 829 | CI26: =CH26 -> 829 | CK26: =CH26+CK76 -> 850 | CL26: =CK26+CL76 -> 869 | CM26: =CL26+CM76 -> 891 | CN26: =CM26+CN76 -> 915 | CO26: =CN26 -> 915 | CQ26: =CN26+CQ76 -> 932 | CR26: =CQ26+CR76 -> 945 | CS26: =CR26+CS76 -> 966 | CT26: =CS26+CT76 -> 997 | CU26: =CT26 -> 997 | CW26: =CT26+CW76 -> 1013 | CX26: =CW26+CX76 -> 1030 | CY26: =CX26+CY76 -> 1041 | CZ26: =CY26+CZ76 -> 1065 | DA26: =CZ26 -> 1065 | DC26: =CZ26+DC76 -> 1089 | DD26: =DC26+DD76 -> 1105 | DE26: =DD26+DE76 -> 1126 | DF26: =DE26+DF76 -> 1146 | DG26: =DF26 -> 1146 | DI26: =DF26+DI76 -> 1164 | DJ26: =DI26+DJ76 -> 1185 | DK26: =DJ26+DK76 -> 1205 | DL26: =DK26+DL76 -> 1227 | DM26: =DL26 -> 1227 | DO26: =DL26+DO76 -> 1252 | DP26: =DO26+DP76 -> 1291 | DQ26: =DP26+DQ76 -> 1323 | DR26: =DQ26+DR76 -> 1352 | DS26: =DR26 -> 1352 | DU26: =DR26+DU76 -> 1372 | DV26: =DS26+DV76 -> 1384 | DW26: =DV26+DW76 -> 1422 | DX26: =DW26+DX76 -> 1461 | DY26: =DX26 -> 1461 | EA26: =DX26+EA76 -> 1486 | EB26: =EA26+EB76 -> 1517 | EC26: =EB26+EC76 -> 1555 | ED26: =EC26+ED76 -> 1592 | EE26: =ED26 -> 1592 | EG26: =ED26+EG76 -> 1609 | EH26: =EG26+EH76 -> 1635.5 | EI26: =EH26+EI76 -> 1668.5 | EJ26: =EI26+EJ76 -> 1713.5 | EK26: =EJ26 -> 1713.5 | EL26: =FN26+EL76 -> 1868.7815 | FE26: =CI26 -> 829 | FF26: =CO26 -> 915 | FG26: =CU26 -> 997 | FH26: =DA26 -> 1065 | FI26: =DG26 -> 1146 | FJ26: =DM26 -> 1227 | FK26: =DS26 -> 1352 | FL26: =DY26 -> 1461 | FM26: =EE26 -> 1592 | FN26: =EK26 -> 1713.5 | FO26: =EL26 -> 1868.7815 | FP26: =GR26+FP76 -> 0 | FQ26: =EN26 -> 0 | FR26: =EO26 -> 0
B27: Total installed base | CE27: =SUM(CE24:CE26) -> 782 | CF27: =SUM(CF24:CF26) -> 800 | CG27: =SUM(CG24:CG26) -> 826 | CH27: =SUM(CH24:CH26) -> 851 | CI27: =SUM(CI24:CI26) -> 851 | CK27: =SUM(CK24:CK26) -> 873 | CL27: =SUM(CL24:CL26) -> 899 | CM27: =SUM(CM24:CM26) -> 926 | CN27: =SUM(CN24:CN26) -> 955 | CO27: =SUM(CO24:CO26) -> 955 | CQ27: =SUM(CQ24:CQ26) -> 976 | CR27: =SUM(CR24:CR26) -> 996 | CS27: =SUM(CS24:CS26) -> 1024 | CT27: =SUM(CT24:CT26) -> 1063 | CU27: =SUM(CU24:CU26) -> 1063 | CW27: =SUM(CW24:CW26) -> 1081 | CX27: =SUM(CX24:CX26) -> 1105 | CY27: =SUM(CY24:CY26) -> 1130 | CZ27: =SUM(CZ24:CZ26) -> 1162 | DA27: =SUM(DA24:DA26) -> 1162 | DC27: =SUM(DC24:DC26) -> 1193 | DD27: =SUM(DD24:DD26) -> 1218 | DE27: =SUM(DE24:DE26) -> 1254 | DF27: =SUM(DF24:DF26) -> 1285 | DG27: =SUM(DG24:DG26) -> 1285 | DI27: =SUM(DI24:DI26) -> 1306 | DJ27: =SUM(DJ24:DJ26) -> 1339 | DK27: =SUM(DK24:DK26) -> 1371 | DL27: =SUM(DL24:DL26) -> 1406 | DM27: =SUM(DM24:DM26) -> 1406 | DO27: =SUM(DO24:DO26) -> 1448 | DP27: =SUM(DP24:DP26) -> 1499 | DQ27: =SUM(DQ24:DQ26) -> 1542 | DR27: =SUM(DR24:DR26) -> 1584 | DS27: =SUM(DS24:DS26) -> 1584 | DU27: =SUM(DU24:DU26) -> 1615 | DV27: =SUM(DV24:DV26) -> 1624 | DW27: =SUM(DW24:DW26) -> 1673 | DX27: =SUM(DX24:DX26) -> 1724 | DY27: =SUM(DY24:DY26) -> 1724 | EA27: =SUM(EA24:EA26) -> 1763 | EB27: =SUM(EB24:EB26) -> 1790 | EC27: =SUM(EC24:EC26) -> 1837 | ED27: =SUM(ED24:ED26) -> 1888 | EE27: =SUM(EE24:EE26) -> 1888 | EG27: =SUM(EG24:EG26) -> 1921 | EH27: =SUM(EH24:EH26) -> 1961.5 | EI27: =SUM(EI24:EI26) -> 2013.5 | EJ27: =SUM(EJ24:EJ26) -> 2078.5 | EK27: =SUM(EK24:EK26) -> 2078.5 | EL27: =SUM(EL24:EL26) -> 2323.7815 | FE27: =SUM(FE24:FE26) -> 851 | FF27: =SUM(FF24:FF26) -> 955 | FG27: =SUM(FG24:FG26) -> 1063 | FH27: =SUM(FH24:FH26) -> 1162 | FI27: =SUM(FI24:FI26) -> 1285 | FJ27: =SUM(FJ24:FJ26) -> 1406 | FK27: =SUM(FK24:FK26) -> 1584 | FL27: =SUM(FL24:FL26) -> 1724 | ... FR27: =SUM(FR24:FR26) -> 0
B29: High NA - installled units | EG29: 5 | EH29: 5 | EI29: 5 | EJ29: 5 | EK29: =EK34/EE24 -> 0 | EL29: 20 | FE29: =CI29 -> 0 | FF29: =CO29 -> 0 | FG29: =CU29 -> 0 | FH29: =DA29 -> 0 | FI29: =DG29 -> 0 | FJ29: =DM29 -> 0 | FK29: =DS29 -> 0 | FL29: =DY29 -> 0 | FM29: =EE29 -> 0 | FN29: =EK29 -> 0 | FO29: =EL29 -> 20 | FP29: 15 | FQ29: 15 | FR29: 15
B30: Low NA - installled units | CK30: =CK35/CE25 -> 1.4472727 | CL30: =CL35/CF25 -> 3.08 | CM30: =CM35/CG25 -> 3.7929412 | CN30: =CN35/CH25 -> 3.2536364 | CO30: =CO35/CI25 -> 8.7281818 | CQ30: =CQ35/CK25 -> 1.3086957 | CR30: =CR35/CL25 -> 3.6266667 | CS30: =CS35/CM25 -> 1.0628571 | CT30: =CT35/CN25 -> 2.055 | CU30: =CU35/CO25 -> 6.4575 | CW30: =CW35/CQ25 -> 4.6409091 | CX30: =CX35/CR25 -> 4.4235294 | CY30: =CY35/CS25 -> 3.2103448 | CZ30: =CZ35/CT25 -> 2.4015152 | DA30: =DA35/CU25 -> 11.734848 | DC30: =DC35/CW25 -> 6.2455882 | DD30: =DD35/CX25 -> 4.6613333 | DE30: =DE35/CY25 -> 4.511236 | DF30: =DF35/CZ25 -> 5.8134021 | DG30: =DG35/DA25 -> 17.935052 | DI30: =DI35/DC25 -> 4.6625 | DJ30: =DJ35/DD25 -> 4.5707965 | DK30: =DK35/DE25 -> 4.865625 | DL30: =DL35/DF25 -> 4.6827338 | DM30: =DM35/DG25 -> 16.367626 | DO30: =DO35/DI25 -> 3.3323944 | DP30: =DP35/DJ25 -> 3.0305195 | DQ30: =DQ35/DK25 -> 3.1403614 | DR30: =DR35/DL25 -> 2.5150838 | DS30: =DS35/DM25 -> 10.678212 | DU30: =DU35/DO25 -> 2.2841837 | DV30: =DV35/DP25 -> 2.7798077 | DW30: =DW35/DQ25 -> 2.8091324 | DX30: =DX35/DR25 -> 3.4262931 | DY30: =DY35/DS25 -> 10.5 | EA30: =EA35/DU25 -> 4.282716 | EB30: =EB35/DV25 -> 4.695 | EC30: =EC35/DW25 -> 3.8517928 | ED30: =ED35/DX25 -> 4.2254753 | EE30: =EE35/DY25 -> 16.142966 | EG30: =EG35/EA25 -> 4.6884477 | EH30: 4.6 | EI30: 4 | EJ30: 4 | EK30: =EK35/EE25 -> 16.554608 | EL30: 16 | FE30: =CI30 -> 0 | FF30: =CO30 -> 8.7281818 | FG30: =CU30 -> 6.4575 | FH30: =DA30 -> 11.734848 | FI30: =DG30 -> 17.935052 | FJ30: =DM30 -> 16.367626 | FK30: =DS30 -> 10.678212 | FL30: =DY30 -> 10.5 | FM30: =EE30 -> 16.142966 | FN30: =EK30 -> 16.554608 | FO30: =EL30 -> 16 | FP30: 12.5 | FQ30: 12.5 | FR30: 12.5
B31: ArF - installled units | CK31: 0.78 | CL31: 0.78 | CM31: 0.78 | CN31: 0.78 | CO31: =CO36/CI26 -> 3.0070929 | CQ31: 0.6 | CR31: 0.7 | CS31: 0.7 | CT31: 0.9 | CU31: =CU36/CO26 -> 2.8038251 | CW31: 0.7 | CX31: 0.7 | CY31: 0.7 | CZ31: 0.9 | DA31: =DA36/CU26 -> 2.8960883 | DC31: 0.8 | DD31: 0.7 | DE31: 0.7 | DF31: 0.9 | DG31: =DG36/DA26 -> 3.0221596 | DI31: 0.7 | DJ31: 0.7 | DK31: 0.8 | DL31: 0.9 | DM31: =DM36/DG26 -> 3.026178 | DO31: 0.8 | DP31: 0.7 | DQ31: 0.7 | DR31: 0.9 | DS31: =DS36/DM26 -> 3.0224124 | DU31: 0.7 | DV31: 0.7 | DW31: 0.7 | DX31: 1 | DY31: =DY36/DS26 -> 3.0016272 | EA31: 0.7 | EB31: 0.7 | EC31: 0.7 | ED31: 0.7 | EE31: =EE36/DY26 -> 2.7017796 | EG31: 0.8 | EH31: 0.8 | EI31: 0.7 | EJ31: 0.6 | EK31: =EK36/EE26 -> 2.7927764 | EL31: 2.8 | FE31: =CI31 -> 0 | FF31: =CO31 -> 3.0070929 | FG31: =CU31 -> 2.8038251 | FH31: =DA31 -> 2.8960883 | FI31: =DG31 -> 3.0221596 | FJ31: =DM31 -> 3.026178 | FK31: =DS31 -> 3.0224124 | FL31: =DY31 -> 3.0016272 | FM31: =EE31 -> 2.7017796 | FN31: =EK31 -> 2.7927764 | FO31: =EL31 -> 2.8 | FP31: 2.8 | FQ31: 3 | FR31: 3
B32: IBM per installed system | CK32: =CK37/CE27 -> 0.78938619 | CL32: =CL37/CF27 -> 0.817375 | CM32: =CM37/CG27 -> 0.84200969 | CN32: =CN37/CH27 -> 0.8439483 | CO32: =CO37/CI27 -> 3.1549941 | CQ32: =CQ37/CK27 -> 0.61867125 | CR32: =CR37/CL27 -> 0.79766407 | CS32: =CS37/CM27 -> 0.7137149 | CT32: =CT37/CN27 -> 0.94837696 | CU32: =CU37/CO27 -> 2.9568586 | CW32: =CW37/CQ27 -> 0.87766393 | CX32: =CX37/CR27 -> 0.89066265 | CY32: =CY37/CS27 -> 0.8421875 | CZ32: =CZ37/CT27 -> 0.99322672 | DA32: =DA37/CU27 -> 3.444873 | DC32: =DC37/CW27 -> 1.1425532 | DD32: =DD37/CX27 -> 0.96886878 | DE32: =DE37/CY27 -> 1.000177 | DF32: =DF37/CZ27 -> 1.3101549 | DG32: =DG37/DA27 -> 4.2670396 | DI32: =DI37/DC27 -> 1.0454317 | DJ32: =DJ37/DD27 -> 1.0591133 | DK32: =DK37/DE27 -> 1.214992 | DL32: =DL37/DF27 -> 1.3091829 | DM32: =DM37/DG27 -> 4.4693385 | DO32: =DO37/DI27 -> 1.0753446 | DP32: =DP37/DJ27 -> 0.96803585 | DQ32: =DQ37/DK27 -> 0.99547775 | DR32: =DR37/DL27 -> 1.1056188 | DS32: =DS37/DM27 -> 3.9970839 | DU32: =DU37/DO27 -> 0.9144337 | DV32: =DV37/DP27 -> 0.98859239 | DW32: =DW37/DQ27 -> 0.99954604 | DX32: =DX37/DR27 -> 1.3553662 | DY32: =DY37/DS27 -> 4.0998737 | EA32: =EA37/DU27 -> 1.2390712 | EB32: =EB37/DV27 -> 1.2903941 | EC32: =EC37/DW27 -> 1.1728631 | ED32: =ED37/DX27 -> 1.237819 | EE32: =EE37/DY27 -> 4.7522622 | EG32: =EG37/EA27 -> 1.4109472 | EH32: =EH37/EB27 -> 1.3795531 | EI32: =EI37/EC27 -> 1.2044094 | EJ32: =EJ37/ED27 -> 1.1266949 | EK32: =EK37/EE27 -> 4.9240466 | EL32: =EL37/EK27 -> 5.077604 | FE32: =FE9/FE27 -> 3.1481786 | FF32: =FF9/FF27 -> 2.8114136 | FG32: =FG9/FG27 -> 2.656444 | FH32: =FH9/FH27 -> 3.1513769 | FI32: =FI9/FI27 -> 3.8585992 | FJ32: =FJ9/FJ27 -> 4.0847084 | FK32: =FK9/FK27 -> 3.5479167 | FL32: =FL9/FL27 -> 3.7669374 | ... FO32: =FO9/FO27 -> 4.5416491 | FP32: =FP37/FO27 -> 4.7154125 | FQ32: =FQ37/FP27 -> 13.184524 | FR32: =IFERROR(FR37/FQ27,"0") -> 0 | FU32: assume asymptotes in time to c.5k
B34: High NA IBM rev (2 yr warranty) | EG34: =DU24*EG29 -> 0 | EH34: =DV24*EH29 -> 0 | EI34: =DW24*EI29 -> 0 | EJ34: =DX24*EJ29 -> 0 | EK34: =SUM(EG34:EJ34) -> 0 | EL34: =EE24*EL29 -> 60 | FE34: =CI34 -> 0 | FF34: =CO34 -> 0 | FG34: =CU34 -> 0 | FH34: =DA34 -> 0 | FI34: =DG34 -> 0 | FJ34: =DM34 -> 0 | FK34: =DS34 -> 0 | FL34: =DY34 -> 0 | FM34: =EE34 -> 0 | FN34: =EK34 -> 0 | FO34: =EL34 -> 60 | FP34: =FO24*FP29 -> 225 | FQ34: =FP24*FQ29 -> 345 | FR34: =FQ24*FR29 -> 0
B35: Low NA IBM rev (1 yr warranty) | CK35: =CK37-CK36 -> 15.92 | CL35: =CL37-CL36 -> 40.04 | CM35: =CM37-CM36 -> 64.48 | CN35: =CN37-CN36 -> 71.58 | CO35: =CO37-CO36 -> 192.02 | CQ35: =CQ37-CQ36 -> 30.1 | CR35: =CR37-CR36 -> 108.8 | CS35: =CS37-CS36 -> 37.2 | CT35: =CT37-CT36 -> 82.2 | CU35: =CU37-CU36 -> 258.3 | CW35: =CW37-CW36 -> 204.2 | CX35: =CX37-CX36 -> 225.6 | CY35: =CY37-CY36 -> 186.2 | CZ35: =CZ37-CZ36 -> 158.5 | DA35: =DA37-DA36 -> 774.5 | DC35: =DC37-DC36 -> 424.7 | DD35: =DD37-DD36 -> 349.6 | DE35: =DE37-DE36 -> 401.5 | DF35: =DF37-DF36 -> 563.9 | DG35: =DG37-DG36 -> 1739.7 | DI35: =DI37-DI36 -> 484.9 | DJ35: =DJ37-DJ36 -> 516.5 | DK35: =DK37-DK36 -> 622.8 | DL35: =DL37-DL36 -> 650.9 | DM35: =DM37-DM36 -> 2275.1 | DO35: =DO37-DO36 -> 473.2 | DP35: =DP37-DP36 -> 466.7 | DQ35: =DQ37-DQ36 -> 521.3 | DR35: =DR37-DR36 -> 450.2 | DS35: =DS37-DS36 -> 1911.4 | DU35: =DU37-DU36 -> 447.7 | DV35: =DV37-DV36 -> 578.2 | DW35: =DW37-DW36 -> 615.2 | DX35: =DX37-DX36 -> 794.9 | DY35: =DY37-DY36 -> 2436 | EA35: =EA37-EA36 -> 1040.7 | EB35: =EB37-EB36 -> 1126.8 | EC35: =EC37-EC36 -> 966.8 | ED35: =ED37-ED36 -> 1111.3 | EE35: =EE37-EE36 -> 4245.6 | EG35: =EG37-EG36 -> 1298.7 | EH35: =EB25*EH30 -> 1255.8 | EI35: =EC25*EI30 -> 1124 | EJ35: =ED25*EJ30 -> 1172 | EK35: =SUM(EG35:EJ35) -> 4850.5 | EL35: =EK25*EL30 -> 5696 | FE35: =CI35 -> 0 | FF35: =CO35 -> 192.02 | FG35: =CU35 -> 258.3 | FH35: =DA35 -> 774.5 | FI35: =DG35 -> 1739.7 | FJ35: =DM35 -> 2275.1 | FK35: =DS35 -> 1911.4 | FL35: =DY35 -> 2436 | FM35: =EE35 -> 4245.6 | FN35: =EK35 -> 4850.5 | FO35: =EL35 -> 5696 | FP35: =FO25*FP30 -> 5500 | FQ35: =FP25*FQ30 -> 762.5 | FR35: =FQ25*FR30 -> 0
B36: ArF IBM rev (1 year warranty) | CK36: =CE26*CK31 -> 601.38 | CL36: =CF26*CL31 -> 613.86 | CM36: =CG26*CM31 -> 631.02 | CN36: =CH26*CN31 -> 646.62 | CO36: =SUM(CK36:CN36) -> 2492.88 | CQ36: =CK26*CQ31 -> 510 | CR36: =CL26*CR31 -> 608.3 | CS36: =CM26*CS31 -> 623.7 | CT36: =CN26*CT31 -> 823.5 | CU36: =SUM(CQ36:CT36) -> 2565.5 | CW36: =CQ26*CW31 -> 652.4 | CX36: =CR26*CX31 -> 661.5 | CY36: =CS26*CY31 -> 676.2 | CZ36: =CT26*CZ31 -> 897.3 | DA36: =SUM(CW36:CZ36) -> 2887.4 | DC36: =CW26*DC31 -> 810.4 | DD36: =CX26*DD31 -> 721 | DE36: =CY26*DE31 -> 728.7 | DF36: =CZ26*DF31 -> 958.5 | DG36: =SUM(DC36:DF36) -> 3218.6 | DI36: =DC26*DI31 -> 762.3 | DJ36: =DD26*DJ31 -> 773.5 | DK36: =DE26*DK31 -> 900.8 | DL36: =DF26*DL31 -> 1031.4 | DM36: =SUM(DI36:DL36) -> 3468 | DO36: =DI26*DO31 -> 931.2 | DP36: =DJ26*DP31 -> 829.5 | DQ36: =DK26*DQ31 -> 843.5 | DR36: =DL26*DR31 -> 1104.3 | DS36: =SUM(DO36:DR36) -> 3708.5 | DU36: =DO26*DU31 -> 876.4 | DV36: =DP26*DV31 -> 903.7 | DW36: =DQ26*DW31 -> 926.1 | DX36: =DR26*DX31 -> 1352 | DY36: =SUM(DU36:DX36) -> 4058.2 | EA36: =DU26*EA31 -> 960.4 | EB36: =DV26*EB31 -> 968.8 | EC36: =DW26*EC31 -> 995.4 | ED36: =DX26*ED31 -> 1022.7 | EE36: =SUM(EA36:ED36) -> 3947.3 | EG36: =EA26*EG31 -> 1188.8 | EH36: =EB26*EH31 -> 1213.6 | EI36: =EC26*EI31 -> 1088.5 | EJ36: =ED26*EJ31 -> 955.2 | EK36: =SUM(EG36:EJ36) -> 4446.1 | EL36: =EK26*EL31 -> 4797.8 | FE36: =CI36 -> 0 | FF36: =CO36 -> 2492.88 | FG36: =CU36 -> 2565.5 | FH36: =DA36 -> 2887.4 | FI36: =DG36 -> 3218.6 | FJ36: =DM36 -> 3468 | FK36: =DS36 -> 3708.5 | FL36: =DY36 -> 4058.2 | FM36: =EE36 -> 3947.3 | FN36: =EK36 -> 4446.1 | FO36: =EL36 -> 4797.8 | FP36: =FO26*FP31 -> 5232.5881 | FQ36: =FP26*FQ31 -> 0 | FR36: =FQ26*FR31 -> 0
B37: IBM revenue | K37: =K9 -> 52.545 | L37: =L9 -> 82.731 | M37: =M9 -> 74.161 | N37: =N9 -> 91.852 | O37: =K37+L37+M37+N37 -> 301.289 | Q37: =Q9 -> 76.289 | R37: =R9 -> 100.937 | S37: =S9 -> 101.877 | T37: =T9 -> 88.936 | U37: =Q37+R37+S37+T37 -> 368.039 | W37: =W9 -> 101.295 | X37: =X9 -> 104.405 | Y37: =Y9 -> 91.142 | Z37: =Z9 -> 120.063 | AA37: =W37+X37+Y37+Z37 -> 416.905 | AC37: =AC9 -> 99.222 | AD37: =AD9 -> 118.571 | AE37: =AE9 -> 105.77 | AF37: =AF9 -> 113.354 | AG37: =AC37+AD37+AE37+AF37 -> 436.917 | AI37: =AI9 -> 82.525 | AJ37: =AJ9 -> 93.341 | AK37: =AK9 -> 96.581 | AL37: =AL9 -> 148.758 | AM37: =AI37+AJ37+AK37+AL37 -> 421.205 | AO37: =AO9 -> 110.2 | AP37: =AP9 -> 145.7 | AQ37: =AQ9 -> 149 | AR37: =AR9 -> 208.3 | AS37: =AO37+AP37+AQ37+AR37 -> 613.2 | AU37: =AU9 -> 167.8 | AV37: =AV9 -> 195.8 | AW37: =AW9 -> 185.3 | AX37: =AX9 -> 218.2 | AY37: =AU37+AV37+AW37+AX37 -> 767.1 | BA37: =BA9 -> 201.9 | BB37: =BB9 -> 242.9 | BC37: =BC9 -> 228.5 | BD37: =BD9 -> 256.6 | BE37: =BA37+BB37+BC37+BD37 -> 929.9 | BG37: =BG9 -> 215.2 | BH37: =BH9 -> 271.2 | BI37: =BI9 -> 358.7 | BJ37: =BJ9 -> 407.1 | BK37: =BG37+BH37+BI37+BJ37 -> 1252.2 | BM37: =BM9 -> 366.5 | BN37: =BN9 -> 400.6 | BO37: =BO9 -> 437.7 | BP37: =BP9 -> 408.7 | BQ37: =BM37+BN37+BO37+BP37 -> 1613.5 | BS37: =BS9 -> 403.4 | BT37: =BT9 -> 519.6 | BU37: =BU9 -> 573.9 | BV37: =BV9 -> 553.3 | BW37: =BS37+BT37+BU37+BV37 -> 2050.2 | BY37: =BY9 -> 473.4 | BZ37: =BZ9 -> 474.2 | CA37: =CA9 -> 556.9 | CB37: =CB9 -> 618.3 | CC37: =BY37+BZ37+CA37+CB37 -> 2122.8 | CE37: =CE9 -> 727.8 | CF37: =CF9 -> 717.3 | CG37: =CG9 -> 628.5 | CH37: =CH9 -> 605.5 | CI37: =CE37+CF37+CG37+CH37 -> 2679.1 | CK37: =CK9 -> 617.3 | CL37: =CL9 -> 653.9 | CM37: =CM9 -> 695.5 | CN37: =CN9 -> 718.2 | CO37: =CK37+CL37+CM37+CN37 -> 2684.9 | CQ37: =CQ9 -> 540.1 | CR37: =CR9 -> 717.1 | CS37: =CS9 -> 660.9 | CT37: =CT9 -> 905.7 | CU37: =CQ37+CR37+CS37+CT37 -> 2823.8 | CW37: =CW9 -> 856.6 | CX37: =CX9 -> 887.1 | CY37: =CY9 -> 862.4 | CZ37: =CZ9 -> 1055.8 | DA37: =CW37+CX37+CY37+CZ37 -> 3661.9 | DC37: =DC9 -> 1235.1 | DD37: =DD9 -> 1070.6 | DE37: =DE9 -> 1130.2 | DF37: =DF9 -> 1522.4 | DG37: =DC37+DD37+DE37+DF37 -> 4958.3 | DI37: =DI9 -> 1247.2 | DJ37: =DJ9 -> 1290 | DK37: =DK9 -> 1523.6 | DL37: =DL9 -> 1682.3 | DM37: =DI37+DJ37+DK37+DL37 -> 5743.1 | DO37: =DO9 -> 1404.4 | DP37: =DP9 -> 1296.2 | DQ37: =DQ9 -> 1364.8 | DR37: =DR9 -> 1554.5 | DS37: =DO37+DP37+DQ37+DR37 -> 5619.9 | DT37: =DS37/DM37-1 -> -0.021451829 | DU37: =DU9 -> 1324.1 | DV37: =DV9 -> 1481.9 | DW37: =DW9 -> 1541.3 | DX37: =DX9 -> 2146.9 | DY37: =SUM(DU37:DX37) -> 6494.2 | DZ37: =DY37/DS37-1 -> 0.15557216 | EA37: =EA9 -> 2001.1 | EB37: =EB9 -> 2095.6 | EC37: =EC9 -> 1962.2 | ED37: =ED9 -> 2134 | EE37: =SUM(EA37:ED37) -> 8192.9 | EG37: =EG9 -> 2487.5 | EH37: =SUM(EH34:EH36) -> 2469.4 | EI37: =SUM(EI34:EI36) -> 2212.5 | EJ37: =SUM(EJ34:EJ36) -> 2127.2 | EK37: =SUM(EK34:EK36) -> 9296.6 | EL37: =SUM(EL34:EL36) -> 10553.8 | FA37: =BK37 -> 1252.2 | FB37: =BQ37 -> 1613.5 | FC37: =BW37 -> 2050.2 | FD37: =CC37 -> 2122.8 | FE37: =CI37 -> 2679.1 | FF37: =CO37 -> 2684.9 | FG37: =CU37 -> 2823.8 | FH37: =DA37 -> 3661.9 | FI37: =DG37 -> 4958.3 | FJ37: =DM37 -> 5743.1 | FK37: =DS37 -> 5619.9 | FL37: =DY37 -> 6494.2 | FM37: =EE37 -> 8192.9 | FN37: =FN27*FN32 -> 9296.6 | FO37: =FO27*FO32 -> 10553.8 | FP37: =SUM(FP34:FP36) -> 10957.588 | FQ37: =SUM(FQ34:FQ36) -> 1107.5 | FR37: =SUM(FR34:FR36) -> 0
B38: IBM y/y | CK38: =CK37/CE37-1 -> -0.15182743 | CL38: =CL37/CF37-1 -> -0.088387007 | CM38: =CM37/CG37-1 -> 0.10660302 | CN38: =CN37/CH37-1 -> 0.18612717 | CO38: =CO37/CI37-1 -> 0.0021649061 | CQ38: =CQ37/CK37-1 -> -0.12506075 | CR38: =CR37/CL37-1 -> 0.096650864 | CS38: =CS37/CM37-1 -> -0.049748382 | CT38: =CT37/CN37-1 -> 0.26106934 | CU38: =CU37/CO37-1 -> 0.05173377 | CW38: =CW37/CQ37-1 -> 0.58600259 | CX38: =CX37/CR37-1 -> 0.23706596 | CY38: =CY37/CS37-1 -> 0.30488727 | CZ38: =CZ37/CT37-1 -> 0.16572817 | DA38: =DA37/CU37-1 -> 0.29679864 | DC38: =DC37/CW37-1 -> 0.44186318 | DD38: =DD37/CX37-1 -> 0.20685379 | DE38: =DE37/CY37-1 -> 0.31052876 | DF38: =DF37/CZ37-1 -> 0.44193976 | DG38: =DG37/DA37-1 -> 0.35402387 | DI38: =DI37/DC37-1 -> 0.0097967776 | DJ38: =DJ37/DD37-1 -> 0.20493181 | DK38: =DK37/DE37-1 -> 0.34807999 | DL38: =DL37/DF37-1 -> 0.10503153 | DM38: =DM37/DG37-1 -> 0.15828006 | DO38: =DO37/DI37-1 -> 0.12604233 | DP38: =DP37/DJ37-1 -> 0.0048062016 | DQ38: =DQ37/DK37-1 -> -0.10422683 | DR38: =DR37/DL37-1 -> -0.075967426 | DS38: =DS37/DM37-1 -> -0.021451829 | DU38: =DU37/DO37-1 -> -0.057177442 | DV38: =DV37/DP37-1 -> 0.14326493 | DW38: =DW37/DQ37-1 -> 0.12932298 | DX38: =DX37/DR37-1 -> 0.38108717 | DY38: =DY37/DS37-1 -> 0.15557216 | EA38: =EA37/DU37-1 -> 0.51129069 | EB38: =EB37/DV37-1 -> 0.41413051 | EC38: =EC37/DW37-1 -> 0.27308117 | ED38: =ED37/DX37-1 -> -0.0060086637 | EE38: =EE37/DY37-1 -> 0.26157186 | EG38: =EG37/EA37-1 -> 0.24306631 | EH38: =EH37/EB37-1 -> 0.17837374 | EI38: =EI37/EC37-1 -> 0.1275609 | EJ38: =EJ37/ED37-1 -> -0.0031865042 | EK38: =EK37/EE37-1 -> 0.1347142 | EL38: =EL37/EK37-1 -> 0.13523224 | FM38: =FM37/FL37-1 -> 0.26157186 | FN38: =FN37/FM37-1 -> 0.1347142 | FO38: =FO37/FN37-1 -> 0.13523224 | FP38: =FP37/FO37-1 -> 0.038259976 | FQ38: =FQ37/FP37-1 -> -0.89892849 | FR38: =FR37/FQ37-1 -> -1
B39: IBM / System sales | K39: =K$37/K10 -> 0.07674388 | L39: =L$37/L10 -> 0.10839093 | M39: =M$37/M10 -> 0.13909891 | N39: =N$37/N10 -> 0.16765322 | O39: =O$37/O10 -> 0.1191352 | Q39: =Q$37/Q10 -> 0.12121101 | R39: =R$37/R10 -> 0.10717979 | S39: =S$37/S10 -> 0.10629538 | T39: =T$37/T10 -> 0.083310305 | U39: =U$37/U10 -> 0.10231536 | W39: =W$37/W10 -> 0.10548892 | X39: =X$37/X10 -> 0.11223665 | Y39: =Y$37/Y10 -> 0.097543382 | Z39: =Z$37/Z10 -> 0.12340899 | AA39: =AA$37/AA10 -> 0.10977754 | AC39: =AC$37/AC10 -> 0.10794292 | AD39: =AD$37/AD10 -> 0.14046084 | AE39: =AE$37/AE10 -> 0.15186082 | AF39: =AF$37/AF10 -> 0.22954518 | AG39: =AG$37/AG10 -> 0.14792303 | AI39: =AI$37/AI10 -> 0.44942138 | AJ39: =AJ$37/AJ10 -> 0.33745842 | AK39: =AK$37/AK10 -> 0.17393458 | AL39: =AL$37/AL10 -> 0.25622927 | AM39: =AM$37/AM10 -> 0.26390249 | AO39: =AO$37/AO10 -> 0.14855756 | AP39: =AP$37/AP10 -> 0.13633386 | AQ39: =AQ$37/AQ10 -> 0.12670068 | AR39: =AR$37/AR10 -> 0.13691337 | AS39: =AS$37/AS10 -> 0.13602786 | AU39: =AU$37/AU10 -> 0.11554882 | AV39: =AV$37/AV10 -> 0.12802406 | AW39: =AW$37/AW10 -> 0.12704834 | AX39: =AX$37/AX10 -> 0.18019655 | AY39: =AY$37/AY10 -> 0.13574589 | BA39: =BA$37/BA10 -> 0.16127486 | BB39: =BB$37/BB10 -> 0.19784964 | BC39: =BC$37/BC10 -> 0.18595378 | BD39: =BD$37/BD10 -> 0.25080637 | BE39: =BE$37/BE10 -> 0.19653387 | BG39: =BG$37/BG10 -> 0.24122856 | BH39: =BH$37/BH10 -> 0.22253221 | BI39: =BI$37/BI10 -> 0.25764976 | BJ39: =BJ$37/BJ10 -> 0.21177756 | BK39: =BK$37/BK10 -> 0.23080751 | BM39: =BM$37/BM10 -> 0.26244182 | BN39: =BN$37/BN10 -> 0.24373327 | BO39: =BO$37/BO10 -> 0.33103918 | BP39: =BP$37/BP10 -> 0.27356091 | BQ39: =BQ$37/BQ10 -> 0.27551526 | BS39: =BS$37/BS10 -> 0.24449967 | BT39: =BT$37/BT10 -> 0.31412853 | BU39: =BU$37/BU10 -> 0.37044926 | BV39: =BV$37/BV10 -> 0.38578999 | BW39: =BW$37/BW10 -> 0.32608073 | BY39: =BY$37/BY10 -> 0.35508551 | BZ39: =BZ$37/BZ10 -> 0.2725914 | CA39: =CA$37/CA10 -> 0.30689959 | CB39: =CB$37/CB10 -> 0.32415854 | CC39: =CC$37/CC10 -> 0.31241538 | CE39: =CE37/CE55 -> 0.59861819 | CF39: =CF37/CF55 -> 0.5182429 | CG39: =CG37/CG55 -> 0.34553851 | CH39: =CH37/CH55 -> 0.30973451 | CI39: =CI37/CI55 -> 0.4203367 | CK39: =CK37/CK55 -> 0.37015051 | CL39: =CL37/CL55 -> 0.31339564 | CM39: =CM37/CM55 -> 0.33427857 | CN39: =CN37/CN55 -> 0.29625046 | CO39: =CO37/CO55 -> 0.32508385 | CQ39: =CQ37/CQ55 -> 0.31977501 | CR39: =CR37/CR55 -> 0.38745407 | CS39: =CS37/CS55 -> 0.28418473 | CT39: =CT37/CT55 -> 0.28929632 | CU39: =CU37/CU55 -> 0.31389158 | CW39: =CW37/CW55 -> 0.54078283 | CX39: =CX37/CX55 -> 0.3637743 | CY39: =CY37/CY55 -> 0.27858896 | CZ39: =CZ37/CZ55 -> 0.33011287 | DA39: =DA37/DA55 -> 0.35495565 | DC39: =DC37/DC55 -> 0.39475198 | DD39: =DD37/DD55 -> 0.36296447 | DE39: =DE37/DE55 -> 0.27491426 | DF39: =DF37/DF55 -> 0.43959344 | DG39: =DG37/DG55 -> 0.36317358 | DI39: =DI37/DI55 -> 0.54529556 | DJ39: =DJ37/DJ55 -> 0.31155658 | DK39: =DK37/DK55 -> 0.3580981 | DL39: =DL37/DL55 -> 0.35432507 | DM39: =DM37/DM55 -> 0.37219626 | DO39: =DO37/DO55 -> 0.26290763 | DP39: =DP37/DP55 -> 0.23121243 | DQ39: =DQ37/DQ55 -> 0.25711164 | DR39: =DR37/DR55 -> 0.27355917 | DS39: =DS37/DS55 -> 0.25616493 | DU39: =DU37/DU55 -> 0.33387125 | DV39: =DV37/DV55 -> 0.31126468 | DW39: =DW37/DW55 -> 0.26009112 | DX39: =DX37/DX55 -> 0.30170463 | DY39: =DY37/DY55 -> 0.29832742 | EA39: =EA37/EA55 -> 0.3485994 | EB39: =EB37/EB55 -> 0.37447508 | EC39: =EC37/EC55 -> 0.35330765 | ED39: =ED37/ED55 -> 0.28138186 | EE39: =EE37/EE55 -> 0.33475419 | EG39: =EG37/EG55 -> 0.39616181 | EH39: =EH37/EH55 -> 0.42068143 | EI39: =EI37/EI55 -> 0.27900378 | EJ39: =EJ37/EJ55 -> 0.25635108 | EK39: =EK37/EK55 -> 0.32761045 | EL39: =EL37/EL55 -> 0.28174912 | FA39: =FA37/FA55 -> 0.31359094 | FB39: =FB37/FB55 -> 0.38029132 | FC39: =FC37/FC55 -> 0.48385726 | FD39: =FD37/FD55 -> 0.45436644 | FE39: =FE37/FE55 -> 0.4203367 | FF39: =FF37/FF55 -> 0.32508385 | FG39: =FG37/FG55 -> 0.31389158 | FH39: =FH37/FH55 -> 0.35495565 | ... FR39: =FR37/FR55 -> 0
A42: SYSTEM SALES - BY TECHNOLOGY | FA42: =FA$3 -> 2013 | FB42: =FB$3 -> 2014 | FC42: =FC$3 -> 2015 | FD42: =FD$3 -> 2016
B44: System Sales (EURm) - by technology | EE44: =4500/EE47 -> 0.4313819 | EL44: =4500/EL47 -> 0.22796353
B45: EUV - Hyper NA | FQ45: =FQ72*FQ85 -> 0 | FR45: =FR72*FR85 -> 1800 | FU45: Hyper NA
B46: EUV - High NA | DO46: =DO206 -> 0 | DP46: =DP206 -> 0 | DQ46: =DQ206 -> 0 | DR46: =DR206 -> 0 | DS46: =DO46+DP46+DQ46+DR46 -> 0 | DU46: =DU206 -> 0 | DV46: =DV206 -> 0 | DW46: =DW206 -> 0 | DX46: =DX206 -> 500 | DY46: =DU46+DV46+DW46+DX46 -> 500 | EA46: =EA206 -> 0 | EB46: =EB206 -> 250 | EC46: =EC206 -> 360 | ED46: =ED206 -> 610 | EE46: =SUM(EA46:ED46) -> 1220 | EG46: =EG206 -> 720 | EH46: =EH206 -> 0 | EI46: =EI206 -> 720 | EJ46: =EJ206 -> 720 | EK46: =SUM(EG46:EJ46) -> 2160 | EL46: =EL206 -> 2190 | FA46: =BK46 -> 0 | FB46: =BQ46 -> 0 | FC46: =BW46 -> 0 | FD46: =CC46 -> 0 | FE46: =CI46 -> 0 | FF46: =CO46 -> 0 | FG46: =CU46 -> 0 | FH46: =DA46 -> 0 | FI46: =DG46 -> 0 | FJ46: =DM46 -> 0 | FK46: =DS46 -> 0 | FL46: =DY46 -> 500 | FM46: =EE46 -> 1220 | FN46: =EK46 -> 2160 | FO46: =EL46 -> 2190 | FP46: =FP206 -> 2880 | FQ46: =FQ73*FQ86 -> 7700 | FR46: =FR73*FR86 -> 9600 | FU46: ASML won't recognise revenues until '2022' on first four R&D tools (€270m each)
B47: EUV - Low NA | AV47: =AV72*AV87 -> 0 | AW47: =AW55-SUM(AW49:AW52) -> 78.9384 | AX47: =AX55-SUM(AX49:AX52) -> 39.708 | AY47: =AU47+AV47+AW47+AX47 -> 118.6464 | BA47: =BA55-SUM(BA49:BA52) -> 42 | BE47: =BA47+BB47+BC47+BD47 -> 42 | BH47: =BH60*BH$55 -> 0 | BI47: =BI60*BI$55 -> 0 | BJ47: =BJ60*BJ$55 -> 57.648 | BK47: =BG47+BH47+BI47+BJ47 -> 57.648 | BM47: =BM60*BM$55 -> 61.8 | BN47: =BN60*BN$55 -> 62.15 | BO47: =BO60*BO$55 -> 123.83 | BP47: =BP60*BP$55 -> 65.118 | BQ47: =BM47+BN47+BO47+BP47 -> 312.898 | BS47: =BS60*BS$55 -> 0 | BT47: =BT60*BT$55 -> 68.07 | BU47: =BU60*BU$55 -> 0 | BV47: =BV60*BV$55 -> 0 | BW47: =BS47+BT47+BU47+BV47 -> 68.07 | BY47: =BY60*BY$55 -> 0 | BZ47: =BZ60*BZ$55 -> 101.232 | CA47: =CA60*CA$55 -> 88.039 | CB47: =CB60*CB$55 -> 141.801 | CC47: =BY47+BZ47+CA47+CB47 -> 331.072 | CE47: =CE60*CE$55 -> 0 | CF47: =CF60*CF$55 -> 221.456 | CG47: =CG60*CG$55 -> 381.969 | CH47: =CH60*CH$55 -> 488.725 | CI47: =CE47+CF47+CG47+CH47 -> 1092.15 | CK47: =CK60*CK$55 -> 116.739 | CL47: =CL60*CL$55 -> 667.68 | CM47: =CM60*CM$55 -> 520.15 | CN47: =CN60*CN$55 -> 581.832 | CO47: =CK47+CL47+CM47+CN47 -> 1886.401 | CQ47: =CQ60*CQ$55 -> 371.58 | CR47: =CR60*CR$55 -> 758.828 | CS47: =CS60*CS$55 -> 744.192 | CT47: =CT60*CT$55 -> 907.903 | CU47: =CQ47+CR47+CS47+CT47 -> 2782.503 | CW47: =CW60*CW$55 -> 348.48 | CX47: =CX60*CX$55 -> 951.054 | CY47: =CY60*CY$55 -> 2043.096 | CZ47: =CZ60*CZ$55 -> 1151.388 | DA47: =CW47+CX47+CY47+CZ47 -> 4494.018 | DC47: =DC60*DC$55 -> 1126.368 | DD47: =DD60*DD$55 -> 1327.32 | DE47: =DE60*DE$55 -> 2219.994 | DF47: =DF60*DF$55 -> 1593.072 | DG47: =DC47+DD47+DE47+DF47 -> 6266.754 | DI47: =DI60*DI$55 -> 594.672 | DJ47: =DJ60*DJ$55 -> 1987.44 | DK47: =DK60*DK$55 -> 2169.897 | DL47: =DL60*DL$55 -> 2326.471 | DM47: =DI47+DJ47+DK47+DL47 -> 7078.48 | DO47: =DO179 -> 2884.68 | DP47: =DP179 -> 2074.22 | DQ47: =DQ179 -> 1857.87 | DR47: =DR179 -> 2397.484 | DS47: =DO47+DP47+DQ47+DR47 -> 9214.254 | DT47: =DS47/DM47-1 -> 0.30172777 | DU47: =DU179 -> 1824.314 | DV47: =DV179 -> 1475.879 | DW47: =DW179 -> 2074.1 | DX47: =DX179 -> 2488.678 | DY47: =DU47+DV47+DW47+DX47 -> 7862.971 | EA47: =EA179 -> 3214.624 | EB47: =EB179 -> 2436.128 | EC47: =EC179 -> 1750.52 | ED47: =ED179 -> 3030.32 | EE47: =SUM(EA47:ED47) -> 10431.592 | EG47: =EG179 -> 3424.14 | EH47: =EH179 -> 3220 | EI47: =EI179 -> 3910 | EJ47: =EJ179 -> 4140 | EK47: =SUM(EG47:EJ47) -> 14694.14 | EL47: =EL179 -> 19740 | FA47: =BK47 -> 57.648 | FB47: =BQ47 -> 312.898 | FC47: =BW47 -> 68.07 | FD47: =CC47 -> 331.072 | FE47: =CI47 -> 1092.15 | FF47: =CO47 -> 1886.401 | FG47: =CU47 -> 2782.503 | FH47: =DA47 -> 4494.018 | FI47: =DG47 -> 6266.754 | FJ47: =DM47 -> 7078.48 | FK47: =DS47 -> 9214.254 | FL47: =DY47 -> 7862.971 | FM47: =EE47 -> 10431.592 | FN47: =EK47 -> 14694.14 | FO47: =EL47 -> 19740 | FP47: =FP179 -> 14335 | FQ47: =FQ74*FQ87 -> 13230 | FR47: =FR74*FR87 -> 13440
B48: Total EUV | CQ48: =SUM(CQ45:CQ47) -> 371.58 | CR48: =SUM(CR45:CR47) -> 758.828 | CS48: =SUM(CS45:CS47) -> 744.192 | CT48: =SUM(CT45:CT47) -> 907.903 | CU48: =SUM(CU45:CU47) -> 2782.503 | CW48: =SUM(CW45:CW47) -> 348.48 | CX48: =SUM(CX45:CX47) -> 951.054 | CY48: =SUM(CY45:CY47) -> 2043.096 | CZ48: =SUM(CZ45:CZ47) -> 1151.388 | DA48: =SUM(DA45:DA47) -> 4494.018 | DC48: =SUM(DC45:DC47) -> 1126.368 | DD48: =SUM(DD45:DD47) -> 1327.32 | DE48: =SUM(DE45:DE47) -> 2219.994 | DF48: =SUM(DF45:DF47) -> 1593.072 | DG48: =SUM(DG45:DG47) -> 6266.754 | DI48: =SUM(DI45:DI47) -> 594.672 | DJ48: =SUM(DJ45:DJ47) -> 1987.44 | DK48: =SUM(DK45:DK47) -> 2169.897 | DL48: =SUM(DL45:DL47) -> 2326.471 | DM48: =SUM(DM45:DM47) -> 7078.48 | DO48: =SUM(DO45:DO47) -> 2884.68 | DP48: =SUM(DP45:DP47) -> 2074.22 | DQ48: =SUM(DQ45:DQ47) -> 1857.87 | DR48: =SUM(DR45:DR47) -> 2397.484 | DS48: =SUM(DS45:DS47) -> 9214.254 | DU48: =SUM(DU45:DU47) -> 1824.314 | DV48: =SUM(DV45:DV47) -> 1475.879 | DW48: =SUM(DW45:DW47) -> 2074.1 | DX48: =SUM(DX45:DX47) -> 2988.678 | DY48: =SUM(DY45:DY47) -> 8362.971 | EA48: =SUM(EA45:EA47) -> 3214.624 | EB48: =SUM(EB45:EB47) -> 2686.128 | EC48: =SUM(EC45:EC47) -> 2110.52 | ED48: =SUM(ED45:ED47) -> 3640.32 | EE48: =SUM(EE45:EE47) -> 11651.592 | EG48: =SUM(EG45:EG47) -> 4144.14 | EH48: =SUM(EH45:EH47) -> 3220 | EI48: =SUM(EI45:EI47) -> 4630 | EJ48: =SUM(EJ45:EJ47) -> 4860 | EK48: =SUM(EK45:EK47) -> 16854.14 | EL48: =SUM(EL45:EL47) -> 21930 | FG48: =SUM(FG45:FG47) -> 2782.503 | FH48: =SUM(FH45:FH47) -> 4494.018 | FI48: =SUM(FI45:FI47) -> 6266.754 | FJ48: =SUM(FJ45:FJ47) -> 7078.48 | FK48: =SUM(FK45:FK47) -> 9214.254 | FL48: =SUM(FL45:FL47) -> 8362.971 | FM48: =SUM(FM45:FM47) -> 11651.592 | FN48: =SUM(FN45:FN47) -> 16854.14 | ... FR48: =SUM(FR45:FR47) -> 24840
B49: ArF Immersion | Y49: =Y$55*Y62 -> 337.2928 | Z49: =Z$55*Z62 -> 392.29904 | AA49: =W49+X49+Y49+Z49 -> 729.59184 | AC49: =AC$55*AC62 -> 418.19286 | AD49: =AD$55*AD62 -> 471.6309 | AE49: =AE$55*AE62 -> 454.85671 | AF49: =AF$55*AF62 -> 277.74018 | AG49: =AC49+AD49+AE49+AF49 -> 1622.4207 | AI49: =AI$55*AI62 -> 29.319 | AJ49: =AJ$55*AJ62 -> 163.10051 | AK49: =AK$55*AK62 -> 385.30044 | AL49: =AL$55*AL62 -> 302.2656 | AM49: =AI49+AJ49+AK49+AL49 -> 879.98555 | AO49: =AO$55*AO62 -> 524.228 | AP49: =AP$55*AP62 -> 784.55 | AQ49: =AQ$55*AQ62 -> 749.71 | AR49: =AR$55*AR62 -> 919.17 | AS49: =AO49+AP49+AQ49+AR49 -> 2977.658 | AU49: =AU$55*AU62 -> 911.924 | AV49: =AV$55*AV62 -> 920.184 | AW49: =AW$55*AW62 -> 901.4256 | AX49: =AX$55*AX62 -> 804.087 | AY49: =AU49+AV49+AW49+AX49 -> 3537.6206 | BA49: =BA62*BA$55 -> 588 | BB49: =BB62*BB$55 -> 709.056 | BC49: =BC62*BC$55 -> 830.249 | BD49: =BD62*BD$55 -> 582.54 | BE49: =BA49+BB49+BC49+BD49 -> 2709.845 | BG49: =BG62*BG$55 -> 500.906 | BH49: =BH62*BH$55 -> 714.09 | BI49: =BI62*BI$55 -> 844.36 | BJ49: =BJ62*BJ$55 -> 1066.488 | BK49: =BG49+BH49+BI49+BJ49 -> 3125.844 | BM49: =BM62*BM$55 -> 782.8 | BN49: =BN62*BN$55 -> 1131.13 | BO49: =BO62*BO$55 -> 636.84 | BP49: =BP62*BP$55 -> 900.799 | BQ49: =BM49+BN49+BO49+BP49 -> 3451.569 | BS49: =BS62*BS$55 -> 1034.595 | BT49: =BT62*BT$55 -> 896.255 | BU49: =BU62*BU$55 -> 663.204 | BV49: =BV62*BV$55 -> 634.248 | BW49: =BS49+BT49+BU49+BV49 -> 3228.302 | BY49: =BY62*BY$55 -> 679.242 | BZ49: =BZ62*BZ$55 -> 961.704 | CA49: =CA62*CA$55 -> 968.429 | CB49: =CB62*CB$55 -> 915.261 | CC49: =BY49+BZ49+CA49+CB49 -> 3524.636 | CE49: =CE62*CE$55 -> 899.692 | CF49: =CF62*CF$55 -> 885.824 | CG49: =CG62*CG$55 -> 1145.907 | CH49: =CH62*CH$55 -> 1094.744 | CI49: =CE49+CF49+CG49+CH49 -> 4026.167 | CK49: =CK62*CK$55 -> 1200.744 | CL49: =CL62*CL$55 -> 1022.385 | CM49: =CM62*CM$55 -> 1206.748 | CN49: =CN62*CN$55 -> 1381.851 | CO49: =CK49+CL49+CM49+CN49 -> 4811.728 | CQ49: =CQ62*CQ$55 -> 1013.4 | CR49: =CR62*CR$55 -> 758.828 | CS49: =CS62*CS$55 -> 1186.056 | CT49: =CT62*CT$55 -> 1753.192 | CU49: =CQ49+CR49+CS49+CT49 -> 4711.476 | CW49: =CW62*CW$55 -> 823.68 | CX49: =CX62*CX$55 -> 999.826 | CY49: =CY62*CY$55 -> 650.076 | CZ49: =CZ62*CZ$55 -> 1439.235 | DA49: =CW49+CX49+CY49+CZ49 -> 3912.817 | DC49: =DC62*DC$55 -> 1470.536 | DD49: =DD62*DD$55 -> 1002.864 | DE49: =DE62*DE$55 -> 1315.552 | DF49: =DF62*DF$55 -> 1212.12 | DG49: =DC49+DD49+DE49+DF49 -> 5001.072 | DI49: =DI62*DI$55 -> 1074.984 | DJ49: =DJ62*DJ$55 -> 1366.365 | DK49: =DK62*DK$55 -> 1318.957 | DL49: =DL62*DL$55 -> 1471.849 | DM49: =DI49+DJ49+DK49+DL49 -> 5232.155 | DO49: =DO62*DO$55 -> 1602.54 | DP49: =DP62*DP$55 -> 2746.989 | DQ49: =DQ62*DQ$55 -> 2547.936 | DR49: =DR62*DR$55 -> 2097.391 | DS49: =DO49+DP49+DQ49+DR49 -> 8994.856 | DU49: =DU62*DU$55 -> 1546.701 | DV49: =DV62*DV$55 -> 2380.45 | DW49: =DW62*DW$55 -> 2844.48 | DX49: =DX62*DX$55 -> 2917.519 | DY49: =DU49+DV49+DW49+DX49 -> 9689.15 | EA49: =EA62*EA$55 -> 1894.332 | EB49: =EB62*EB$55 -> 2406.323 | EC49: =EC62*EC$55 -> 2887.976 | ED49: =ED62*ED$55 -> 3033.6 | EG49: =EG62*EG$55 -> 1444.17 | FA49: =BK49 -> 3125.844 | FB49: =BQ49 -> 3451.569 | FC49: =BW49 -> 3228.302 | FD49: =CC49 -> 3524.636 | FE49: =CI49 -> 4026.167 | FF49: =CO49 -> 4811.728 | FG49: =CU49 -> 4711.476 | FH49: =DA49 -> 3912.817 | FI49: =DG49 -> 5001.072 | FJ49: =DM49 -> 5232.155 | FK49: =DS49 -> 8994.856 | FL49: =DY49 -> 9689.15 | FQ49: =FQ76*FQ89 -> 0 | FR49: =FR76*FR89 -> 0
B50: ArF dry | K50: =K$55*K63 -> 265.4967 | L50: =L$55*L63 -> 449.15244 | M50: =M$55*M63 -> 325.88432 | N50: =N$55*N63 -> 218.88816 | O50: =SUM(K50:N50) -> 1259.4216 | Q50: =Q$55*Q63 -> 276.5505 | R50: =R$55*R63 -> 487.67386 | S50: =S$55*S63 -> 548.19584 | T50: =T$55*T63 -> 685.0137 | U50: =SUM(Q50:T50) -> 1997.4339 | W50: =W$55*W63 -> 481.01088 | X50: =X$55*X63 -> 487.23203 | Y50: =Y$55*Y63 -> 286.69888 | Z50: =Z$55*Z63 -> 281.43192 | AA50: =W50+X50+Y50+Z50 -> 1536.3737 | AC50: =AC$55*AC63 -> 262.39552 | AD50: =AD$55*AD63 -> 188.65236 | AE50: =AE$55*AE63 -> 59.0723 | AF50: =AF$55*AF63 -> 72.28854 | AG50: =AC50+AD50+AE50+AF50 -> 582.40872 | AI50: =AI$55*AI63 -> 60.66 | AJ50: =AJ$55*AJ63 -> 16.49331 | AK50: =AK$55*AK63 -> 18.34764 | AL50: =AL$55*AL63 -> 38.86272 | AM50: =AI50+AJ50+AK50+AL50 -> 134.36367 | AO50: =AO$55*AO63 -> 31.58 | AP50: =AP$55*AP63 -> 27.69 | AQ50: =AQ$55*AQ63 -> 10.27 | AR50: =AR$55*AR63 -> 118.179 | AS50: =AO50+AP50+AQ50+AR50 -> 187.719 | AU50: =AU$55*AU63 -> 64.22 | AV50: =AV$55*AV63 -> 93.352 | AW50: =AW$55*AW63 -> 63.66 | AX50: =AX$55*AX63 -> 0 | AY50: =AU50+AV50+AW50+AX50 -> 221.232 | BA50: =BA63*BA$55 -> 63 | BB50: =BB63*BB$55 -> 0 | BC50: =BC63*BC$55 -> 0 | BD50: =BD63*BD$55 -> 22.995 | BE50: =BA50+BB50+BC50+BD50 -> 85.995 | BG50: =BG63*BG$55 -> 0 | BH50: =BH63*BH$55 -> 0 | BI50: =BI63*BI$55 -> 0 | BJ50: =BJ63*BJ$55 -> 43.236 | BK50: =BG50+BH50+BI50+BJ50 -> 43.236 | BM50: =BM63*BM$55 -> 0 | BN50: =BN63*BN$55 -> 12.43 | BO50: =BO63*BO$55 -> 0 | BP50: =BP63*BP$55 -> 10.853 | BQ50: =BM50+BN50+BO50+BP50 -> 23.283 | BS50: =BS63*BS$55 -> 37.395 | BT50: =BT63*BT$55 -> 11.345 | BU50: =BU63*BU$55 -> 29.259 | BV50: =BV63*BV$55 -> 26.427 | BW50: =BS50+BT50+BU50+BV50 -> 104.426 | BY50: =BY63*BY$55 -> 42.99 | BZ50: =BZ63*BZ$55 -> 37.962 | CA50: =CA63*CA$55 -> 25.154 | CB50: =CB63*CB$55 -> 25.782 | CC50: =BY50+BZ50+CA50+CB50 -> 131.888 | CE50: =CE63*CE$55 -> 60.79 | CF50: =CF63*CF$55 -> 41.523 | CG50: =CG63*CG$55 -> 36.378 | CH50: =CH63*CH$55 -> 78.196 | CI50: =CE50+CF50+CG50+CH50 -> 216.887 | CK50: =CK63*CK$55 -> 66.708 | CL50: =CL63*CL$55 -> 83.46 | CM50: =CM63*CM$55 -> 62.418 | CN50: =CN63*CN$55 -> 72.729 | CO50: =CK50+CL50+CM50+CN50 -> 285.315 | CQ50: =CQ63*CQ$55 -> 67.56 | CR50: =CR63*CR$55 -> 37.016 | CS50: =CS63*CS$55 -> 162.792 | CT50: =CT63*CT$55 -> 125.228 | CU50: =CQ50+CR50+CS50+CT50 -> 392.596 | CW50: =CW63*CW$55 -> 110.88 | CX50: =CX63*CX$55 -> 121.93 | CY50: =CY63*CY$55 -> 30.956 | CZ50: =CZ63*CZ$55 -> 127.932 | DA50: =CW50+CX50+CY50+CZ50 -> 391.698 | DC50: =DC63*DC$55 -> 62.576 | DD50: =DD63*DD$55 -> 147.48 | DE50: =DE63*DE$55 -> 123.333 | DF50: =DF63*DF$55 -> 103.896 | DG50: =DC50+DD50+DE50+DF50 -> 437.285 | DI50: =DI63*DI$55 -> 137.232 | DJ50: =DJ63*DJ$55 -> 165.62 | DK50: =DK63*DK$55 -> 127.641 | DL50: =DL63*DL$55 -> 189.916 | DM50: =DI50+DJ50+DK50+DL50 -> 620.409 | DO50: =DO63*DO$55 -> 160.254 | DP50: =DP63*DP$55 -> 112.122 | DQ50: =DQ63*DQ$55 -> 106.164 | DR50: =DR63*DR$55 -> 433.1879 | DS50: =DO50+DP50+DQ50+DR50 -> 811.7279 | DU50: =DU63*DU$55 -> 118.977 | DV50: =DV63*DV$55 -> 333.263 | DW50: =DW63*DW$55 -> 177.78 | DX50: =DX63*DX$55 -> 142.318 | DY50: =DU50+DV50+DW50+DX50 -> 772.338 | EA50: =EA63*EA$55 -> 114.808 | EB50: =EB63*EB$55 -> 111.922 | EC50: =EC63*EC$55 -> 111.076 | ED50: =ED63*ED$55 -> 151.68 | EG50: =EG63*EG$55 -> 125.58 | FA50: =BK50 -> 43.236 | FB50: =BQ50 -> 23.283 | FC50: =BW50 -> 104.426 | FD50: =CC50 -> 131.888 | FE50: =CI50 -> 216.887 | FF50: =CO50 -> 285.315 | FG50: =CU50 -> 392.596 | FH50: =DA50 -> 391.698 | FI50: =DG50 -> 437.285 | FJ50: =DM50 -> 620.409 | FK50: =DS50 -> 811.7279 | FL50: =DY50 -> 772.338 | FQ50: =FQ77*FQ90 -> 0 | FR50: =FR77*FR90 -> 0
B51: KrF | K51: =K$55*K64 -> 322.38885 | L51: =L$55*L64 -> 217.77088 | M51: =M$55*M64 -> 110.15808 | N51: =N$55*N64 -> 205.20765 | O51: =SUM(K51:N51) -> 855.52546 | Q51: =Q$55*Q64 -> 254.42646 | R51: =R$55*R64 -> 302.69412 | S51: =S$55*S64 -> 248.40124 | T51: =T$55*T64 -> 215.29002 | U51: =SUM(Q51:T51) -> 1020.8118 | W51: =W$55*W64 -> 292.04232 | X51: =X$55*X64 -> 256.00327 | Y51: =Y$55*Y64 -> 143.34944 | Z51: =Z$55*Z64 -> 127.9236 | AA51: =W51+X51+Y51+Z51 -> 819.31863 | AC51: =AC$55*AC64 -> 114.79804 | AD51: =AD$55*AD64 -> 36.2793 | AE51: =AE$55*AE64 -> 47.25784 | AF51: =AF$55*AF64 -> 22.82796 | AG51: =AC51+AD51+AE51+AF51 -> 221.16314 | AI51: =AI$55*AI64 -> 3.033 | AJ51: =AJ$55*AJ64 -> 0 | AK51: =AK$55*AK64 -> 45.8691 | AL51: =AL$55*AL64 -> 90.67968 | AM51: =AI51+AJ51+AK51+AL51 -> 139.58178 | AO51: =AO$55*AO64 -> 69.476 | AP51: =AP$55*AP64 -> 101.53 | AQ51: =AQ$55*AQ64 -> 256.75 | AR51: =AR$55*AR64 -> 249.489 | AS51: =AO51+AP51+AQ51+AR51 -> 677.245 | AU51: =AU$55*AU64 -> 295.412 | AV51: =AV$55*AV64 -> 306.728 | AW51: =AW$55*AW64 -> 203.712 | AX51: =AX$55*AX64 -> 138.978 | AY51: =AU51+AV51+AW51+AX51 -> 944.83 | BA51: =BA64*BA$55 -> 346.5 | BB51: =BB64*BB$55 -> 265.896 | BC51: =BC64*BC$55 -> 150.045 | BD51: =BD64*BD$55 -> 145.635 | BE51: =BA51+BB51+BC51+BD51 -> 908.076 | BG51: =BG64*BG$55 -> 155.687 | BH51: =BH64*BH$55 -> 183.1 | BI51: =BI64*BI$55 -> 105.545 | BJ51: =BJ64*BJ$55 -> 273.828 | BK51: =BG51+BH51+BI51+BJ51 -> 718.16 | BM51: =BM64*BM$55 -> 175.1 | BN51: =BN64*BN$55 -> 24.86 | BO51: =BO64*BO$55 -> 106.14 | BP51: =BP64*BP$55 -> 97.677 | BQ51: =BM51+BN51+BO51+BP51 -> 403.777 | BS51: =BS64*BS$55 -> 149.58 | BT51: =BT64*BT$55 -> 136.14 | BU51: =BU64*BU$55 -> 263.331 | BV51: =BV64*BV$55 -> 202.607 | BW51: =BS51+BT51+BU51+BV51 -> 751.658 | BY51: =BY64*BY$55 -> 120.372 | BZ51: =BZ64*BZ$55 -> 139.194 | CA51: =CA64*CA$55 -> 150.924 | CB51: =CB64*CB$55 -> 128.91 | CC51: =BY51+BZ51+CA51+CB51 -> 539.4 | CE51: =CE64*CE$55 -> 182.37 | CF51: =CF64*CF$55 -> 124.569 | CG51: =CG64*CG$55 -> 181.89 | CH51: =CH64*CH$55 -> 195.49 | CI51: =CE51+CF51+CG51+CH51 -> 684.319 | CK51: =CK64*CK$55 -> 233.478 | CL51: =CL64*CL$55 -> 208.65 | CM51: =CM64*CM$55 -> 187.254 | CN51: =CN64*CN$55 -> 242.43 | CO51: =CK51+CL51+CM51+CN51 -> 871.812 | CQ51: =CQ64*CQ$55 -> 152.01 | CR51: =CR64*CR$55 -> 203.588 | CS51: =CS64*CS$55 -> 139.536 | CT51: =CT64*CT$55 -> 187.842 | CU51: =CQ51+CR51+CS51+CT51 -> 682.976 | CW51: =CW64*CW$55 -> 205.92 | CX51: =CX64*CX$55 -> 243.86 | CY51: =CY64*CY$55 -> 247.648 | CZ51: =CZ64*CZ$55 -> 351.813 | DA51: =CW51+CX51+CY51+CZ51 -> 1049.241 | DC51: =DC64*DC$55 -> 344.168 | DD51: =DD64*DD$55 -> 324.456 | DE51: =DE64*DE$55 -> 287.777 | DF51: =DF64*DF$55 -> 346.32 | DG51: =DC51+DD51+DE51+DF51 -> 1302.721 | DI51: =DI64*DI$55 -> 274.464 | DJ51: =DJ64*DJ$55 -> 414.05 | DK51: =DK64*DK$55 -> 425.47 | DL51: =DL64*DL$55 -> 569.748 | DM51: =DI51+DJ51+DK51+DL51 -> 1683.732 | DO51: =DO64*DO$55 -> 480.762 | DP51: =DP64*DP$55 -> 504.549 | DQ51: =DQ64*DQ$55 -> 530.82 | DR51: =DR64*DR$55 -> 677.73 | DS51: =DO51+DP51+DQ51+DR51 -> 2193.861 | DU51: =DU64*DU$55 -> 317.272 | DV51: =DV64*DV$55 -> 428.481 | DW51: =DW64*DW$55 -> 592.6 | DX51: =DX64*DX$55 -> 640.431 | DY51: =DU51+DV51+DW51+DX51 -> 1978.784 | EA51: =EA64*EA$55 -> 287.02 | EB51: =EB64*EB$55 -> 223.844 | EC51: =EC64*EC$55 -> 166.614 | ED51: =ED64*ED$55 -> 379.2 | EG51: =EG64*EG$55 -> 376.74 | FA51: =BK51 -> 718.16 | FB51: =BQ51 -> 403.777 | FC51: =BW51 -> 751.658 | FD51: =CC51 -> 539.4 | FE51: =CI51 -> 684.319 | FF51: =CO51 -> 871.812 | FG51: =CU51 -> 682.976 | FH51: =DA51 -> 1049.241 | FI51: =DG51 -> 1302.721 | FJ51: =DM51 -> 1683.732 | FK51: =DS51 -> 2193.861 | FL51: =DY51 -> 1978.784 | FQ51: =FQ78*FQ91 -> 1037.5 | FR51: =FR78*FR91 -> 1100
B52: i-Line | K52: =K$55*K65 -> 44.24945 | L52: =L$55*L65 -> 13.61068 | M52: =M$55*M65 -> 22.9496 | N52: =N$55*N65 -> 31.92119 | O52: =SUM(K52:N52) -> 112.73092 | Q52: =Q$55*Q65 -> 22.12404 | R52: =R$55*R65 -> 50.44902 | S52: =S$55*S65 -> 59.95892 | T52: =T$55*T65 -> 78.28728 | U52: =SUM(Q52:T52) -> 210.81926 | W52: =W55-W51-W50-W49 -> 85.8948 | X52: =X55-X51-X50-X49 -> 82.5817 | Y52: =Y$55*Y65 -> 75.89088 | Z52: =Z$55*Z65 -> 51.16944 | AA52: =W52+X52+Y52+Z52 -> 295.53682 | AC52: =AC$55*AC65 -> 24.59958 | AD52: =AD$55*AD65 -> 29.02344 | AE52: =AE$55*AE65 -> 29.53615 | AF52: =AF$55*AF65 -> 7.60932 | AG52: =AC52+AD52+AE52+AF52 -> 90.76849 | AI52: =AI$55*AI65 -> 8.088 | AJ52: =AJ$55*AJ65 -> 3.66518 | AK52: =AK$55*AK65 -> 9.17382 | AL52: =AL$55*AL65 -> 0 | AM52: =AI52+AJ52+AK52+AL52 -> 20.927 | AO52: =AO$55*AO65 -> 6.316 | AP52: =AP$55*AP65 -> 9.23 | AQ52: =AQ$55*AQ65 -> 10.27 | AR52: =AR$55*AR65 -> 26.262 | AS52: =AO52+AP52+AQ52+AR52 -> 52.078 | AU52: =AU$55*AU65 -> 12.844 | AV52: =AV$55*AV65 -> 13.336 | AW52: =AW$55*AW65 -> 25.464 | AX52: =AX$55*AX65 -> 9.927 | AY52: =AU52+AV52+AW52+AX52 -> 61.571 | BA52: =BA65*BA$55 -> 10.5 | BB52: =BB65*BB$55 -> 9.848 | BC52: =BC65*BC$55 -> 20.006 | BD52: =BD65*BD$55 -> 15.33 | BE52: =BA52+BB52+BC52+BD52 -> 55.684 | BG52: =BG65*BG$55 -> 20.307 | BH52: =BH65*BH$55 -> 18.31 | BI52: =BI65*BI$55 -> 9.595 | BJ52: =BJ65*BJ$55 -> 0 | BK52: =BG52+BH52+BI52+BJ52 -> 48.212 | BM52: =BM65*BM$55 -> 10.3 | BN52: =BN65*BN$55 -> 12.43 | BO52: =BO65*BO$55 -> 17.69 | BP52: =BP65*BP$55 -> 10.853 | BQ52: =BM52+BN52+BO52+BP52 -> 51.273 | BS52: =BS65*BS$55 -> 24.93 | BT52: =BT65*BT$55 -> 22.69 | BU52: =BU65*BU$55 -> 19.506 | BV52: =BV65*BV$55 -> 17.618 | BW52: =BS52+BT52+BU52+BV52 -> 84.744 | BY52: =BY65*BY$55 -> 17.196 | BZ52: =BZ65*BZ$55 -> 25.308 | CA52: =CA65*CA$55 -> 25.154 | CB52: =CB65*CB$55 -> 12.891 | CC52: =BY52+BZ52+CA52+CB52 -> 80.549 | CE52: =CE65*CE$55 -> 12.158 | CF52: =CF65*CF$55 -> 27.682 | CG52: =CG65*CG$55 -> 18.189 | CH52: =CH65*CH$55 -> 19.549 | CI52: =CE52+CF52+CG52+CH52 -> 77.578 | CK52: =CK65*CK$55 -> 16.677 | CL52: =CL65*CL$55 -> 20.865 | CM52: =CM65*CM$55 -> 20.806 | CN52: =CN65*CN$55 -> 24.243 | CO52: =CK52+CL52+CM52+CN52 -> 82.591 | CQ52: =CQ65*CQ$55 -> 33.78 | CR52: =CR65*CR$55 -> 18.508 | CS52: =CS65*CS$55 -> 23.256 | CT52: =CT65*CT$55 -> 62.614 | CU52: =CQ52+CR52+CS52+CT52 -> 138.158 | CW52: =CW65*CW$55 -> 47.52 | CX52: =CX65*CX$55 -> 24.386 | CY52: =CY65*CY$55 -> 30.956 | CZ52: =CZ65*CZ$55 -> 31.983 | DA52: =CW52+CX52+CY52+CZ52 -> 134.845 | DC52: =DC65*DC$55 -> 31.288 | DD52: =DD65*DD$55 -> 29.496 | DE52: =DE65*DE$55 -> 41.111 | DF52: =DF65*DF$55 -> 34.632 | DG52: =DC52+DD52+DE52+DF52 -> 136.527 | DI52: =DI65*DI$55 -> 45.744 | DJ52: =DJ65*DJ$55 -> 41.405 | DK52: =DK65*DK$55 -> 42.547 | DL52: =DL65*DL$55 -> 47.479 | DM52: =DI52+DJ52+DK52+DL52 -> 177.175 | DO52: =DO65*DO$55 -> 53.418 | DP52: =DP65*DP$55 -> 56.061 | DQ52: =DQ65*DQ$55 -> 53.082 | DR52: =DR65*DR$55 -> 56.825 | DS52: =DO52+DP52+DQ52+DR52 -> 219.386 | DU52: =DU65*DU$55 -> 39.659 | DV52: =DV65*DV$55 -> 95.218 | DW52: =DW65*DW$55 -> 118.52 | DX52: =DX65*DX$55 -> 142.318 | DY52: =DU52+DV52+DW52+DX52 -> 395.715 | EA52: =EA65*EA$55 -> 57.404 | EB52: =EB65*EB$55 -> 55.961 | EC52: =EC65*EC$55 -> 55.538 | ED52: =ED65*ED$55 -> 75.84 | EG52: =EG65*EG$55 -> 62.79 | FA52: =BK52 -> 48.212 | FB52: =BQ52 -> 51.273 | FC52: =BW52 -> 84.744 | FD52: =CC52 -> 80.549 | FE52: =CI52 -> 77.578 | FF52: =CO52 -> 82.591 | FG52: =CU52 -> 138.158 | FH52: =DA52 -> 134.845 | FI52: =DG52 -> 136.527 | FJ52: =DM52 -> 177.175 | FK52: =DS52 -> 219.386 | FL52: =DY52 -> 395.715 | FQ52: =FQ79*FQ92 -> 0 | FR52: =FR79*FR92 -> 0
B53: Total DUV | CQ53: =SUM(CQ49:CQ52) -> 1266.75 | CR53: =SUM(CR49:CR52) -> 1017.94 | CS53: =SUM(CS49:CS52) -> 1511.64 | CT53: =SUM(CT49:CT52) -> 2128.876 | CU53: =SUM(CU49:CU52) -> 5925.206 | CW53: =SUM(CW49:CW52) -> 1188 | CX53: =SUM(CX49:CX52) -> 1390.002 | CY53: =SUM(CY49:CY52) -> 959.636 | CZ53: =SUM(CZ49:CZ52) -> 1950.963 | DA53: =SUM(DA49:DA52) -> 5488.601 | DC53: =SUM(DC49:DC52) -> 1908.568 | DD53: =SUM(DD49:DD52) -> 1504.296 | DE53: =SUM(DE49:DE52) -> 1767.773 | DF53: =SUM(DF49:DF52) -> 1696.968 | DG53: =SUM(DG49:DG52) -> 6877.605 | DI53: =SUM(DI49:DI52) -> 1532.424 | DJ53: =SUM(DJ49:DJ52) -> 1987.44 | DK53: =SUM(DK49:DK52) -> 1914.615 | DL53: =SUM(DL49:DL52) -> 2278.992 | DM53: =SUM(DM49:DM52) -> 7713.471 | DO53: =SUM(DO49:DO52) -> 2296.974 | DP53: =SUM(DP49:DP52) -> 3419.721 | DQ53: =SUM(DQ49:DQ52) -> 3238.002 | DR53: =SUM(DR49:DR52) -> 3265.1339 | DS53: =SUM(DS49:DS52) -> 12219.831 | DU53: =SUM(DU49:DU52) -> 2022.609 | DV53: =SUM(DV49:DV52) -> 3237.412 | DW53: =SUM(DW49:DW52) -> 3733.38 | DX53: =SUM(DX49:DX52) -> 3842.586 | DY53: =SUM(DY49:DY52) -> 12835.987 | EA53: =SUM(EA49:EA52) -> 2353.564 | EB53: =SUM(EB49:EB52) -> 2798.05 | EC53: =SUM(EC49:EC52) -> 3221.204 | ED53: =SUM(ED49:ED52) -> 3640.32 | EE53: =SUM(EA53:ED53) -> 12013.138 | EG53: =SUM(EG49:EG52) -> 2009.28 | EH53: =EH338 -> 2500 | EI53: =EI338 -> 3125 | EJ53: =EJ338 -> 3237.995 | EK53: =SUM(EG53:EJ53) -> 10872.275 | EL53: =EL338 -> 14678.148 | FE53: =CI53 -> 0 | FF53: =CO53 -> 0 | FG53: =CU53 -> 5925.206 | FH53: =DA53 -> 5488.601 | FI53: =DG53 -> 6877.605 | FJ53: =DM53 -> 7713.471 | FK53: =DS53 -> 12219.831 | FL53: =DY53 -> 12835.987 | FM53: =EE53 -> 12013.138 | FN53: =EK53 -> 10872.275 | FO53: =EL53 -> 14678.148 | FP53: =FP338 -> 12243.833 | FQ53: =FQ80*FQ93 -> 0 | FR53: =FR80*FR93 -> 0
B54: Metrology & Inspection | BY54: =BY67*BY$55 -> 0 | BZ54: =BZ67*BZ$55 -> 0 | CA54: =CA67*CA$55 -> 0 | CB54: =CB67*CB$55 -> 64.455 | CC54: =BY54+BZ54+CA54+CB54 -> 64.455 | CE54: =CE67*CE$55 -> 60.79 | CF54: =CF67*CF$55 -> 83.046 | CG54: =CG67*CG$55 -> 54.567 | CH54: =CH67*CH$55 -> 78.196 | CI54: =CE54+CF54+CG54+CH54 -> 276.599 | CK54: =CK67*CK$55 -> 33.354 | CL54: =CL67*CL$55 -> 83.46 | CM54: =CM67*CM$55 -> 83.224 | CN54: =CN67*CN$55 -> 121.215 | CO54: =CK54+CL54+CM54+CN54 -> 321.253 | CQ54: =CQ67*CQ$55 -> 50.67 | CR54: =CR67*CR$55 -> 74.032 | CS54: =CS67*CS$55 -> 69.768 | CT54: =CT67*CT$55 -> 93.921 | CU54: =CQ54+CR54+CS54+CT54 -> 288.391 | CW54: =CW67*CW$55 -> 47.52 | CX54: =CX67*CX$55 -> 97.544 | CY54: =CY67*CY$55 -> 92.868 | CZ54: =CZ67*CZ$55 -> 95.949 | DA54: =CW54+CX54+CY54+CZ54 -> 333.881 | DC54: =DC67*DC$55 -> 93.864 | DD54: =DD67*DD$55 -> 117.984 | DE54: =DE67*DE$55 -> 123.333 | DF54: =DF67*DF$55 -> 173.16 | DG54: =DC54+DD54+DE54+DF54 -> 508.341 | DI54: =DI67*DI$55 -> 160.104 | DJ54: =DJ67*DJ$55 -> 165.62 | DK54: =DK67*DK$55 -> 170.188 | DL54: =DL67*DL$55 -> 142.437 | DM54: =DI54+DJ54+DK54+DL54 -> 638.349 | DO54: =DO67*DO$55 -> 160.254 | DP54: =DP67*DP$55 -> 112.122 | DQ54: =DQ67*DQ$55 -> 212.328 | DR54: =DR67*DR$55 -> 19.8821 | DS54: =DO54+DP54+DQ54+DR54 -> 504.5861 | DT54: =SUM(DS49:DS54)/SUM(DM49:DM54)-1 -> 0.55267949 | DU54: =DU67*DU$55 -> 118.977 | DV54: =DV67*DV$55 -> 47.609 | DW54: =DW67*DW$55 -> 118.52 | DX54: =DX67*DX$55 -> 284.636 | DY54: =DU54+DV54+DW54+DX54 -> 569.742 | EA54: =EA67*EA$55 -> 172.212 | EB54: =EB67*EB$55 -> 111.922 | EC54: =EC67*EC$55 -> 222.152 | ED54: =ED67*ED$55 -> 303.36 | EE54: =SUM(EA54:ED54) -> 809.646 | EG54: =EG67*EG$55 -> 125.58 | EH54: 150 | EI54: 175 | EJ54: 200 | EK54: =SUM(EG54:EJ54) -> 650.58 | EL54: 850 | FA54: =BK54 -> 0 | FB54: =BQ54 -> 0 | FC54: =BW54 -> 0 | FD54: =CC54 -> 64.455 | FE54: =CI54 -> 276.599 | FF54: =CO54 -> 321.253 | FG54: =CU54 -> 288.391 | FH54: =DA54 -> 333.881 | FI54: =DG54 -> 508.341 | FJ54: =DM54 -> 638.349 | FK54: =DS54 -> 504.5861 | FL54: =DY54 -> 569.742 | FM54: =EE54 -> 809.646 | FN54: =EK54 -> 650.58 | FO54: =EL54 -> 850 | FP54: 880 | FQ54: 100 | FR54: 1100
B55: Total | K55: =K$8 -> 632.135 | L55: =L$8 -> 680.534 | M55: =M$8 -> 458.992 | N55: =N$8 -> 456.017 | O55: =SUM(O46:O54) -> 2227.678 | Q55: =Q$8 -> 553.101 | R55: =R$8 -> 840.817 | S55: =S$8 -> 856.556 | T55: =T$8 -> 978.591 | U55: =SUM(U46:U54) -> 3229.065 | W55: =W$8 -> 858.948 | X55: =X$8 -> 825.817 | Y55: =Y$8 -> 843.232 | Z55: =Z$8 -> 852.824 | AA55: =SUM(AA46:AA54) -> 3380.821 | AC55: =AC$8 -> 819.986 | AD55: =AD$8 -> 725.586 | AE55: =AE$8 -> 590.723 | AF55: =AF$8 -> 380.466 | AG55: =SUM(AG46:AG54) -> 2516.761 | AI55: =AI$8 -> 101.1 | AJ55: =AJ$8 -> 183.259 | AK55: =AK$8 -> 458.691 | AL55: =AL$8 -> 431.808 | AM55: =SUM(AM46:AM54) -> 1174.858 | AO55: =AO$8 -> 631.6 | AP55: =AP$8 -> 923 | AQ55: =AQ$8 -> 1027 | AR55: =AR$8 -> 1313.1 | AS55: =SUM(AS46:AS54) -> 3894.7 | AU55: =AU$8 -> 1284.4 | AV55: =AV$8 -> 1333.6 | AW55: =AW$8 -> 1273.2 | AX55: =AX$8 -> 992.7 | AY55: =SUM(AY46:AY54) -> 4883.9 | BA55: =BA$8 -> 1050 | BB55: =BB$8 -> 984.8 | BC55: =BC$8 -> 1000.3 | BD55: =BD$8 -> 766.5 | BE55: =SUM(BE46:BE54) -> 3801.6 | BG55: =BG$8 -> 676.9 | BH55: =BH$8 -> 915.5 | BI55: =BI$8 -> 959.5 | BJ55: =BJ$8 -> 1441.2 | BK55: =SUM(BK46:BK54) -> 3993.1 | BM55: =BM$8 -> 1030 | BN55: =BN$8 -> 1243 | BO55: =BO$8 -> 884.5 | BP55: =BP$8 -> 1085.3 | BQ55: =SUM(BQ46:BQ54) -> 4242.8 | BS55: =BS$8 -> 1246.5 | BT55: =BT$8 -> 1134.5 | BU55: =BU$8 -> 975.3 | BV55: =BV$8 -> 880.9 | BW55: =SUM(BW46:BW54) -> 4237.2 | BY55: =BY$8 -> 859.8 | BZ55: =BZ$8 -> 1265.4 | CA55: =CA$8 -> 1257.7 | CB55: =CB$8 -> 1289.1 | CC55: =SUM(CC46:CC54) -> 4672 | CE55: =CE8 -> 1215.8 | CF55: =CF8 -> 1384.1 | CG55: =CG8 -> 1818.9 | CH55: =CH8 -> 1954.9 | CI55: =SUM(CI46:CI54) -> 6373.7 | CK55: =CK8 -> 1667.7 | CL55: =CL8 -> 2086.5 | CM55: =CM8 -> 2080.6 | CN55: =CN8 -> 2424.3 | CO55: =SUM(CO46:CO54) -> 8259.1 | CQ55: =CQ8 -> 1689 | CR55: =CR8 -> 1850.8 | CS55: =CS8 -> 2325.6 | CT55: =CT8 -> 3130.7 | CU55: =CU8 -> 8996.1 | CW55: =CW8 -> 1584 | CX55: =CX8 -> 2438.6 | CY55: =CY8 -> 3095.6 | CZ55: =CZ8 -> 3198.3 | DA55: =DA8 -> 10316.5 | DC55: =DC8 -> 3128.8 | DD55: =DD8 -> 2949.6 | DE55: =DE8 -> 4111.1 | DF55: =DF8 -> 3463.2 | DG55: =DG8 -> 13652.7 | DI55: =DI8 -> 2287.2 | DJ55: =DJ8 -> 4140.5 | DK55: =DK8 -> 4254.7 | DL55: =DL8 -> 4747.9 | DM55: =DM8 -> 15430.3 | DO55: =DO8 -> 5341.8 | DP55: =DP8 -> 5606.1 | DQ55: =DQ8 -> 5308.2 | DR55: =DR8 -> 5682.5 | DS55: =DS8 -> 21938.6 | DT55: =DS55/DM55-1 -> 0.421787 | DU55: =DU8 -> 3965.9 | DV55: =DV8 -> 4760.9 | DW55: =DW8 -> 5926 | DX55: =DX8 -> 7115.9 | DY55: =DY8 -> 21768.7 | EA55: =EA8 -> 5740.4 | EB55: =EB8 -> 5596.1 | EC55: =EC8 -> 5553.8 | ED55: =ED8 -> 7584 | EE55: =SUM(EE48,EE53:EE54) -> 24474.376 | EG55: =EG8 -> 6279 | EH55: =SUM(EH48,EH53:EH54) -> 5870 | EI55: =SUM(EI48,EI53:EI54) -> 7930 | EJ55: =SUM(EJ48,EJ53:EJ54) -> 8297.995 | EK55: =SUM(EK48,EK53:EK54) -> 28376.995 | EL55: =SUM(EL48,EL53:EL54) -> 37458.148 | FA55: =SUM(FA45:FA54) -> 3993.1 | FB55: =SUM(FB45:FB54) -> 4242.8 | FC55: =SUM(FC45:FC54) -> 4237.2 | FD55: =SUM(FD45:FD54) -> 4672 | FE55: =SUM(FE45:FE54) -> 6373.7 | FF55: =SUM(FF45:FF54) -> 8259.1 | FG55: =SUM(FG48,FG53:FG54) -> 8996.1 | FH55: =SUM(FH48,FH53:FH54) -> 10316.5 | FI55: =SUM(FI48,FI53:FI54) -> 13652.7 | FJ55: =SUM(FJ48,FJ53:FJ54) -> 15430.3 | FK55: =SUM(FK48,FK53:FK54) -> 21938.671 | FL55: =SUM(FL48,FL53:FL54) -> 21768.7 | FM55: =SUM(FM48,FM53:FM54) -> 24474.376 | FN55: =SUM(FN48,FN53:FN54) -> 28376.995 | ... FR55: =SUM(FR48,FR53:FR54) -> 25940
B56: check: | CE56: =CE55-CE8 -> 0 | CF56: =CF55-CF8 -> 0 | CG56: =CG55-CG8 -> 0 | CH56: =CH55-CH8 -> 0 | CK56: =CK55-CK8 -> 0 | CL56: =CL55-CL8 -> 0 | CM56: =CM55-CM8 -> 0 | CN56: =CN55-CN8 -> 0 | CQ56: =CQ55-CQ8 -> 0 | CR56: =CR55-CR8 -> 0 | CS56: =CS55-CS8 -> 0 | CT56: =CT55-CT8 -> 0 | CW56: =CW55-CW8 -> 0 | CX56: =CX55-CX8 -> 0 | CY56: =CY55-CY8 -> 0 | CZ56: =CZ55-CZ8 -> 0 | DC56: =DC55-DC8 -> 0 | DD56: =DD55-DD8 -> 0 | DE56: =DE55-DE8 -> 0 | DF56: =DF55-DF8 -> 0 | DI56: =DI55-DI8 -> 0 | DJ56: =DJ55-DJ8 -> 0 | DK56: =DK55-DK8 -> 0 | DL56: =DL55-DL8 -> 0 | DM56: =DM55-DM8 -> 0 | DO56: =SUM(DO46:DO47,DO49:DO52,DO54)-DO55 -> 0.108 | DP56: =SUM(DP46:DP47,DP49:DP52,DP54)-DP55 -> -0.037 | DQ56: =SUM(DQ46:DQ47,DQ49:DQ52,DQ54)-DQ55 -> 0 | DR56: =SUM(DR46:DR47,DR49:DR52,DR54)-DR55 -> 0 | DS56: =DS55-DS8 -> 0 | DU56: =DU55-DU8 -> 0 | DV56: =DV55-DV8 -> 0 | DW56: =DW55-DW8 -> 0 | DX56: =DX55-DX8 -> 0 | DY56: =DY55-DY8 -> 0 | EA56: =EA55-EA8 -> 0 | EB56: =EB55-EB8 -> 0 | EC56: =EC55-EC8 -> 0 | ED56: =ED55-ED8 -> 0 | EE56: =EE55-EE8 -> 0.076 | EG56: =EG55-EG8 -> 0 | EH56: =EH55-EH8 -> 0 | EI56: =EI55-EI8 -> 0 | EJ56: =EJ55-EJ8 -> 0 | EK56: =EK55-EK8 -> 0 | EL56: =EL55-EL8 -> 0 | FA56: =FA55-FA8 -> 0 | FB56: =FB55-FB8 -> 0 | FC56: =FC55-FC8 -> 0 | FD56: =FD55-FD8 -> 0 | FE56: =FE55-FE8 -> 0 | FF56: =FF55-FF8 -> 0 | FG56: =FG55-FG8 -> 0 | FH56: =FH55-FH8 -> 0 | ... FR56: =FR55-FR8 -> 0
B57: % split
B58: EUV - Hyper NA | FQ58: =FQ45/FQ$55 -> 0 | FR58: =FR45/FR$55 -> 0.069390902
B59: EUV - High NA | CQ59: =CQ46/CQ$55 -> 0 | CR59: =CR46/CR$55 -> 0 | CS59: =CS46/CS$55 -> 0 | CT59: =CT46/CT$55 -> 0 | CU59: =CU46/CU$55 -> 0 | CW59: =CW46/CW$55 -> 0 | CX59: =CX46/CX$55 -> 0 | CY59: =CY46/CY$55 -> 0 | CZ59: =CZ46/CZ$55 -> 0 | DA59: =DA46/DA$55 -> 0 | DC59: =DC46/DC$55 -> 0 | DD59: =DD46/DD$55 -> 0 | DE59: =DE46/DE$55 -> 0 | DF59: =DF46/DF$55 -> 0 | DG59: =DG46/DG$55 -> 0 | DI59: =DI46/DI$55 -> 0 | DJ59: =DJ46/DJ$55 -> 0 | DK59: =DK46/DK$55 -> 0 | DL59: =DL46/DL$55 -> 0 | DM59: =DM46/DM$55 -> 0 | DO59: =DO46/DO$55 -> 0 | DP59: =DP46/DP$55 -> 0 | DQ59: =DQ46/DQ$55 -> 0 | DR59: =DR46/DR$55 -> 0 | DS59: =DS46/DS$55 -> 0 | DU59: =DU46/DU$55 -> 0 | DV59: =DV46/DV$55 -> 0 | DW59: =DW46/DW$55 -> 0 | DX59: =DX46/DX$55 -> 0.070265181 | DY59: =DY46/DY$55 -> 0.022968758 | EA59: =EA46/EA$55 -> 0 | EB59: =EB46/EB$55 -> 0.044673969 | EC59: =EC46/EC$55 -> 0.064820483 | ED59: =ED46/ED$55 -> 0.080432489 | EE59: =EE46/EE55 -> 0.049848053 | EG59: =EG46/EG55 -> 0.11466794 | EH59: =EH46/EH55 -> 0 | EI59: =EI46/EI55 -> 0.090794451 | EJ59: =EJ46/EJ55 -> 0.086767948 | EK59: =EK46/EK55 -> 0.076117996 | EL59: =EL46/EL55 -> 0.058465251 | FJ59: =FJ46/FJ$55 -> 0 | FK59: =FK46/FK$55 -> 0 | FL59: =FL46/FL$55 -> 0.022968758 | FM59: =FM46/FM$55 -> 0.049848053 | FN59: =FN46/FN$55 -> 0.076117996 | FO59: =FO46/FO$55 -> 0.058465251 | FP59: =FP46/FP55 -> 0.094927844 | FQ59: =FQ46/FQ$55 -> 0.3661436 | FR59: =FR46/FR$55 -> 0.37008481
B60: EUV - Low NA | AW60: =AW47/AW55 -> 0.062 | AX60: =AX47/AX55 -> 0.04 | AY60: =AY47/AY$55 -> 0.024293372 | BA60: =BA47/BA55 -> 0.04 | BB60: =BB47/BB$55 -> 0 | BC60: =BC47/BC$55 -> 0 | BD60: =BD47/BD$55 -> 0 | BE60: =BE47/BE$55 -> 0.01104798 | BG60: =BG47/BG$55 -> 0 | BH60: =BH47/BH$55 -> 0 | BI60: =BI47/BI$55 -> 0 | BJ60: 0.04 | BK60: =BK47/BK$55 -> 0.014436904 | BM60: 0.06 | BN60: 0.05 | BO60: 0.14 | BP60: 0.06 | BQ60: =BQ47/BQ$55 -> 0.073747997 | BS60: 0 | BT60: 0.06 | BU60: 0 | BV60: 0 | BW60: =BW47/BW$55 -> 0.016064854 | BY60: 0 | BZ60: 0.08 | CA60: 0.07 | CB60: 0.11 | CC60: =CC47/CC$55 -> 0.070863014 | CE60: 0 | CF60: 0.16 | CG60: 0.21 | CH60: 0.25 | CI60: =CI47/CI55 -> 0.17135259 | CK60: 0.07 | CL60: 0.32 | CM60: 0.25 | CN60: 0.24 | CO60: =CO47/CO55 -> 0.22840273 | CQ60: 0.22 | CR60: 0.41 | CS60: 0.32 | CT60: 0.29 | CU60: 0 | CW60: 0.22 | CX60: 0.39 | CY60: 0.66 | CZ60: 0.36 | DA60: 0 | DC60: 0.36 | DD60: 0.45 | DE60: 0.54 | DF60: 0.46 | DG60: 0 | DI60: 0.26 | DJ60: 0.48 | DK60: 0.51 | DL60: 0.49 | DM60: 0 | DO60: 0.54 | DP60: 0.37 | DQ60: 0.35 | DR60: 0.42190656 | DS60: 0.42 | DU60: 0.46 | DV60: 0.31 | DW60: 0.35 | DX60: 0.34973482 | DY60: 0.35703124 | EA60: 0.56 | EB60: 0.43532603 | EC60: 0.31517952 | ED60: 0.39956751 | EE60: =EE47/EE55 -> 0.42622504 | EG60: =EG47/EG55 -> 0.54533206 | EH60: =EH47/EH55 -> 0.54855196 | EI60: =EI47/EI55 -> 0.49306431 | EJ60: =EJ47/EJ55 -> 0.4989157 | EK60: =EK47/EK55 -> 0.51781875 | EL60: =EL47/EL55 -> 0.52698815 | FA60: =FA47/FA$55 -> 0.014436904 | FB60: =FB47/FB$55 -> 0.073747997 | FC60: =FC47/FC$55 -> 0.016064854 | FD60: =FD47/FD$55 -> 0.070863014 | FE60: =FE47/FE$55 -> 0.17135259 | FF60: =FF47/FF$55 -> 0.22840273 | FG60: =FG47/FG$55 -> 0.30930103 | FH60: =FH47/FH$55 -> 0.4356146 | ... FO60: =FO47/FO$55 -> 0.52698815 | FP60: =FP47/FP55 -> 0.47249675 | FQ60: =FQ47/FQ$55 -> 0.62910128 | FR60: =FR47/FR$55 -> 0.51811874
B61: Total EUV | CQ61: =CQ48/CQ55 -> 0.22 | CR61: =CR48/CR55 -> 0.41 | CS61: =CS48/CS55 -> 0.32 | CT61: =CT48/CT55 -> 0.29 | CU61: =CU48/CU55 -> 0.30930103 | CW61: =CW48/CW55 -> 0.22 | CX61: =CX48/CX55 -> 0.39 | CY61: =CY48/CY55 -> 0.66 | CZ61: =CZ48/CZ55 -> 0.36 | DA61: =DA48/DA55 -> 0.4356146 | DC61: =DC48/DC55 -> 0.36 | DD61: =DD48/DD55 -> 0.45 | DE61: =DE48/DE55 -> 0.54 | DF61: =DF48/DF55 -> 0.46 | DG61: =DG48/DG55 -> 0.45901206 | DI61: =DI48/DI55 -> 0.26 | DJ61: =DJ48/DJ55 -> 0.48 | DK61: =DK48/DK55 -> 0.51 | DL61: =DL48/DL55 -> 0.49 | DM61: =DM48/DM55 -> 0.45873897 | DO61: =DO48/DO55 -> 0.54002022 | DP61: =DP48/DP55 -> 0.3699934 | DQ61: =DQ48/DQ55 -> 0.35 | DR61: =DR48/DR55 -> 0.42190656 | DS61: =DS48/DS55 -> 0.42000191 | DU61: =DU48/DU55 -> 0.46 | DV61: =DV48/DV55 -> 0.31 | DW61: =DW48/DW55 -> 0.35 | DX61: =DX48/DX55 -> 0.42 | DY61: =DY48/DY55 -> 0.38417411 | EA61: =EA48/EA55 -> 0.56 | EB61: =EB48/EB55 -> 0.48 | EC61: =EC48/EC55 -> 0.38001368 | ED61: =ED48/ED55 -> 0.48 | EE61: =EE48/EE55 -> 0.4760731 | EG61: =EG48/EG55 -> 0.66 | EH61: =EH48/EH55 -> 0.54855196 | EI61: =EI48/EI55 -> 0.58385876 | EJ61: =EJ48/EJ55 -> 0.58568365 | EK61: =EK48/EK55 -> 0.59393674 | EL61: =EL48/EL55 -> 0.5854534 | FP61: =FP48/FP55 -> 0.56742459
B62: ArF Immersion | W62: 0.02 | X62: 0.02 | Y62: 0.4 | Z62: 0.46 | AA62: =AA49/AA$55 -> 0.21580316 | AC62: 0.51 | AD62: 0.65 | AE62: 0.77 | AF62: 0.73 | AG62: =AG49/AG$55 -> 0.64464629 | AI62: 0.29 | AJ62: 0.89 | AK62: 0.84 | AL62: 0.7 | AM62: =AM49/AM$55 -> 0.74901439 | AO62: =100%-AO63-AO64-AO65 -> 0.83 | AP62: 0.85 | AQ62: 0.73 | AR62: 0.7 | AS62: =AS49/AS$55 -> 0.76454104 | AU62: 0.71 | AV62: 0.69 | AW62: 0.708 | AX62: 0.81 | AY62: =AY49/AY$55 -> 0.72434337 | BA62: 0.56 | BB62: 0.72 | BC62: 0.83 | BD62: 0.76 | BE62: =BE49/BE$55 -> 0.71281697 | BG62: 0.74 | BH62: 0.78 | BI62: 0.88 | BJ62: 0.74 | BK62: =BK49/BK$55 -> 0.78281135 | BM62: 0.76 | BN62: 0.91 | BO62: 0.72 | BP62: 0.83 | BQ62: =BQ49/BQ$55 -> 0.81351207 | BS62: 0.83 | BT62: 0.79 | BU62: 0.68 | BV62: 0.72 | BW62: =BW49/BW$55 -> 0.76189512 | BY62: 0.79 | BZ62: 0.76 | CA62: 0.77 | CB62: 0.71 | CC62: =CC49/CC$55 -> 0.75441695 | CE62: 0.74 | CF62: 0.64 | CG62: 0.63 | CH62: 0.56 | CI62: =CI49/CI$55 -> 0.63168442 | CK62: 0.72 | CL62: 0.49 | CM62: 0.58 | CN62: 0.57 | CO62: =CO49/CO$55 -> 0.58259714 | CQ62: 0.6 | CR62: 0.41 | CS62: 0.51 | CT62: 0.56 | CU62: 0 | CW62: 0.52 | CX62: 0.41 | CY62: 0.21 | CZ62: 0.45 | DA62: 0 | DC62: 0.47 | DD62: 0.34 | DE62: 0.32 | DF62: 0.35 | DG62: 0 | DI62: 0.47 | DJ62: 0.33 | DK62: 0.31 | DL62: 0.31 | DM62: 0 | DO62: 0.3 | DP62: 0.49 | DQ62: 0.48 | DR62: 0.36909652 | DS62: 0.41 | DU62: 0.39 | DV62: 0.5 | DW62: 0.48 | DX62: 0.41 | DY62: 0.44 | EA62: 0.33 | EB62: 0.43 | EC62: 0.52 | ED62: 0.4 | EG62: 0.23 | FA62: =FA49/FA$55 -> 0.78281135 | FB62: =FB49/FB$55 -> 0.81351207 | FC62: =FC49/FC$55 -> 0.76189512 | FD62: =FD49/FD$55 -> 0.75441695 | FE62: =FE49/FE$55 -> 0.63168442 | FF62: =FF49/FF$55 -> 0.58259714 | FG62: =FG49/FG$55 -> 0.52372428 | FH62: =FH49/FH$55 -> 0.37927757 | ... FO62: =FO49/FO$55 -> 0 | FQ62: =FQ49/FQ$55 -> 0 | FR62: =FR49/FR$55 -> 0
B63: ArF dry | K63: 0.42 | L63: 0.66 | M63: 0.71 | N63: 0.48 | O63: =O50/O$55 -> 0.56535173 | Q63: 0.5 | R63: 0.58 | S63: 0.64 | T63: 0.7 | U63: =U50/U$55 -> 0.61857965 | W63: 0.56 | X63: 0.59 | Y63: 0.34 | Z63: 0.33 | AA63: =AA50/AA$55 -> 0.45443805 | AC63: 0.32 | AD63: 0.26 | AE63: 0.1 | AF63: 0.19 | AG63: =AG50/AG$55 -> 0.23141201 | AI63: 0.6 | AJ63: 0.09 | AK63: 0.04 | AL63: 0.09 | AM63: =AM50/AM$55 -> 0.11436588 | AO63: 0.05 | AP63: 0.03 | AQ63: 0.01 | AR63: 0.09 | AS63: =AS50/AS$55 -> 0.048198578 | AU63: 0.05 | AV63: 0.07 | AW63: 0.05 | AX63: 0 | AY63: =AY50/AY$55 -> 0.045298225 | BA63: 0.06 | BB63: 0 | BC63: 0 | BD63: 0.03 | BE63: =BE50/BE$55 -> 0.022620739 | BG63: 0 | BH63: 0 | BI63: =BI50/BI$55 -> 0 | BJ63: 0.03 | BK63: =BK50/BK$55 -> 0.010827678 | BM63: 0 | BN63: 0.01 | BO63: 0 | BP63: 0.01 | BQ63: =BQ50/BQ$55 -> 0.0054876497 | BS63: 0.03 | BT63: 0.01 | BU63: 0.03 | BV63: 0.03 | BW63: =BW50/BW$55 -> 0.024645049 | BY63: 0.05 | BZ63: 0.03 | CA63: 0.02 | CB63: 0.02 | CC63: =CC50/CC$55 -> 0.028229452 | CE63: 0.05 | CF63: 0.03 | CG63: 0.02 | CH63: 0.04 | CI63: =CI50/CI$55 -> 0.034028429 | CK63: 0.04 | CL63: 0.04 | CM63: 0.03 | CN63: 0.03 | CO63: =CO50/CO$55 -> 0.034545532 | CQ63: 0.04 | CR63: 0.02 | CS63: 0.07 | CT63: 0.04 | CU63: 0 | CW63: 0.07 | CX63: 0.05 | CY63: 0.01 | CZ63: 0.04 | DA63: 0 | DC63: 0.02 | DD63: 0.05 | DE63: 0.03 | DF63: 0.03 | DG63: 0 | DI63: 0.06 | DJ63: 0.04 | DK63: 0.03 | DL63: 0.04 | DM63: 0 | DO63: 0.03 | DP63: 0.02 | DQ63: 0.02 | DR63: 0.076231923 | DS63: 0.037 | DU63: 0.03 | DV63: 0.07 | DW63: 0.03 | DX63: 0.02 | DY63: 0.04 | EA63: 0.02 | EB63: 0.02 | EC63: 0.02 | ED63: 0.02 | EG63: 0.02 | FA63: =FA50/FA$55 -> 0.010827678 | FB63: =FB50/FB$55 -> 0.0054876497 | FC63: =FC50/FC$55 -> 0.024645049 | FD63: =FD50/FD$55 -> 0.028229452 | FE63: =FE50/FE$55 -> 0.034028429 | FF63: =FF50/FF$55 -> 0.034545532 | FG63: =FG50/FG$55 -> 0.043640689 | FH63: =FH50/FH$55 -> 0.037968109 | ... FO63: =FO50/FO$55 -> 0 | FQ63: =FQ50/FQ$55 -> 0 | FR63: =FR50/FR$55 -> 0
B64: KrF | K64: 0.51 | L64: 0.32 | M64: 0.24 | N64: 0.45 | O64: =O51/O$55 -> 0.38404359 | Q64: 0.46 | R64: 0.36 | S64: 0.29 | T64: 0.22 | U64: =U51/U$55 -> 0.31613233 | W64: 0.34 | X64: 0.31 | Y64: 0.17 | Z64: 0.15 | AA64: =AA51/AA$55 -> 0.2423431 | AC64: 0.14 | AD64: 0.05 | AE64: 0.08 | AF64: 0.06 | AG64: =AG51/AG$55 -> 0.087876099 | AI64: 0.03 | AJ64: 0 | AK64: 0.1 | AL64: 0.21 | AM64: =AM51/AM$55 -> 0.11880736 | AO64: 0.11 | AP64: 0.11 | AQ64: 0.25 | AR64: 0.19 | AS64: =AS51/AS$55 -> 0.17388887 | AU64: 0.23 | AV64: 0.23 | AW64: 0.16 | AX64: 0.14 | AY64: =AY51/AY$55 -> 0.1934581 | BA64: 0.33 | BB64: 0.27 | BC64: 0.15 | BD64: 0.19 | BE64: =BE51/BE$55 -> 0.23886679 | BG64: 0.23 | BH64: 0.2 | BI64: 0.11 | BJ64: 0.19 | BK64: =BK51/BK$55 -> 0.17985024 | BM64: 0.17 | BN64: 0.02 | BO64: 0.12 | BP64: 0.09 | BQ64: =BQ51/BQ$55 -> 0.095167578 | BS64: 0.12 | BT64: 0.12 | BU64: 0.27 | BV64: 0.23 | BW64: =BW51/BW$55 -> 0.17739498 | BY64: 0.14 | BZ64: 0.11 | CA64: 0.12 | CB64: 0.1 | CC64: =CC51/CC$55 -> 0.11545377 | CE64: 0.15 | CF64: 0.09 | CG64: 0.1 | CH64: 0.1 | CI64: =CI51/CI$55 -> 0.10736605 | CK64: 0.14 | CL64: 0.1 | CM64: 0.09 | CN64: 0.1 | CO64: =CO51/CO$55 -> 0.10555775 | CQ64: 0.09 | CR64: 0.11 | CS64: 0.06 | CT64: 0.06 | CU64: 0 | CW64: 0.13 | CX64: 0.1 | CY64: 0.08 | CZ64: 0.11 | DA64: 0 | DC64: 0.11 | DD64: 0.11 | DE64: 0.07 | DF64: 0.1 | DG64: 0 | DI64: 0.12 | DJ64: 0.1 | DK64: 0.1 | DL64: 0.12 | DM64: 0 | DO64: 0.09 | DP64: 0.09 | DQ64: 0.1 | DR64: 0.11926617 | DS64: 0.1 | DU64: 0.08 | DV64: 0.09 | DW64: 0.1 | DX64: 0.09 | DY64: 0.09 | EA64: 0.05 | EB64: 0.04 | EC64: 0.03 | ED64: 0.05 | EG64: 0.06 | FA64: =FA51/FA$55 -> 0.17985024 | FB64: =FB51/FB$55 -> 0.095167578 | FC64: =FC51/FC$55 -> 0.17739498 | FD64: =FD51/FD$55 -> 0.11545377 | FE64: =FE51/FE$55 -> 0.10736605 | FF64: =FF51/FF$55 -> 0.10555775 | FG64: =FG51/FG$55 -> 0.075919121 | FH64: =FH51/FH$55 -> 0.10170513 | ... FO64: =FO51/FO$55 -> 0 | FQ64: =FQ51/FQ$55 -> 0.049334284 | FR64: =FR51/FR$55 -> 0.042405551
B65: i-Line | K65: 0.07 | L65: 0.02 | M65: 0.05 | N65: 0.07 | O65: =O52/O$55 -> 0.050604674 | Q65: 0.04 | R65: 0.06 | S65: 0.07 | T65: 0.08 | U65: =U52/U$55 -> 0.06528802 | W65: 0.08 | X65: 0.08 | Y65: 0.09 | Z65: 0.06 | AA65: =AA52/AA$55 -> 0.087415696 | AC65: 0.03 | AD65: 0.04 | AE65: 0.05 | AF65: 0.02 | AG65: =AG52/AG$55 -> 0.036065598 | AI65: 0.08 | AJ65: 0.02 | AK65: 0.02 | AL65: 0 | AM65: =AM52/AM$55 -> 0.017812365 | AO65: 0.01 | AP65: 0.01 | AQ65: 0.01 | AR65: 0.02 | AS65: =AS52/AS$55 -> 0.013371505 | AU65: 0.01 | AV65: 0.01 | AW65: 0.02 | AX65: 0.01 | AY65: =AY52/AY$55 -> 0.012606933 | BA65: 0.01 | BB65: 0.01 | BC65: 0.02 | BD65: 0.02 | BE65: =BE52/BE$55 -> 0.014647517 | BG65: 0.03 | BH65: 0.02 | BI65: 0.01 | BJ65: 0 | BK65: =BK52/BK$55 -> 0.012073827 | BM65: 0.01 | BN65: 0.01 | BO65: 0.02 | BP65: 0.01 | BQ65: =BQ52/BQ$55 -> 0.012084708 | BS65: 0.02 | BT65: 0.02 | BU65: 0.02 | BV65: 0.02 | BW65: =BW52/BW$55 -> 0.02 | BY65: 0.02 | BZ65: 0.02 | CA65: 0.02 | CB65: 0.01 | CC65: =CC52/CC$55 -> 0.017240796 | CE65: 0.01 | CF65: 0.02 | CG65: 0.01 | CH65: 0.01 | CI65: =CI52/CI$55 -> 0.01217158 | CK65: 0.01 | CL65: 0.01 | CM65: 0.01 | CN65: 0.01 | CO65: =CO52/CO$55 -> 0.01 | CQ65: 0.02 | CR65: 0.01 | CS65: 0.01 | CT65: 0.02 | CU65: 0 | CW65: 0.03 | CX65: 0.01 | CY65: 0.01 | CZ65: 0.01 | DA65: 0 | DC65: 0.01 | DD65: 0.01 | DE65: 0.01 | DF65: 0.01 | DG65: 0 | DI65: 0.02 | DJ65: 0.01 | DK65: 0.01 | DL65: 0.01 | DM65: 0 | DO65: 0.01 | DP65: 0.01 | DQ65: 0.01 | DR65: 0.01 | DS65: 0.01 | DU65: 0.01 | DV65: 0.02 | DW65: 0.02 | DX65: 0.02 | DY65: 0.02 | EA65: 0.01 | EB65: 0.01 | EC65: 0.01 | ED65: 0.01 | EG65: 0.01 | FA65: =FA52/FA$55 -> 0.012073827 | FB65: =FB52/FB$55 -> 0.012084708 | FC65: =FC52/FC$55 -> 0.02 | FD65: =FD52/FD$55 -> 0.017240796 | FE65: =FE52/FE$55 -> 0.01217158 | FF65: =FF52/FF$55 -> 0.01 | FG65: =FG52/FG$55 -> 0.015357544 | FH65: =FH52/FH$55 -> 0.013070809 | ... FO65: =FO52/FO$55 -> 0 | FQ65: =FQ52/FQ$55 -> 0 | FR65: =FR52/FR$55 -> 0
B66: Total DUV | CQ66: =CQ53/CQ55 -> 0.75 | CR66: =CR53/CR55 -> 0.55 | CS66: =CS53/CS55 -> 0.65 | CT66: =CT53/CT55 -> 0.68 | CU66: =CU53/CU55 -> 0.65864163 | CW66: =CW53/CW55 -> 0.75 | CX66: =CX53/CX55 -> 0.57 | CY66: =CY53/CY55 -> 0.31 | CZ66: =CZ53/CZ55 -> 0.61 | DA66: =DA53/DA55 -> 0.53202162 | DC66: =DC53/DC55 -> 0.61 | DD66: =DD53/DD55 -> 0.51 | DE66: =DE53/DE55 -> 0.43 | DF66: =DF53/DF55 -> 0.49 | DG66: =DG53/DG55 -> 0.5037542 | DI66: =DI53/DI55 -> 0.67 | DJ66: =DJ53/DJ55 -> 0.48 | DK66: =DK53/DK55 -> 0.45 | DL66: =DL53/DL55 -> 0.48 | DM66: =DM53/DM55 -> 0.49989119 | DO66: =DO53/DO55 -> 0.43 | DP66: =DP53/DP55 -> 0.61 | DQ66: =DQ53/DQ55 -> 0.61 | DR66: =DR53/DR55 -> 0.57459462 | DS66: =DS53/DS55 -> 0.5570014 | DU66: =DU53/DU55 -> 0.51 | DV66: =DV53/DV55 -> 0.68 | DW66: =DW53/DW55 -> 0.63 | DX66: =DX53/DX55 -> 0.54 | DY66: =DY53/DY55 -> 0.58965336 | EA66: =EA53/EA55 -> 0.41 | EB66: =EB53/EB55 -> 0.5 | EC66: =EC53/EC55 -> 0.58 | ED66: =ED53/ED55 -> 0.48 | EE66: =EE53/EE55 -> 0.49084553 | EG66: =EG53/EG55 -> 0.32 | EH66: =EH53/EH55 -> 0.42589438 | EI66: =EI53/EI55 -> 0.39407314 | EJ66: =EJ53/EJ55 -> 0.39021414 | EK66: =EK53/EK55 -> 0.38313694 | EL66: =EL53/EL55 -> 0.3918546 | FP66: =FP53/FP55 -> 0.40356968
B67: Metrology & Inspection | CB67: 0.05 | CC67: =CC55/CC$55 -> 1 | CE67: 0.05 | CF67: 0.06 | CG67: 0.03 | CH67: 0.04 | CI67: =CI54/CI$55 -> 0.043396928 | CK67: 0.02 | CL67: 0.04 | CM67: 0.04 | CN67: 0.05 | CO67: =CO54/CO$55 -> 0.038896853 | CQ67: 0.03 | CR67: 0.04 | CS67: 0.03 | CT67: 0.03 | CU67: =CU54/CU55 -> 0.032057336 | CW67: 0.03 | CX67: 0.04 | CY67: 0.03 | CZ67: 0.03 | DA67: =DA54/DA55 -> 0.032363786 | DC67: 0.03 | DD67: 0.04 | DE67: 0.03 | DF67: 0.05 | DG67: =DG54/DG55 -> 0.037233734 | DI67: 0.07 | DJ67: 0.04 | DK67: 0.04 | DL67: 0.03 | DM67: =DM54/DM55 -> 0.041369837 | DO67: 0.03 | DP67: 0.02 | DQ67: 0.04 | DR67: 0.0034988297 | DS67: =DS54/DS55 -> 0.022999923 | DU67: 0.03 | DV67: 0.01 | DW67: 0.02 | DX67: 0.04 | DY67: =DY54/DY55 -> 0.026172532 | EA67: 0.03 | EB67: 0.02 | EC67: 0.04 | ED67: 0.04 | EE67: =EE54/EE55 -> 0.033081375 | EG67: 0.02 | EH67: =EH54/EH55 -> 0.025553663 | EI67: =EI54/EI55 -> 0.022068096 | EJ67: =EJ54/EJ55 -> 0.024102208 | EK67: =EK54/EK55 -> 0.022926318 | EL67: =EL54/EL55 -> 0.022691992 | FD67: =FD54/FD$55 -> 0.013796019 | FE67: =FE54/FE$55 -> 0.043396928 | FF67: =FF54/FF$55 -> 0.038896853 | FG67: =FG54/FG$55 -> 0.032057336 | FH67: =FH54/FH$55 -> 0.032363786 | FI67: =FI54/FI$55 -> 0.037233734 | FJ67: =FJ54/FJ$55 -> 0.041369837 | FK67: =FK54/FK$55 -> 0.022999848 | ... FO67: =FO54/FO$55 -> 0.022691992 | FP67: =FP54/FP55 -> 0.02900573 | FQ67: =FQ54/FQ$55 -> 0.0047551117 | FR67: =FR54/FR$55 -> 0.042405551
B68: Total | CQ68: =SUM(CQ61,CQ66:CQ67) -> 1 | CR68: =SUM(CR61,CR66:CR67) -> 1 | CS68: =SUM(CS61,CS66:CS67) -> 1 | CT68: =SUM(CT61,CT66:CT67) -> 1 | CU68: =SUM(CU61,CU66:CU67) -> 1 | CW68: =SUM(CW61,CW66:CW67) -> 1 | CX68: =SUM(CX61,CX66:CX67) -> 1 | CY68: =SUM(CY61,CY66:CY67) -> 1 | CZ68: =SUM(CZ61,CZ66:CZ67) -> 1 | DA68: =SUM(DA61,DA66:DA67) -> 1 | DC68: =SUM(DC61,DC66:DC67) -> 1 | DD68: =SUM(DD61,DD66:DD67) -> 1 | DE68: =SUM(DE61,DE66:DE67) -> 1 | DF68: =SUM(DF61,DF66:DF67) -> 1 | DG68: =SUM(DG61,DG66:DG67) -> 1 | DI68: =SUM(DI61,DI66:DI67) -> 1 | DJ68: =SUM(DJ61,DJ66:DJ67) -> 1 | DK68: =SUM(DK61,DK66:DK67) -> 1 | DL68: =SUM(DL61,DL66:DL67) -> 1 | DM68: =SUM(DM61,DM66:DM67) -> 1 | DO68: =SUM(DO61,DO66:DO67) -> 1.0000202 | DP68: =SUM(DP61,DP66:DP67) -> 0.9999934 | DQ68: =SUM(DQ61,DQ66:DQ67) -> 1 | DR68: =SUM(DR61,DR66:DR67) -> 1 | DS68: =SUM(DS61,DS66:DS67) -> 1.0000032 | DU68: =SUM(DU61,DU66:DU67) -> 1 | DV68: =SUM(DV61,DV66:DV67) -> 1 | DW68: =SUM(DW61,DW66:DW67) -> 1 | DX68: =SUM(DX61,DX66:DX67) -> 1 | DY68: =SUM(DY61,DY66:DY67) -> 1 | EA68: =SUM(EA61,EA66:EA67) -> 1 | EB68: =SUM(EB61,EB66:EB67) -> 1 | EC68: =SUM(EC61,EC66:EC67) -> 1.0000137 | ED68: =SUM(ED61,ED66:ED67) -> 1 | EE68: =SUM(EE61,EE66:EE67) -> 1 | EG68: =SUM(EG61,EG66:EG67) -> 1 | EH68: =SUM(EH61,EH66:EH67) -> 1 | EI68: =SUM(EI61,EI66:EI67) -> 1 | EJ68: =SUM(EJ61,EJ66:EJ67) -> 1 | EK68: =SUM(EK61,EK66:EK67) -> 1 | EL68: =SUM(EL61,EL66:EL67) -> 1 | FP68: =SUM(FP61,FP66:FP67) -> 1
B71: Units 'Shipped' (Rev. Recog.) - by technology | FF71: =FF76/SUM(FF73:FF74) -> 4.7777778 | FG71: =FG76/SUM(FG73:FG74) -> 3.1538462 | FH71: =FH76/SUM(FH73:FH74) -> 2.1935484 | FI71: =FI76/SUM(FI73:FI74) -> 1.9285714 | FJ71: =FJ76/SUM(FJ73:FJ74) -> 2.025 | FK71: =FK76/SUM(FK73:FK74) -> 2.3584906 | FL71: =FL76/SUM(FL73:FL74) -> 2.9318182 | FM71: =FM76/SUM(FM73:FM74) -> 2.7291667 | ... FR71: =FR76/SUM(FR73:FR74) -> 0
B72: EUV - Hyper NA | FR72: 3 | FU72: Assume unlikely to see anything other than a pilot line shipment before 2030; HVM ramp c.2034/35
B73: EUV - High NA | DX73: =DX227+DX280 -> 2 | DY73: =DU73+DV73+DW73+DX73 -> 2 | EA73: =EA205 -> 0 | EB73: =EB205 -> 1 | EC73: =EC205 -> 1 | ED73: =ED205 -> 2 | EE73: =SUM(EA73:ED73) -> 4 | EG73: =EG205 -> 2 | EH73: =EH205 -> 0 | EI73: =EI205 -> 2 | EJ73: =EJ205 -> 2 | EK73: =EG73+EH73+EI73+EJ73 -> 6 | EL73: =EL205 -> 6 | FF73: =CO73 -> 0 | FG73: =CU73 -> 0 | FH73: =DA73 -> 0 | FI73: =DG73 -> 0 | FJ73: =DM73 -> 0 | FK73: =DS73 -> 0 | FL73: =DY73 -> 2 | FM73: =EE73 -> 4 | FN73: =EE73 -> 4 | FO73: =EG73 -> 2 | FP73: =FP205 -> 8 | FQ73: =FQ280 -> 20 | FR73: =FR280 -> 24 | FU73: Assume 2 pilot tools in 2024; MSD tools in 2025 and 15-20 in 2027+ (??)
B74: EUV - Low NA | BE74: =BA74+BB74+BC74+BD74 -> 0 | BH74: 0 | BI74: 0 | BJ74: 1 | BK74: =BG74+BH74+BI74+BJ74 -> 1 | BM74: 1 | BN74: 1 | BO74: 2 | BP74: 1 | BQ74: =BM74+BN74+BO74+BP74 -> 5 | BS74: 0 | BT74: 1 | BU74: 0 | BV74: 0 | BW74: =BS74+BT74+BU74+BV74 -> 1 | BY74: 0 | BZ74: 2 | CA74: 1 | CB74: 1 | CC74: =BY74+BZ74+CA74+CB74 -> 4 | CE74: 0 | CF74: 2 | CG74: 4 | CH74: 5 | CI74: =CE74+CF74+CG74+CH74 -> 11 | CK74: 1 | CL74: 7 | CM74: 5 | CN74: 5 | CO74: =CK74+CL74+CM74+CN74 -> 18 | CQ74: 4 | CR74: 7 | CS74: 7 | CT74: 8 | CU74: =CQ74+CR74+CS74+CT74 -> 26 | CW74: 2 | CX74: 7 | CY74: 14 | CZ74: 8 | DA74: =CW74+CX74+CY74+CZ74 -> 31 | DC74: 7 | DD74: 9 | DE74: 15 | DF74: 11 | DG74: =DC74+DD74+DE74+DF74 -> 42 | DI74: 3 | DJ74: 12 | DK74: 12 | DL74: 13 | DM74: =DI74+DJ74+DK74+DL74 -> 40 | DO74: 17 | DP74: 12 | DQ74: 11 | DR74: 13 | DS74: =DO74+DP74+DQ74+DR74 -> 53 | DU74: 11 | DV74: 8 | DW74: 11 | DX74: 12 | DY74: =DU74+DV74+DW74+DX74 -> 42 | EA74: =EA168 -> 14 | EB74: =EB168 -> 10 | EC74: =EC168 -> 8 | ED74: =ED168 -> 12 | EE74: =SUM(EA74:ED74) -> 44 | EG74: =EG75-EG73 -> 14 | EH74: =EH168 -> 14 | EI74: =EI168 -> 17 | EJ74: =EJ168 -> 18 | EK74: =EG74+EH74+EI74+EJ74 -> 63 | EL74: =EL168 -> 84 | FA74: =BK74 -> 1 | FB74: =BQ74 -> 5 | FC74: =BW74 -> 1 | FD74: =CC74 -> 4 | FE74: =CI74 -> 11 | FF74: =CO74 -> 18 | FG74: =CU74 -> 26 | FH74: =DA74 -> 31 | FI74: =DG74 -> 42 | FJ74: =DM74 -> 40 | FK74: =DS74 -> 53 | FL74: =DY74 -> 42 | FM74: =EE74 -> 44 | FN74: =EK74 -> 63 | FO74: =EL74 -> 84 | FP74: =FP168 -> 61 | FQ74: =FQ168 -> 63 | FR74: =FR168 -> 64 | FU74: Assume c.40 tools in 2022 and c.50 in 2023 and 2024; 70+ in 2025
B75: Total EUV | EA75: =SUM(EA72:EA74) -> 14 | EB75: =SUM(EB72:EB74) -> 11 | EC75: =SUM(EC72:EC74) -> 9 | ED75: =SUM(ED72:ED74) -> 14 | EE75: =SUM(EA75:ED75) -> 48 | EG75: 16 | EH75: =SUM(EH72:EH74) -> 14 | EI75: =SUM(EI72:EI74) -> 19 | EJ75: =SUM(EJ72:EJ74) -> 20 | EK75: =SUM(EK72:EK74) -> 69 | EL75: =SUM(EL72:EL74) -> 90
B76: ArF Immersion | W76: 3 | X76: 3 | Y76: 12 | Z76: 13 | AA76: =W76+X76+Y76+Z76 -> 31 | AC76: 14 | AD76: 16 | AE76: 16 | AF76: 11 | AG76: =AC76+AD76+AE76+AF76 -> 57 | AI76: 1 | AJ76: 6 | AK76: 13 | AM76: =AI76+AJ76+AK76+AL76 -> 20 | AO76: 17 | AP76: 25 | AQ76: 23 | AR76: 29 | AS76: =AO76+AP76+AQ76+AR76 -> 94 | AU76: 27 | AV76: 26 | AW76: 25 | AX76: 23 | AY76: =AU76+AV76+AW76+AX76 -> 101 | BA76: 16 | BB76: 18 | BC76: 22 | BD76: 16 | BE76: =BA76+BB76+BC76+BD76 -> 72 | BG76: 12 | BH76: 18 | BI76: 20 | BJ76: 27 | BK76: =BG76+BH76+BI76+BJ76 -> 77 | BM76: 19 | BN76: 24 | BO76: 13 | BP76: 20 | BQ76: =BM76+BN76+BO76+BP76 -> 76 | BS76: 23 | BT76: 19 | BU76: 14 | BV76: 11 | BW76: =BS76+BT76+BU76+BV76 -> 67 | BY76: 15 | BZ76: 19 | CA76: 19 | CB76: 17 | CC76: =BY76+BZ76+CA76+CB76 -> 70 | CE76: 18 | CF76: 16 | CG76: 22 | CH76: 20 | CI76: =CE76+CF76+CG76+CH76 -> 76 | CK76: 21 | CL76: 19 | CM76: 22 | CN76: 24 | CO76: =CK76+CL76+CM76+CN76 -> 86 | CQ76: 17 | CR76: 13 | CS76: 21 | CT76: 31 | CU76: =CQ76+CR76+CS76+CT76 -> 82 | CW76: 16 | CX76: 17 | CY76: 11 | CZ76: 24 | DA76: =CW76+CX76+CY76+CZ76 -> 68 | DC76: 24 | DD76: 16 | DE76: 21 | DF76: 20 | DG76: =DC76+DD76+DE76+DF76 -> 81 | DI76: 18 | DJ76: 21 | DK76: 20 | DL76: 22 | DM76: =DI76+DJ76+DK76+DL76 -> 81 | DO76: 25 | DP76: 39 | DQ76: 32 | DR76: 29 | DS76: =DO76+DP76+DQ76+DR76 -> 125 | DT76: =DS76/DT79 -> 0.31565657 | DU76: 20 | DV76: 32 | DW76: 38 | DX76: 39 | DY76: =DU76+DV76+DW76+DX76 -> 129 | EA76: 25 | EB76: 31 | EC76: 38 | ED76: 37 | EE76: =EA76+EB76+EC76+ED76 -> 131 | EG76: 17 | EH76: =EH80*0.4 -> 26.5 | EI76: =EI80*0.4 -> 33 | EJ76: 45 | EK76: =EG76+EH76+EI76+EJ76 -> 121.5 | EL76: =EL80*0.4 -> 155.28148 | FA76: =BK76 -> 77 | FB76: =BQ76 -> 76 | FC76: =BW76 -> 67 | FD76: =CC76 -> 70 | FE76: =CI76 -> 76 | FF76: =CO76 -> 86 | FG76: =CU76 -> 82 | FH76: =DA76 -> 68 | FI76: =DG76 -> 81 | FJ76: =DM76 -> 81 | FK76: =DS76 -> 125 | FL76: =DY76 -> 129 | FM76: =EE76 -> 131 | FN76: =EF76 -> 0 | FO76: =EG76 -> 17 | FP76: =ROUNDUP(FP71*SUM(FP73:FP74),0) -> 0 | FQ76: =ROUNDUP(FQ71*SUM(FQ73:FQ74),0) -> 0 | FR76: =ROUNDUP(FR71*SUM(FR73:FR74),0) -> 0 | FU76: Assume on growth in fabs for bulk semis (14nm - 28nm); for now, assume c.90 in 2022 and 100-110 in 2023
B77: ArF dry | K77: 14 | L77: 23 | M77: 17 | N77: 11 | Q77: 14 | R77: 25 | S77: 26 | T77: 33 | W77: 24 | X77: 24 | Y77: =27-Y76 -> 15 | Z77: 16 | AA77: =W77+X77+Y77+Z77 -> 79 | AC77: 14 | AD77: 9 | AE77: 4 | AF77: 5 | AG77: =AC77+AD77+AE77+AF77 -> 32 | AI77: 4 | AJ77: 1 | AK77: 1 | AL77: 4 | AM77: =AI77+AJ77+AK77+AL77 -> 10 | AO77: 2 | AP77: 2 | AQ77: 2 | AR77: 6 | AS77: =AO77+AP77+AQ77+AR77 -> 12 | AU77: 4 | AV77: 4 | AW77: 3 | AX77: 0 | AY77: =AU77+AV77+AW77+AX77 -> 11 | BA77: 3 | BB77: 0 | BC77: 0 | BD77: 1 | BE77: =BA77+BB77+BC77+BD77 -> 4 | BG77: 0 | BH77: 0 | BI77: 0 | BJ77: 2 | BK77: =BG77+BH77+BI77+BJ77 -> 2 | BM77: 0 | BN77: 2 | BO77: 0 | BP77: 1 | BQ77: =BM77+BN77+BO77+BP77 -> 3 | BS77: 2 | BT77: 2 | BU77: 2 | BV77: 3 | BW77: =BS77+BT77+BU77+BV77 -> 9 | BY77: 2 | BZ77: 2 | CA77: 1 | CB77: 1 | CC77: =BY77+BZ77+CA77+CB77 -> 6 | CE77: 4 | CF77: 3 | CG77: 2 | CH77: 5 | CI77: =CE77+CF77+CG77+CH77 -> 14 | CK77: 3 | CL77: 5 | CM77: 3 | CN77: 5 | CO77: =CK77+CL77+CM77+CN77 -> 16 | CQ77: 4 | CR77: 3 | CS77: 9 | CT77: 6 | CU77: =CQ77+CR77+CS77+CT77 -> 22 | CW77: 6 | CX77: 7 | CY77: 2 | CZ77: 7 | DA77: =CW77+CX77+CY77+CZ77 -> 22 | DC77: 4 | DD77: 7 | DE77: 6 | DF77: 5 | DG77: =DC77+DD77+DE77+DF77 -> 22 | DI77: 6 | DJ77: 8 | DK77: 6 | DL77: 8 | DM77: =DI77+DJ77+DK77+DL77 -> 28 | DO77: 7 | DP77: 6 | DQ77: 9 | DR77: 10 | DS77: =DO77+DP77+DQ77+DR77 -> 32 | DU77: 4 | DV77: 11 | DW77: 7 | DX77: 6 | DY77: =DU77+DV77+DW77+DX77 -> 28 | EA77: 3 | EB77: 4 | EC77: 4 | ED77: 5 | EG77: 5 | FA77: =BK77 -> 2 | FB77: =BQ77 -> 3 | FC77: =BW77 -> 9 | FD77: =CC77 -> 6 | FE77: =CI77 -> 14 | FF77: =CO77 -> 16 | FG77: =CU77 -> 22 | FH77: =DA77 -> 22 | FI77: =DG77 -> 22 | FJ77: =DM77 -> 28 | FK77: =DS77 -> 32 | FL77: =DY77 -> 28 | FM77: =EE77 -> 0 | FN77: =EF77 -> 0 | FO77: =EG77 -> 5 | FP77: =ROUND(FP76/3,0) -> 0 | FQ77: =ROUND(FQ76/3,0) -> 0 | FR77: =ROUND(FR76/3,0) -> 0
B78: KrF | K78: 31 | L78: 22 | M78: 12 | N78: 24 | Q78: 25 | R78: 31 | S78: 25 | T78: 19 | W78: 30 | X78: 25 | Y78: 14 | Z78: 13 | AA78: =W78+X78+Y78+Z78 -> 82 | AC78: 13 | AD78: 5 | AE78: 5 | AF78: 6 | AG78: =AC78+AD78+AE78+AF78 -> 29 | AI78: 2 | AJ78: 0 | AK78: 6 | AL78: 9 | AM78: =AI78+AJ78+AK78+AL78 -> 17 | AO78: 10 | AP78: 12 | AQ78: 21 | AR78: 25 | AS78: =AO78+AP78+AQ78+AR78 -> 68 | AU78: 28 | AV78: 27 | AW78: 18 | AX78: 14 | AY78: =AU78+AV78+AW78+AX78 -> 87 | BA78: 29 | BB78: 22 | BC78: 13 | BD78: 14 | BE78: =BA78+BB78+BC78+BD78 -> 78 | BG78: 13 | BH78: 15 | BI78: 10 | BJ78: 26 | BK78: =BG78+BH78+BI78+BJ78 -> 64 | BM78: 17 | BN78: 2 | BO78: 10 | BP78: 10 | BQ78: =BM78+BN78+BO78+BP78 -> 39 | BS78: 16 | BT78: 14 | BU78: 24 | BV78: 20 | BW78: =BS78+BT78+BU78+BV78 -> 74 | BY78: 12 | BZ78: 16 | CA78: 14 | CB78: 15 | CC78: =BY78+BZ78+CA78+CB78 -> 57 | CE78: 19 | CF78: 14 | CG78: 18 | CH78: 20 | CI78: =CE78+CF78+CG78+CH78 -> 71 | CK78: 19 | CL78: 19 | CM78: 18 | CN78: 22 | CO78: =CK78+CL78+CM78+CN78 -> 78 | CQ78: 14 | CR78: 19 | CS78: 14 | CT78: 18 | CU78: =CQ78+CR78+CS78+CT78 -> 65 | CW78: 22 | CX78: 23 | CY78: 23 | CZ78: 35 | DA78: =CW78+CX78+CY78+CZ78 -> 103 | DC78: 35 | DD78: 31 | DE78: 30 | DF78: 35 | DG78: =DC78+DD78+DE78+DF78 -> 131 | DI78: 26 | DJ78: 38 | DK78: 38 | DL78: 49 | DM78: =DI78+DJ78+DK78+DL78 -> 151 | DO78: 43 | DP78: 43 | DQ78: 44 | DR78: 54 | DS78: =DO78+DP78+DQ78+DR78 -> 184 | DU78: 25 | DV78: 33 | DW78: 42 | DX78: 52 | DY78: =DU78+DV78+DW78+DX78 -> 152 | EA78: 22 | EB78: 16 | EC78: 11 | ED78: 29 | EG78: 30 | FA78: =BK78 -> 64 | FB78: =BQ78 -> 39 | FC78: =BW78 -> 74 | FD78: =CC78 -> 57 | FE78: =CI78 -> 71 | FF78: =CO78 -> 78 | FG78: =CU78 -> 65 | FH78: =DA78 -> 103 | FI78: =DG78 -> 131 | FJ78: =DM78 -> 151 | FK78: =DS78 -> 184 | FL78: =DY78 -> 152 | FM78: =EE78 -> 0 | FN78: =EF78 -> 0 | FO78: =EG78 -> 30 | FP78: =ROUNDUP(1.1*(FP74+FP73+FP76),0) -> 76 | FQ78: =ROUNDUP((FQ74+FQ73+FQ76),0) -> 83 | FR78: =ROUNDUP((FR74+FR73+FR76),0) -> 88 | FU78: Assume matches same # tools as EUV + immersion (note: tracks at that level , with range of 0.8x - 1.2x, per Q for last 3-4 years)
B79: i-Line | K79: 14 | L79: 6 | M79: 10 | N79: 12 | Q79: 12 | R79: 16 | S79: 20 | T79: 20 | W79: 23 | X79: 20 | Y79: 18 | Z79: 13 | AA79: =W79+X79+Y79+Z79 -> 74 | AC79: 9 | AD79: 9 | AE79: 12 | AF79: 3 | AG79: =AC79+AD79+AE79+AF79 -> 33 | AI79: 4 | AJ79: 3 | AK79: 4 | AL79: 1 | AM79: =AI79+AJ79+AK79+AL79 -> 12 | AO79: 5 | AP79: 4 | AQ79: 5 | AR79: 9 | AS79: =AO79+AP79+AQ79+AR79 -> 23 | AU79: 4 | AV79: 6 | AW79: 7 | AX79: 3 | AY79: =AU79+AV79+AW79+AX79 -> 20 | BA79: 3 | BB79: 4 | BC79: 5 | BD79: 3 | BE79: =BA79+BB79+BC79+BD79 -> 15 | BG79: 4 | BH79: 5 | BI79: 4 | BJ79: 0 | BK79: =BG79+BH79+BI79+BJ79 -> 13 | BM79: 3 | BN79: 2 | BO79: 5 | BP79: 3 | BQ79: =BM79+BN79+BO79+BP79 -> 13 | BS79: 6 | BT79: 5 | BU79: 4 | BV79: 3 | BW79: =BS79+BT79+BU79+BV79 -> 18 | BY79: 4 | BZ79: 7 | CA79: 5 | CB79: 4 | CC79: =BY79+BZ79+CA79+CB79 -> 20 | CE79: 3 | CF79: 7 | CG79: 9 | CH79: 7 | CI79: =CE79+CF79+CG79+CH79 -> 26 | CK79: 5 | CL79: 8 | CM79: 5 | CN79: 8 | CO79: =CK79+CL79+CM79+CN79 -> 26 | CQ79: 9 | CR79: 6 | CS79: 6 | CT79: 13 | CU79: =CQ79+CR79+CS79+CT79 -> 34 | CW79: 11 | CX79: 7 | CY79: 10 | CZ79: 6 | DA79: =CW79+CX79+CY79+CZ79 -> 34 | DC79: 6 | DD79: 9 | DE79: 7 | DF79: 11 | DG79: =DC79+DD79+DE79+DF79 -> 33 | DI79: 9 | DJ79: 12 | DK79: 10 | DL79: 14 | DM79: =DI79+DJ79+DK79+DL79 -> 45 | DO79: 8 | DP79: 13 | DQ79: 16 | DR79: 18 | DS79: =DO79+DP79+DQ79+DR79 -> 55 | DT79: =SUM(DS76:DS79) -> 396 | DU79: 10 | DV79: 16 | DW79: 18 | DX79: 21 | DY79: =DU79+DV79+DW79+DX79 -> 65 | EA79: 13 | EB79: 14 | EC79: 10 | ED79: 17 | EG79: 11 | FA79: =BK79 -> 13 | FB79: =BQ79 -> 13 | FC79: =BW79 -> 18 | FD79: =CC79 -> 20 | FE79: =CI79 -> 26 | FF79: =CO79 -> 26 | FG79: =CU79 -> 34 | FH79: =DA79 -> 34 | FI79: =DG79 -> 33 | FJ79: =DM79 -> 45 | FK79: =DS79 -> 55 | FL79: =DY79 -> 65 | FM79: =EE79 -> 0 | FN79: =EF79 -> 0 | FO79: =EG79 -> 11 | FP79: =ROUNDUP((1.5*FP77),0) -> 0 | FQ79: =ROUNDUP((1.5*FQ77),0) -> 0 | FR79: =ROUNDUP((1.5*FR77),0) -> 0
B80: Total DUV | DY80: =SUM(DY76:DY79) -> 374 | EA80: =SUM(EA76:EA79) -> 63 | EB80: =SUM(EB76:EB79) -> 65 | EC80: =SUM(EC76:EC79) -> 63 | ED80: =SUM(ED76:ED79) -> 88 | EE80: =SUM(EA80:ED80) -> 279 | EG80: =EG367 -> 63 | EH80: =EH367 -> 66.25 | EI80: =EI367 -> 82.5 | EJ80: =EJ367 -> 85.949875 | EK80: =SUM(EG80:EJ80) -> 297.69987 | EL80: =EL367 -> 388.20369 | FE80: =CI80 -> 0 | FF80: =CO80 -> 0 | FG80: =CU80 -> 0 | FH80: =DA80 -> 0 | FI80: =DG80 -> 0 | FJ80: =DM80 -> 0 | FK80: =DS80 -> 0 | FL80: =DY80 -> 374 | FM80: =EE80 -> 279 | FN80: =EF80 -> 0 | FO80: =EG80 -> 63 | FP80: =FP367 -> 328.09583 | FQ80: =FQ367 -> 327.45833 | FR80: =FR367 -> 326.13333
B82: Subtotal (Litho systems) | K82: =K76+K77+K78+K79 -> 59 | L82: =L76+L77+L78+L79 -> 51 | M82: =M76+M77+M78+M79 -> 39 | N82: =N76+N77+N78+N79 -> 47 | Q82: =Q76+Q77+Q78+Q79 -> 51 | R82: =R76+R77+R78+R79 -> 72 | S82: =S76+S77+S78+S79 -> 71 | T82: =T76+T77+T78+T79 -> 72 | W82: =W76+W77+W78+W79 -> 80 | X82: =X76+X77+X78+X79 -> 72 | Y82: =Y76+Y77+Y78+Y79 -> 59 | Z82: =Z76+Z77+Z78+Z79 -> 55 | AA82: =AA76+AA77+AA78+AA79 -> 266 | AC82: =AC76+AC77+AC78+AC79 -> 50 | AD82: =AD76+AD77+AD78+AD79 -> 39 | AE82: =SUM(AE76:AE79) -> 37 | AF82: =SUM(AF76:AF79) -> 25 | AG82: =SUM(AG76:AG79) -> 151 | AI82: =SUM(AI76:AI79) -> 11 | AJ82: =SUM(AJ76:AJ79) -> 10 | AK82: =SUM(AK76:AK79) -> 24 | AL82: =SUM(AL76:AL79) -> 14 | AM82: =SUM(AM76:AM79) -> 59 | AO82: =SUM(AO76:AO79) -> 34 | AP82: =SUM(AP76:AP79) -> 43 | AQ82: =SUM(AQ76:AQ79) -> 51 | AR82: =SUM(AR76:AR79) -> 69 | AS82: =SUM(AS72:AS79) -> 197 | AU82: =SUM(AU76:AU79) -> 63 | AV82: =SUM(AV76:AV79) -> 63 | AW82: =SUM(AW72:AW79) -> 53 | AX82: =SUM(AX72:AX79) -> 40 | AY82: =SUM(AY72:AY79) -> 219 | BA82: =SUM(BA72:BA79) -> 51 | BB82: =SUM(BB72:BB79) -> 44 | BC82: =SUM(BC72:BC79) -> 40 | BD82: =SUM(BD72:BD79) -> 34 | BE82: =SUM(BE74:BE79) -> 169 | BG82: =SUM(BG72:BG79) -> 29 | BH82: =SUM(BH74:BH79) -> 38 | BI82: =SUM(BI74:BI79) -> 34 | BJ82: =SUM(BJ74:BJ79) -> 56 | BK82: =SUM(BK74:BK79) -> 157 | BM82: =SUM(BM74:BM79) -> 40 | BN82: =SUM(BN74:BN79) -> 31 | BO82: =SUM(BO74:BO79) -> 30 | BP82: =SUM(BP74:BP79) -> 35 | BQ82: =SUM(BQ74:BQ79) -> 136 | BS82: =SUM(BS74:BS79) -> 47 | BT82: =SUM(BT74:BT79) -> 41 | BU82: =SUM(BU74:BU79) -> 44 | BV82: =SUM(BV74:BV79) -> 37 | BW82: =SUM(BW74:BW79) -> 169 | BY82: =SUM(BY74:BY79) -> 33 | BZ82: =SUM(BZ74:BZ79) -> 46 | CA82: =SUM(CA74:CA79) -> 40 | CB82: =SUM(CB74:CB79) -> 38 | CC82: =SUM(CC74:CC79) -> 157 | CE82: =SUM(CE74:CE79) -> 44 | CF82: =SUM(CF74:CF79) -> 42 | CG82: =SUM(CG74:CG79) -> 55 | CH82: =SUM(CH74:CH79) -> 57 | CI82: =SUM(CI74:CI79) -> 198 | CK82: =SUM(CK74:CK79) -> 49 | CL82: =SUM(CL74:CL79) -> 58 | CM82: =SUM(CM74:CM79) -> 53 | CN82: =SUM(CN74:CN79) -> 64 | CO82: =SUM(CO74:CO79) -> 224 | CQ82: =SUM(CQ74:CQ79) -> 48 | CR82: =SUM(CR74:CR79) -> 48 | CS82: =SUM(CS74:CS79) -> 57 | CT82: =SUM(CT74:CT79) -> 76 | CU82: =SUM(CU74:CU79) -> 229 | CW82: =SUM(CW74:CW79) -> 57 | CX82: =SUM(CX74:CX79) -> 61 | CY82: =SUM(CY74:CY79) -> 60 | CZ82: =SUM(CZ74:CZ79) -> 80 | DA82: =SUM(DA74:DA79) -> 258 | DC82: =SUM(DC74:DC79) -> 76 | DD82: =SUM(DD74:DD79) -> 72 | DE82: =SUM(DE74:DE79) -> 79 | DF82: =SUM(DF74:DF79) -> 82 | DG82: =SUM(DG74:DG79) -> 309 | DI82: =SUM(DI74:DI79) -> 62 | DJ82: =SUM(DJ74:DJ79) -> 91 | DK82: =SUM(DK74:DK79) -> 86 | DL82: =SUM(DL74:DL79) -> 106 | DM82: =SUM(DM74:DM79) -> 345 | DO82: =SUM(DO74:DO79) -> 100 | DP82: =SUM(DP74:DP79) -> 113 | DQ82: =SUM(DQ74:DQ79) -> 112 | DR82: =SUM(DR74:DR79) -> 124 | DS82: =SUM(DS74:DS79) -> 449 | DU82: =SUM(DU74:DU79) -> 70 | DV82: =SUM(DV74:DV79) -> 100 | DW82: =SUM(DW74:DW79) -> 116 | DX82: =SUM(DX73:DX79) -> 132 | DY82: =SUM(DY74:DY79) -> 416 | EA82: =SUM(EA75,EA80) -> 77 | EB82: =SUM(EB75,EB80) -> 76 | EC82: =SUM(EC73:EC79) -> 81 | ED82: =SUM(ED73:ED79) -> 116 | EE82: =SUM(EE73:EE79) -> 227 | EG82: =SUM(EG74:EG79) -> 93 | EH82: =SUM(EH74:EH79) -> 54.5 | EI82: =SUM(EI74:EI79) -> 69 | EJ82: =SUM(EJ74:EJ79) -> 83 | EK82: =SUM(EK74:EK79) -> 253.5 | EL82: =SUM(EL73:EL79) -> 335.28148 | FA82: =SUM(FA74:FA79) -> 157 | FB82: =SUM(FB74:FB79) -> 136 | FC82: =SUM(FC74:FC79) -> 169 | FD82: =SUM(FD74:FD79) -> 157 | FE82: =SUM(FE74:FE79) -> 198 | FF82: =SUM(FF74:FF79) -> 224 | FG82: =SUM(FG74:FG79) -> 229 | FH82: =SUM(FH74:FH79) -> 258 | ... FL82: =SUM(FL74:FL79) -> 416 | FM82: =SUM(FM73:FM79) -> 179 | FN82: =SUM(FN73:FN79) -> 67 | FO82: =SUM(FO73:FO79) -> 149 | FP82: =SUM(FP73:FP79) -> 145 | FQ82: =SUM(FQ73:FQ79) -> 166 | FR82: =SUM(FR73:FR79) -> 176
B84: System ASPs (EURm) - by techology
B85: EUV - Hyper NA | FQ85: 585 | FR85: 600
B86: EUV - High NA | DU86: =DU207 -> 0 | DV86: =DV207 -> 0 | DW86: =DW207 -> 0 | DX86: =DX207 -> 250 | DY86: =IF(DY46=0,DS86,DY46/DY73) -> 250 | EA86: =EA207 -> 0 | EB86: =EB207 -> 250 | EC86: =EC207 -> 360 | ED86: =ED207 -> 305 | EE86: =IF(EE46=0,DY86,EE46/EE73) -> 305 | EG86: =EG314 -> 360 | EH86: =EH314 -> 360 | EI86: =EI314 -> 360 | EJ86: =EJ314 -> 360 | EK86: =IF(EK46=0,EE86,EK46/EK73) -> 360 | EL86: 360 | FL86: =DY86 -> 250 | FM86: =EE86 -> 305 | FN86: =EF86 -> 0 | FO86: =EG86 -> 360 | FP86: =(80%*FP73*360+20%*FP73*385)/FP73 -> 365 | FQ86: 385 | FR86: 400
B87: EUV - Low NA | BJ87: =IF(BJ47=0,BI87,IF(BJ74=0,BJ47,BJ47/BJ74)) -> 57.648 | BK87: =IF(BK47=0,BJ87,IF(BK72=0,BK47,BK47/BK72)) -> 57.648 | BM87: =IF(BM47=0,BJ87,IF(BM74=0,BM47,BM47/BM74)) -> 61.8 | BN87: =IF(BN47=0,BM87,IF(BN74=0,BN47,BN47/BN74)) -> 62.15 | BO87: =IF(BO47=0,BN87,IF(BO74=0,BO47,BO47/BO74)) -> 61.915 | BP87: =IF(BP47=0,BO87,IF(BP74=0,BP47,BP47/BP74)) -> 65.118 | BQ87: =AVERAGE(BM87:BP87) -> 62.74575 | BS87: =IF(BS47=0,BP87,IF(BS74=0,BS47,BS47/BS74)) -> 65.118 | BT87: =IF(BT47=0,BS87,IF(BT74=0,BT47,BT47/BT74)) -> 68.07 | BU87: =IF(BU47=0,BT87,IF(BU74=0,BU47,BU47/BU74)) -> 68.07 | BV87: =IF(BV47=0,BU87,IF(BV74=0,BV47,BV47/BV74)) -> 68.07 | BW87: =AVERAGE(BS87:BV87) -> 67.332 | BY87: =IF(BY47=0,BV87,IF(BY74=0,BY47,BY47/BY74)) -> 68.07 | BZ87: =IF(BZ47=0,BY87,IF(BZ74=0,BZ47,BZ47/BZ74)) -> 50.616 | CA87: =IF(CA47=0,BZ87,IF(CA74=0,CA47,CA47/CA74)) -> 88.039 | CB87: =IF(CB47=0,CA87,IF(CB74=0,CB47,CB47/CB74)) -> 141.801 | CC87: =AVERAGE(BY87:CB87) -> 87.1315 | CE87: =IF(CE47=0,CB87,IF(CE74=0,CE47,CE47/CE74)) -> 141.801 | CF87: =IF(CF47=0,CE87,IF(CF74=0,CF47,CF47/CF74)) -> 110.728 | CG87: =IF(CG47=0,CF87,IF(CG74=0,CG47,CG47/CG74)) -> 95.49225 | CH87: =IF(CH47=0,CG87,IF(CH74=0,CH47,CH47/CH74)) -> 97.745 | CI87: =AVERAGE(CE87:CH87) -> 111.44156 | CK87: =IF(CK47=0,CH87,IF(CK74=0,CK47,CK47/CK74)) -> 116.739 | CL87: =IF(CL47=0,CK87,IF(CL74=0,CL47,CL47/CL74)) -> 95.382857 | CM87: =IF(CM47=0,CL87,IF(CM74=0,CM47,CM47/CM74)) -> 104.03 | CN87: =IF(CN47=0,CM87,IF(CN74=0,CN47,CN47/CN74)) -> 116.3664 | CO87: =AVERAGE(CK87:CN87) -> 108.12956 | CQ87: =IF(CQ47=0,CN87,IF(CQ74=0,CQ47,CQ47/CQ74)) -> 92.895 | CR87: =IF(CR47=0,CQ87,IF(CR74=0,CR47,CR47/CR74)) -> 108.404 | CS87: =IF(CS47=0,CR87,IF(CS74=0,CS47,CS47/CS74)) -> 106.31314 | CT87: =IF(CT47=0,CS87,IF(CT74=0,CT47,CT47/CT74)) -> 113.48787 | CU87: =AVERAGE(CQ87:CT87) -> 105.275 | CW87: =IF(CW47=0,CT87,IF(CW74=0,CW47,CW47/CW74)) -> 174.24 | CX87: =IF(CX47=0,CW87,IF(CX74=0,CX47,CX47/CX74)) -> 135.86486 | CY87: =IF(CY47=0,CX87,IF(CY74=0,CY47,CY47/CY74)) -> 145.93543 | CZ87: =IF(CZ47=0,CY87,IF(CZ74=0,CZ47,CZ47/CZ74)) -> 143.9235 | DA87: =AVERAGE(CW87:CZ87) -> 149.99095 | DC87: =IF(DC47=0,CZ87,IF(DC74=0,DC47,DC47/DC74)) -> 160.90971 | DD87: =IF(DD47=0,DC87,IF(DD74=0,DD47,DD47/DD74)) -> 147.48 | DE87: =IF(DE47=0,DD87,IF(DE74=0,DE47,DE47/DE74)) -> 147.9996 | DF87: =IF(DF47=0,DE87,IF(DF74=0,DF47,DF47/DF74)) -> 144.82473 | DG87: =AVERAGE(DC87:DF87) -> 150.30351 | DI87: =IF(DI47=0,DF87,IF(DI74=0,DI47,DI47/DI74)) -> 198.224 | DJ87: =IF(DJ47=0,DI87,IF(DJ74=0,DJ47,DJ47/DJ74)) -> 165.62 | DK87: =IF(DK47=0,DJ87,IF(DK74=0,DK47,DK47/DK74)) -> 180.82475 | DL87: =IF(DL47=0,DK87,IF(DL74=0,DL47,DL47/DL74)) -> 178.95931 | DM87: =AVERAGE(DI87:DL87) -> 180.90701 | DO87: =IF(DO47=0,DM87,DO47/DO74) -> 169.68706 | DP87: =IF(DP47=0,DO87,DP47/DP74) -> 172.85167 | DQ87: =IF(DQ47=0,DP87,DQ47/DQ74) -> 168.89727 | DR87: =IF(DR47=0,DQ87,DR47/DR74) -> 184.42185 | DS87: =IF(DS47=0,DM86,DS47/DS74) -> 173.85385 | DU87: =IF(DU47=0,DS87,DU47/DU74) -> 165.84673 | DV87: =IF(DV47=0,DU87,DV47/DV74) -> 184.48487 | DW87: =IF(DW47=0,DV87,DW47/DW74) -> 188.55455 | DX87: =IF(DX47=0,DW87,DX47/DX74) -> 207.38983 | DY87: =IF(DY47=0,#REF!,DY47/DY74) -> 187.2136 | EA87: =EA199 -> 229.616 | EB87: =EB199 -> 243.6128 | EC87: =EC199 -> 218.815 | ED87: =ED199 -> 252.52667 | EE87: =IF(EE47=0,DY87,EE47/EE74) -> 237.08164 | EG87: =EG199 -> 230 | EH87: 225 | EI87: 225 | EJ87: 230 | EK87: =IF(EK47=0,EE87,EK47/EK74) -> 233.24032 | EL87: 240 | FA87: =BK87 -> 57.648 | FB87: =BQ87 -> 62.74575 | FC87: =BW87 -> 67.332 | FD87: =CC87 -> 87.1315 | FE87: =CI87 -> 111.44156 | FF87: =CO87 -> 108.12956 | FG87: =CU87 -> 105.275 | FH87: =DA87 -> 149.99095 | FI87: =DG87 -> 150.30351 | FJ87: =DM87 -> 180.90701 | FK87: =DS87 -> 173.85385 | FL87: =DY87 -> 187.2136 | FM87: =EE87 -> 237.08164 | FN87: =EF87 -> 0 | FO87: =EG87 -> 230 | FP87: 210 | FQ87: 210 | FR87: 210
B89: ArF Immersion | Y89: =Y49/Y76 -> 28.107733 | Z89: =Z49/Z76 -> 30.176849 | AA89: =AA49/AA76 -> 23.535221 | AC89: =AC49/AC76 -> 29.870919 | AD89: =AD49/AD76 -> 29.476931 | AE89: =AE49/AE76 -> 28.428544 | AF89: =AF49/AF76 -> 25.249107 | AI89: =AI49/AI76 -> 29.319 | AJ89: =AJ49/AJ76 -> 27.183418 | AK89: =AK49/AK76 -> 29.638495 | AL89: =IFERROR(AL49/AL76,"0") -> 0 | AO89: =AO49/AO76 -> 30.836941 | AP89: =AP49/AP76 -> 31.382 | AQ89: =AQ49/AQ76 -> 32.596087 | AR89: =AR49/AR76 -> 31.695517 | AS89: =AS49/AS76 -> 31.677213 | AU89: =AU49/AU76 -> 33.774963 | AV89: =AV49/AV76 -> 35.391692 | AW89: =AW49/AW76 -> 36.057024 | AX89: =AX49/AX76 -> 34.960304 | AY89: =AY49/AY76 -> 35.025947 | BA89: =BA49/BA76 -> 36.75 | BB89: =BB49/BB76 -> 39.392 | BC89: =BC49/BC76 -> 37.738591 | BD89: =BD49/BD76 -> 36.40875 | BE89: =IF(BE49=0,BD89,BE49/BE76) -> 37.636736 | BG89: =IF(BG49=0,BE89,BG49/BG76) -> 41.742167 | BH89: =IF(BH49=0,BG89,BH49/BH76) -> 39.671667 | BI89: =IF(BI49=0,BH89,BI49/BI76) -> 42.218 | BJ89: =IF(BJ49=0,BI89,BJ49/BJ76) -> 39.499556 | BK89: =IF(BK49=0,BJ89,BK49/BK76) -> 40.595377 | BM89: =IF(BM49=0,BK89,BM49/BM76) -> 41.2 | BN89: =IF(BN49=0,BM89,BN49/BN76) -> 47.130417 | BO89: =IF(BO49=0,BN89,BO49/BO76) -> 48.987692 | BP89: =IF(BP49=0,BO89,BP49/BP76) -> 45.03995 | BQ89: =IF(BQ49=0,BK89,BQ49/BQ76) -> 45.415382 | BS89: =IF(BS49=0,BQ89,BS49/BS76) -> 44.982391 | BT89: =IF(BT49=0,BR89,BT49/BT76) -> 47.171316 | BU89: =IF(BU49=0,BS89,BU49/BU76) -> 47.371714 | BV89: =IF(BV49=0,BT89,BV49/BV76) -> 57.658909 | BW89: =IF(BW49=0,BQ89,BW49/BW76) -> 48.183612 | BY89: =IF(BY49=0,BW89,BY49/BY76) -> 45.2828 | BZ89: =IF(BZ49=0,BY89,BZ49/BZ76) -> 50.616 | CA89: =IF(CA49=0,BZ89,CA49/CA76) -> 50.969947 | CB89: =IF(CB49=0,CA89,CB49/CB76) -> 53.838882 | CC89: =IF(CC49=0,BW89,CC49/CC76) -> 50.351943 | CE89: =IF(CE49=0,CC89,CE49/CE76) -> 49.982889 | CF89: =IF(CF49=0,CE89,CF49/CF76) -> 55.364 | CG89: =IF(CG49=0,CF89,CG49/CG76) -> 52.086682 | CH89: =IF(CH49=0,CG89,CH49/CH76) -> 54.7372 | CI89: =IF(CI49=0,CC89,CI49/CI76) -> 52.975882 | CK89: =IF(CK49=0,CI89,CK49/CK76) -> 57.178286 | CL89: =IF(CL49=0,CK89,CL49/CL76) -> 53.809737 | CM89: =IF(CM49=0,CL89,CM49/CM76) -> 54.852182 | CN89: =IF(CN49=0,CM89,CN49/CN76) -> 57.577125 | CO89: =IF(CO49=0,CI89,CO49/CO76) -> 55.950326 | CQ89: =IF(CQ49=0,CO89,CQ49/CQ76) -> 59.611765 | CR89: =IF(CR49=0,CQ89,CR49/CR76) -> 58.371385 | CS89: =IF(CS49=0,CR89,CS49/CS76) -> 56.478857 | CT89: =IF(CT49=0,CS89,CT49/CT76) -> 56.554581 | CU89: =IF(CU49=0,CO89,CU49/CU76) -> 57.457024 | CW89: =IF(CW49=0,CU89,CW49/CW76) -> 51.48 | CX89: =IF(CX49=0,CW89,CX49/CX76) -> 58.813294 | CY89: =IF(CY49=0,CX89,CY49/CY76) -> 59.097818 | CZ89: =IF(CZ49=0,CY89,CZ49/CZ76) -> 59.968125 | DA89: =IF(DA49=0,CU89,DA49/DA76) -> 57.541426 | DC89: =IF(DC49=0,DA89,DC49/DC76) -> 61.272333 | DD89: =IF(DD49=0,DC89,DD49/DD76) -> 62.679 | DE89: =IF(DE49=0,DD89,DE49/DE76) -> 62.645333 | DF89: =IF(DF49=0,DE89,DF49/DF76) -> 60.606 | DG89: =IF(DG49=0,DA89,DG49/DG76) -> 61.74163 | DI89: =IF(DI49=0,DG89,DI49/DI76) -> 59.721333 | DJ89: =IF(DJ49=0,DH89,DJ49/DJ76) -> 65.065 | DK89: =IF(DK49=0,DI89,DK49/DK76) -> 65.94785 | DL89: =IF(DL49=0,DJ89,DL49/DL76) -> 66.902227 | DM89: =IF(DM49=0,DG89,DM49/DM76) -> 64.594506 | DO89: =IF(DO49=0,DM89,DO49/DO76) -> 64.1016 | DP89: =IF(DP49=0,DN89,DP49/DP76) -> 70.435615 | DQ89: =IF(DQ49=0,DO89,DQ49/DQ76) -> 79.623 | DR89: =IF(DR49=0,DP89,DR49/DR76) -> 72.323828 | DS89: =IF(DS49=0,DM89,DS49/DS76) -> 71.958848 | DU89: =IF(DU49=0,DS89,DU49/DU76) -> 77.33505 | DV89: =IF(DV49=0,DT89,DV49/DV76) -> 74.389062 | DW89: =IF(DW49=0,DU89,DW49/DW76) -> 74.854737 | DX89: =IF(DX49=0,DV89,DX49/DX76) -> 74.808179 | DY89: =IF(DY49=0,#REF!,DY49/DY76) -> 75.10969 | EA89: =EA49/EA76 -> 75.77328 | EB89: =EB49/EB76 -> 77.623323 | EC89: =EC49/EC76 -> 75.999368 | ED89: =ED49/ED76 -> 81.989189 | EE89: =IF(EE49=0,DY89,EE49/EE76) -> 75.10969 | EG89: =EG49/EG76 -> 84.951176 | EH89: 78 | EI89: 78 | EJ89: 78 | EK89: =IF(EK49=0,EE89,EK49/EK76) -> 75.10969 | EL89: 75 | FA89: =BK89 -> 40.595377 | FB89: =BQ89 -> 45.415382 | FC89: =BW89 -> 48.183612 | FD89: =CC89 -> 50.351943 | FE89: =CI89 -> 52.975882 | FF89: =CO89 -> 55.950326 | FG89: =CU89 -> 57.457024 | FH89: =DA89 -> 57.541426 | FI89: =DG89 -> 61.74163 | FJ89: =DM89 -> 64.594506 | FK89: =DS89 -> 71.958848 | FL89: =DY89 -> 75.10969 | FM89: =EE89 -> 75.10969 | FN89: =EF89 -> 0 | FO89: =EG89 -> 84.951176 | FP89: 75 | FQ89: 78 | FR89: 80 | FU89: We should assume a growth in cost per tools - both supply of parts (and cost of sales) as well as sell-on ASP per toolset
B90: ArF dry | K90: =K50/K77 -> 18.96405 | L90: =L50/L77 -> 19.528367 | M90: =M50/M77 -> 19.169666 | N90: =N50/N77 -> 19.898924 | Q90: =Q50/Q77 -> 19.753607 | R90: =R50/R77 -> 19.506954 | S90: =S50/S77 -> 21.084455 | T90: =T50/T77 -> 20.757991 | W90: =W50/W77 -> 20.04212 | X90: =X50/X77 -> 20.301335 | Y90: =Y50/Y77 -> 19.113259 | Z90: =Z50/Z77 -> 17.589495 | AA90: =AA50/AA77 -> 19.447768 | AC90: =AC50/AC77 -> 18.742537 | AD90: =AD50/AD77 -> 20.961373 | AE90: =AE50/AE77 -> 14.768075 | AF90: =AF50/AF77 -> 14.457708 | AI90: =AI50/AI77 -> 15.165 | AJ90: =AJ50/AJ77 -> 16.49331 | AK90: =AK50/AK77 -> 18.34764 | AL90: =AL50/AL77 -> 9.71568 | AO90: =AO50/AO77 -> 15.79 | AP90: =AP50/AP77 -> 13.845 | AQ90: =AQ50/AQ77 -> 5.135 | AR90: =AR50/AR77 -> 19.6965 | AS90: =AS50/AS77 -> 15.64325 | AU90: =AU50/AU77 -> 16.055 | AV90: =AV50/AV77 -> 23.338 | AW90: =AW50/AW77 -> 21.22 | AX90: =IF(AX77=0,"n/a",AX50/AX77) -> n/a | AY90: =AY50/AY77 -> 20.112 | BA90: =BA50/BA77 -> 21 | BB90: =IF(BB50=0,BA90,BB50/BB77) -> 21 | BC90: =IF(BC50=0,BB90,BC50/BC77) -> 21 | BD90: =IF(BD50=0,BC90,BD50/BD77) -> 22.995 | BE90: =IF(BE50=0,BD90,BE50/BE77) -> 21.49875 | BG90: =IF(BG50=0,BE90,BG50/BG77) -> 21.49875 | BH90: =IF(BH50=0,BG90,BH50/BH77) -> 21.49875 | BI90: =IF(BI50=0,BH90,BI50/BI77) -> 21.49875 | BJ90: =IF(BJ50=0,BI90,BJ50/BJ77) -> 21.618 | BK90: =IF(BK50=0,BJ90,BK50/BK77) -> 21.618 | BM90: =IF(BM50=0,BK90,BM50/BM77) -> 21.618 | BN90: =IF(BN50=0,BM90,BN50/BN77) -> 6.215 | BO90: =IF(BO50=0,BN90,BO50/BO77) -> 6.215 | BP90: =IF(BP50=0,BO90,BP50/BP77) -> 10.853 | BQ90: =IF(BQ50=0,BK90,BQ50/BQ77) -> 7.761 | BS90: =IF(BS50=0,BQ90,BS50/BS77) -> 18.6975 | BT90: =IF(BT50=0,BR90,BT50/BT77) -> 5.6725 | BU90: =IF(BU50=0,BS90,BU50/BU77) -> 14.6295 | BV90: =IF(BV50=0,BT90,BV50/BV77) -> 8.809 | BW90: =IF(BW50=0,BQ90,BW50/BW77) -> 11.602889 | BY90: =IF(BY50=0,BW90,BY50/BY77) -> 21.495 | BZ90: =IF(BZ50=0,BY90,BZ50/BZ77) -> 18.981 | CA90: =IF(CA50=0,BZ90,CA50/CA77) -> 25.154 | CB90: =IF(CB50=0,CA90,CB50/CB77) -> 25.782 | CC90: =IF(CC50=0,BW90,CC50/CC77) -> 21.981333 | CE90: =IF(CE50=0,CC90,CE50/CE77) -> 15.1975 | CF90: =IF(CF50=0,CE90,CF50/CF77) -> 13.841 | CG90: =IF(CG50=0,CF90,CG50/CG77) -> 18.189 | CH90: =IF(CH50=0,CG90,CH50/CH77) -> 15.6392 | CI90: =IF(CI50=0,CC90,CI50/CI77) -> 15.491929 | CK90: =IF(CK50=0,CI90,CK50/CK77) -> 22.236 | CL90: =IF(CL50=0,CK90,CL50/CL77) -> 16.692 | CM90: =IF(CM50=0,CL90,CM50/CM77) -> 20.806 | CN90: =IF(CN50=0,CM90,CN50/CN77) -> 14.5458 | CO90: =IF(CO50=0,CI90,CO50/CO77) -> 17.832187 | CQ90: =IF(CQ50=0,CO90,CQ50/CQ77) -> 16.89 | CR90: =IF(CR50=0,CQ90,CR50/CR77) -> 12.338667 | CS90: =IF(CS50=0,CR90,CS50/CS77) -> 18.088 | CT90: =IF(CT50=0,CS90,CT50/CT77) -> 20.871333 | CU90: =IF(CU50=0,CO90,CU50/CU77) -> 17.845273 | CW90: =IF(CW50=0,CU90,CW50/CW77) -> 18.48 | CX90: =IF(CX50=0,CW90,CX50/CX77) -> 17.418571 | CY90: =IF(CY50=0,CX90,CY50/CY77) -> 15.478 | CZ90: =IF(CZ50=0,CY90,CZ50/CZ77) -> 18.276 | DA90: =IF(DA50=0,CU90,DA50/DA77) -> 17.804455 | DC90: =IF(DC50=0,DA90,DC50/DC77) -> 15.644 | DD90: =IF(DD50=0,DC90,DD50/DD77) -> 21.068571 | DE90: =IF(DE50=0,DD90,DE50/DE77) -> 20.5555 | DF90: =IF(DF50=0,DE90,DF50/DF77) -> 20.7792 | DG90: =IF(DG50=0,DA90,DG50/DG77) -> 19.876591 | DI90: =IF(DI50=0,DG90,DI50/DI77) -> 22.872 | DJ90: =IF(DJ50=0,DH90,DJ50/DJ77) -> 20.7025 | DK90: =IF(DK50=0,DI90,DK50/DK77) -> 21.2735 | DL90: =IF(DL50=0,DJ90,DL50/DL77) -> 23.7395 | DM90: =IF(DM50=0,DG90,DM50/DM77) -> 22.157464 | DO90: =IF(DO50=0,DM90,DO50/DO77) -> 22.893429 | DP90: =IF(DP50=0,DN90,DP50/DP77) -> 18.687 | DQ90: =IF(DQ50=0,DO90,DQ50/DQ77) -> 11.796 | DR90: =IF(DR50=0,DP90,DR50/DR77) -> 43.31879 | DS90: =IF(DS50=0,DM90,DS50/DS77) -> 25.366497 | DU90: =IF(DU50=0,DS90,DU50/DU77) -> 29.74425 | DV90: =IF(DV50=0,DT90,DV50/DV77) -> 30.296636 | DW90: =IF(DW50=0,DU90,DW50/DW77) -> 25.397143 | DX90: =IF(DX50=0,DV90,DX50/DX77) -> 23.719667 | DY90: =IF(DY50=0,#REF!,DY50/DY77) -> 27.5835 | EA90: =EA50/EA77 -> 38.269333 | EB90: =EB50/EB77 -> 27.9805 | EC90: =EC50/EC77 -> 27.769 | ED90: =ED50/ED77 -> 30.336 | EE90: =IF(EE50=0,DY90,EE50/EE77) -> 27.5835 | EG90: =EG50/EG77 -> 25.116 | EH90: 28 | EI90: 28 | EJ90: 28 | EK90: =IF(EK50=0,EE90,EK50/EK77) -> 27.5835 | EL90: 30 | FA90: =BK90 -> 21.618 | FB90: =BQ90 -> 7.761 | FC90: =BW90 -> 11.602889 | FD90: =CC90 -> 21.981333 | FE90: =CI90 -> 15.491929 | FF90: =CO90 -> 17.832187 | FG90: =CU90 -> 17.845273 | FH90: =DA90 -> 17.804455 | FI90: =DG90 -> 19.876591 | FJ90: =DM90 -> 22.157464 | FK90: =DS90 -> 25.366497 | FL90: =DY90 -> 27.5835 | FM90: =EE90 -> 27.5835 | FN90: =EF90 -> 0 | FO90: =EG90 -> 25.116 | FP90: 30 | FQ90: 30 | FR90: 30
B91: KrF | K91: =K51/K78 -> 10.39964 | L91: =L51/L78 -> 9.8986764 | M91: =M51/M78 -> 9.17984 | N91: =N51/N78 -> 8.5503188 | Q91: =Q51/Q78 -> 10.177058 | R91: =R51/R78 -> 9.7643265 | S91: =S51/S78 -> 9.9360496 | T91: =T51/T78 -> 11.331054 | W91: =W51/W78 -> 9.734744 | X91: =X51/X78 -> 10.240131 | Y91: =Y51/Y78 -> 10.239246 | Z91: =Z51/Z78 -> 9.8402769 | AA91: =AA51/AA78 -> 9.9916906 | AC91: =AC51/AC78 -> 8.8306185 | AD91: =AD51/AD78 -> 7.25586 | AE91: =AE51/AE78 -> 9.451568 | AF91: =AF51/AF78 -> 3.80466 | AI91: =AI51/AI78 -> 1.5165 | AJ91: 0 | AK91: =AK51/AK78 -> 7.64485 | AL91: =AL51/AL78 -> 10.07552 | AO91: =AO51/AO78 -> 6.9476 | AP91: =AP51/AP78 -> 8.4608333 | AQ91: =AQ51/AQ78 -> 12.22619 | AR91: =AR51/AR78 -> 9.97956 | AS91: =AS51/AS78 -> 9.9594853 | AU91: =AU51/AU78 -> 10.550429 | AV91: =AV51/AV78 -> 11.360296 | AW91: =AW51/AW78 -> 11.317333 | AX91: =AX51/AX78 -> 9.927 | AY91: =AY51/AY78 -> 10.860115 | BA91: =BA51/BA78 -> 11.948276 | BB91: =BB51/BB78 -> 12.086182 | BC91: =IF(BC51=0,BB91,BC51/BC78) -> 11.541923 | BD91: =IF(BD51=0,BC91,BD51/BD78) -> 10.4025 | BE91: =IF(BE51=0,BD91,BE51/BE78) -> 11.642 | BG91: =IF(BG51=0,BE91,BG51/BG78) -> 11.975923 | BH91: =IF(BH51=0,BG91,BH51/BH78) -> 12.206667 | BI91: =IF(BI51=0,BH91,BI51/BI78) -> 10.5545 | BJ91: =IF(BJ51=0,BI91,BJ51/BJ78) -> 10.531846 | BK91: =IF(BK51=0,BJ91,BK51/BK78) -> 11.22125 | BM91: =IF(BM51=0,BK91,BM51/BM78) -> 10.3 | BN91: =IF(BN51=0,BM91,BN51/BN78) -> 12.43 | BO91: =IF(BO51=0,BN91,BO51/BO78) -> 10.614 | BP91: =IF(BP51=0,BO91,BP51/BP78) -> 9.7677 | BQ91: =IF(BQ51=0,BK91,BQ51/BQ78) -> 10.353256 | BS91: =IF(BS51=0,BQ91,BS51/BS78) -> 9.34875 | BT91: =IF(BT51=0,BR91,BT51/BT78) -> 9.7242857 | BU91: =IF(BU51=0,BS91,BU51/BU78) -> 10.972125 | BV91: =IF(BV51=0,BT91,BV51/BV78) -> 10.13035 | BW91: =IF(BW51=0,BQ91,BW51/BW78) -> 10.157541 | BY91: =IF(BY51=0,BW91,BY51/BY78) -> 10.031 | BZ91: =IF(BZ51=0,BY91,BZ51/BZ78) -> 8.699625 | CA91: =IF(CA51=0,BZ91,CA51/CA78) -> 10.780286 | CB91: =IF(CB51=0,CA91,CB51/CB78) -> 8.594 | CC91: =IF(CC51=0,BW91,CC51/CC78) -> 9.4631579 | CE91: =IF(CE51=0,CC91,CE51/CE78) -> 9.5984211 | CF91: =IF(CF51=0,CE91,CF51/CF78) -> 8.8977857 | CG91: =IF(CG51=0,CF91,CG51/CG78) -> 10.105 | CH91: =IF(CH51=0,CG91,CH51/CH78) -> 9.7745 | CI91: =IF(CI51=0,CC91,CI51/CI78) -> 9.6382958 | CK91: =IF(CK51=0,CI91,CK51/CK78) -> 12.288316 | CL91: =IF(CL51=0,CK91,CL51/CL78) -> 10.981579 | CM91: =IF(CM51=0,CL91,CM51/CM78) -> 10.403 | CN91: =IF(CN51=0,CM91,CN51/CN78) -> 11.019545 | CO91: =IF(CO51=0,CI91,CO51/CO78) -> 11.177077 | CQ91: =IF(CQ51=0,CO91,CQ51/CQ78) -> 10.857857 | CR91: =IF(CR51=0,CQ91,CR51/CR78) -> 10.715158 | CS91: =IF(CS51=0,CR91,CS51/CS78) -> 9.9668571 | CT91: =IF(CT51=0,CS91,CT51/CT78) -> 10.435667 | CU91: =IF(CU51=0,CO91,CU51/CU78) -> 10.507323 | CW91: =IF(CW51=0,CU91,CW51/CW78) -> 9.36 | CX91: =IF(CX51=0,CW91,CX51/CX78) -> 10.602609 | CY91: =IF(CY51=0,CX91,CY51/CY78) -> 10.767304 | CZ91: =IF(CZ51=0,CY91,CZ51/CZ78) -> 10.0518 | DA91: =IF(DA51=0,CU91,DA51/DA78) -> 10.186806 | DC91: =IF(DC51=0,DA91,DC51/DC78) -> 9.8333714 | DD91: =IF(DD51=0,DC91,DD51/DD78) -> 10.466323 | DE91: =IF(DE51=0,DD91,DE51/DE78) -> 9.5925667 | DF91: =IF(DF51=0,DE91,DF51/DF78) -> 9.8948571 | DG91: =IF(DG51=0,DA91,DG51/DG78) -> 9.9444351 | DI91: =IF(DI51=0,DG91,DI51/DI78) -> 10.556308 | DJ91: =IF(DJ51=0,DH91,DJ51/DJ78) -> 10.896053 | DK91: =IF(DK51=0,DI91,DK51/DK78) -> 11.196579 | DL91: =IF(DL51=0,DJ91,DL51/DL78) -> 11.62751 | DM91: =IF(DM51=0,DG91,DM51/DM78) -> 11.150543 | DO91: =IF(DO51=0,DM91,DO51/DO78) -> 11.180512 | DP91: =IF(DP51=0,DN91,DP51/DP78) -> 11.733698 | DQ91: =IF(DQ51=0,DO91,DQ51/DQ78) -> 12.064091 | DR91: =IF(DR51=0,DP91,DR51/DR78) -> 12.550556 | DS91: =IF(DS51=0,DM91,DS51/DS78) -> 11.923158 | DU91: =IF(DU51=0,DS91,DU51/DU78) -> 12.69088 | DV91: =IF(DV51=0,DT91,DV51/DV78) -> 12.984273 | DW91: =IF(DW51=0,DU91,DW51/DW78) -> 14.109524 | DX91: =IF(DX51=0,DV91,DX51/DX78) -> 12.315981 | DY91: =IF(DY51=0,#REF!,DY51/DY78) -> 13.018316 | EA91: =EA51/EA78 -> 13.046364 | EB91: =EB51/EB78 -> 13.99025 | EC91: =EC51/EC78 -> 15.146727 | ED91: =ED51/ED78 -> 13.075862 | EE91: =IF(EE51=0,DY91,EE51/EE78) -> 13.018316 | EG91: =EG51/EG78 -> 12.558 | EH91: 14 | EI91: 14 | EJ91: 14 | EK91: =IF(EK51=0,EE91,EK51/EK78) -> 13.018316 | EL91: 12.5 | FA91: =BK91 -> 11.22125 | FB91: =BQ91 -> 10.353256 | FC91: =BW91 -> 10.157541 | FD91: =CC91 -> 9.4631579 | FE91: =CI91 -> 9.6382958 | FF91: =CO91 -> 11.177077 | FG91: =CU91 -> 10.507323 | FH91: =DA91 -> 10.186806 | FI91: =DG91 -> 9.9444351 | FJ91: =DM91 -> 11.150543 | FK91: =DS91 -> 11.923158 | FL91: =DY91 -> 13.018316 | FM91: =EE91 -> 13.018316 | FN91: =EF91 -> 0 | FO91: =EG91 -> 12.558 | FP91: 12.5 | FQ91: 12.5 | FR91: 12.5
B92: i-Line | K92: =K52/K79 -> 3.160675 | L92: =L52/L79 -> 2.2684467 | M92: =M52/M79 -> 2.29496 | N92: =N52/N79 -> 2.6600992 | Q92: =Q52/Q79 -> 1.84367 | R92: =R52/R79 -> 3.1530637 | S92: =S52/S79 -> 2.997946 | T92: =T52/T79 -> 3.914364 | W92: =W52/W79 -> 3.7345565 | X92: =X52/X79 -> 4.129085 | Y92: =Y52/Y79 -> 4.21616 | Z92: =Z52/Z79 -> 3.9361108 | AA92: =AA52/AA79 -> 3.9937408 | AC92: =AC52/AC79 -> 2.7332867 | AD92: =AD52/AD79 -> 3.2248267 | AE92: =AE52/AE79 -> 2.4613458 | AF92: =AF52/AF79 -> 2.53644 | AI92: =AI52/AI79 -> 2.022 | AJ92: =AJ52/AJ79 -> 1.2217267 | AK92: =AK52/AK79 -> 2.293455 | AL92: =AL52/AL79 -> 0 | AO92: =AO52/AO79 -> 1.2632 | AP92: =AP52/AP79 -> 2.3075 | AQ92: =AQ52/AQ79 -> 2.054 | AR92: =AR52/AR79 -> 2.918 | AS92: =AS52/AS79 -> 2.2642609 | AU92: =AU52/AU79 -> 3.211 | AV92: =AV52/AV79 -> 2.2226667 | AW92: =AW52/AW79 -> 3.6377143 | AX92: =AX52/AX79 -> 3.309 | AY92: =AY52/AY79 -> 3.07855 | BA92: =BA52/BA79 -> 3.5 | BB92: =BB52/BB79 -> 2.462 | BC92: =IF(BC52=0,BB92,BC52/BC79) -> 4.0012 | BD92: =IF(BD52=0,BC92,BD52/BD79) -> 5.11 | BE92: =IF(BE52=0,BD92,BE52/BE79) -> 3.7122667 | BG92: =IF(BG52=0,BE92,BG52/BG79) -> 5.07675 | BH92: =IF(BH52=0,BG92,BH52/BH79) -> 3.662 | BI92: =IF(BI52=0,BH92,BI52/BI79) -> 2.39875 | BJ92: =IF(BJ52=0,BI92,BJ52/BJ79) -> 2.39875 | BK92: =IF(BK52=0,BJ92,BK52/BK79) -> 3.7086154 | BM92: =IF(BM52=0,BK92,BM52/BM79) -> 3.4333333 | BN92: =IF(BN52=0,BM92,BN52/BN79) -> 6.215 | BO92: =IF(BO52=0,BN92,BO52/BO79) -> 3.538 | BP92: =IF(BP52=0,BO92,BP52/BP79) -> 3.6176667 | BQ92: =IF(BQ52=0,BK92,BQ52/BQ79) -> 3.9440769 | BS92: =IF(BS52=0,BQ92,BS52/BS79) -> 4.155 | BT92: =IF(BT52=0,BR92,BT52/BT79) -> 4.538 | BU92: =IF(BU52=0,BS92,BU52/BU79) -> 4.8765 | BV92: =IF(BV52=0,BT92,BV52/BV79) -> 5.8726667 | BW92: =IF(BW52=0,BQ92,BW52/BW79) -> 4.708 | BY92: =IF(BY52=0,BW92,BY52/BY79) -> 4.299 | BZ92: =IF(BZ52=0,BY92,BZ52/BZ79) -> 3.6154286 | CA92: =IF(CA52=0,BZ92,CA52/CA79) -> 5.0308 | CB92: =IF(CB52=0,CA92,CB52/CB79) -> 3.22275 | CC92: =IF(CC52=0,BW92,CC52/CC79) -> 4.02745 | CE92: =IF(CE52=0,CC92,CE52/CE79) -> 4.0526667 | CF92: =IF(CF52=0,CE92,CF52/CF79) -> 3.9545714 | CG92: =IF(CG52=0,CF92,CG52/CG79) -> 2.021 | CH92: =IF(CH52=0,CG92,CH52/CH79) -> 2.7927143 | CI92: =IF(CI52=0,CC92,CI52/CI79) -> 2.9837692 | CK92: =IF(CK52=0,CI92,CK52/CK79) -> 3.3354 | CL92: =IF(CL52=0,CK92,CL52/CL79) -> 2.608125 | CM92: =IF(CM52=0,CL92,CM52/CM79) -> 4.1612 | CN92: =IF(CN52=0,CM92,CN52/CN79) -> 3.030375 | CO92: =IF(CO52=0,CI92,CO52/CO79) -> 3.1765769 | CQ92: =IF(CQ52=0,CO92,CQ52/CQ79) -> 3.7533333 | CR92: =IF(CR52=0,CQ92,CR52/CR79) -> 3.0846667 | CS92: =IF(CS52=0,CR92,CS52/CS79) -> 3.876 | CT92: =IF(CT52=0,CS92,CT52/CT79) -> 4.8164615 | CU92: =IF(CU52=0,CO92,CU52/CU79) -> 4.0634706 | CW92: =IF(CW52=0,CU92,CW52/CW79) -> 4.32 | CX92: =IF(CX52=0,CW92,CX52/CX79) -> 3.4837143 | CY92: =IF(CY52=0,CX92,CY52/CY79) -> 3.0956 | CZ92: =IF(CZ52=0,CY92,CZ52/CZ79) -> 5.3305 | DA92: =IF(DA52=0,CU92,DA52/DA79) -> 3.9660294 | DC92: =IF(DC52=0,DA92,DC52/DC79) -> 5.2146667 | DD92: =IF(DD52=0,DC92,DD52/DD79) -> 3.2773333 | DE92: =IF(DE52=0,DD92,DE52/DE79) -> 5.873 | DF92: =IF(DF52=0,DE92,DF52/DF79) -> 3.1483636 | DG92: =IF(DG52=0,DA92,DG52/DG79) -> 4.1371818 | DI92: =IF(DI52=0,DG92,DI52/DI79) -> 5.0826667 | DJ92: =IF(DJ52=0,DH92,DJ52/DJ79) -> 3.4504167 | DK92: =IF(DK52=0,DI92,DK52/DK79) -> 4.2547 | DL92: =IF(DL52=0,DJ92,DL52/DL79) -> 3.3913571 | DM92: =IF(DM52=0,DG92,DM52/DM79) -> 3.9372222 | DO92: =IF(DO52=0,DM92,DO52/DO79) -> 6.67725 | DP92: =IF(DP52=0,DN92,DP52/DP79) -> 4.3123846 | DQ92: =IF(DQ52=0,DO92,DQ52/DQ79) -> 3.317625 | DR92: =IF(DR52=0,DP92,DR52/DR79) -> 3.1569444 | DS92: =IF(DS52=0,DM92,DS52/DS79) -> 3.9888364 | DU92: =IF(DU52=0,DS92,DU52/DU79) -> 3.9659 | DV92: =IF(DV52=0,DT92,DV52/DV79) -> 5.951125 | DW92: =IF(DW52=0,DU92,DW52/DW79) -> 6.5844444 | DX92: =IF(DX52=0,DV92,DX52/DX79) -> 6.7770476 | DY92: =IF(DY52=0,#REF!,DY52/DY79) -> 6.0879231 | EA92: =EA52/EA79 -> 4.4156923 | EB92: =EB52/EB79 -> 3.9972143 | EC92: =EC52/EC79 -> 5.5538 | ED92: =ED52/ED79 -> 4.4611765 | EE92: =IF(EE52=0,DY92,EE52/EE79) -> 6.0879231 | EG92: =EG52/EG79 -> 5.7081818 | EH92: 4 | EI92: 4 | EJ92: 4 | EK92: =IF(EK52=0,EE92,EK52/EK79) -> 6.0879231 | EL92: 5 | FA92: =BK92 -> 3.7086154 | FB92: =BQ92 -> 3.9440769 | FC92: =BW92 -> 4.708 | FD92: =CC92 -> 4.02745 | FE92: =CI92 -> 2.9837692 | FF92: =CO92 -> 3.1765769 | FG92: =CU92 -> 4.0634706 | FH92: =DA92 -> 3.9660294 | FI92: =DG92 -> 4.1371818 | FJ92: =DM92 -> 3.9372222 | FK92: =DS92 -> 3.9888364 | FL92: =DY92 -> 6.0879231 | FM92: =EE92 -> 6.0879231 | FN92: =EF92 -> 0 | FO92: =EG92 -> 5.7081818 | FP92: 5 | FQ92: 5 | FR92: 5
B93: Total DUV | EA93: =EA53/EA80 -> 37.358159 | EB93: =EB53/EB80 -> 43.046923 | EC93: =EC53/EC80 -> 51.130222 | ED93: =ED53/ED80 -> 41.367273 | EG93: =EG53/EG80 -> 31.893333
B95: Used systems ASP | BG95: 3.5 | BH95: 3.5 | BI95: 3.5 | BW95: 3.5 | CK95: 5 | CL95: 5 | CM95: 5 | CN95: 5 | CQ95: 5 | CR95: 5 | CS95: 5 | CT95: 5 | CW95: 5 | CX95: 5 | CY95: 5 | CZ95: 5 | DC95: 5 | DD95: 5 | DE95: 5 | DF95: 5 | DI95: 5 | DJ95: 5 | DK95: 5 | DL95: 5 | DM95: =DG95 -> 0 | DO95: 5 | DP95: 5 | DQ95: 5 | DR95: 5 | DS95: =DM95 -> 0 | DU95: 5 | DV95: 5 | DW95: 5 | DX95: 5 | DY95: =AVERAGE(DU95:DX95) -> 5 | EA95: 5 | EB95: 5 | EC95: 5 | ED95: 6 | FA95: =BK95 -> 0 | FB95: =BQ95 -> 0 | FC95: =BW95 -> 3.5 | FD95: =CC95 -> 0 | FE95: =CI95 -> 0 | FF95: =CO95 -> 0 | FG95: =CE95 -> 0 | FH95: =CF95 -> 0 | FU95: assume: €19m for used immersion, €5m for ArF Dry, €1m elsewhere
B97: FAST SHIPMENTS
B99: Fast shipments ('deferred revenues')
B100: Actual EUV shipped | DC100: 7 | DD100: 9 | DI100: 9 | DJ100: 14 | DK100: 7 | DL100: 12 | DM100: =SUM(DI100:DL100) -> 42 | DO100: 9 | DP100: 12 | DQ100: 10 | DR100: 10 | DS100: 42 | DU100: 9 | DV100: 9 | DW100: 11 | DX100: 14 | DY100: =SUM(DU100:DX100) -> 43 | EA100: =EA168 -> 14 | EB100: =EB168 -> 10 | EN100: assume trimming 8 from fast ships and as such cutting in half (or thereabouts) in 2024
B101: Fast shipments - carrying amount | DL101: 3000 | DM101: =DL101 -> 3000 | DO101: 1500 | DP101: 1400 | DQ101: =DP101-DQ102+DQ103 -> 1225 | DR101: 700 | DS101: =DR101 -> 700 | DU101: =DS101-DU102+DU103 -> 350 | DV101: =DU101-DV102+DV103 -> 525 | DW101: =DV101-DW102+DW103 -> 525 | DX101: =DW101-DX102+DX103 -> 875 | DY101: =DX101-DY102+DY103 -> 875 | EA101: =DY101-EA102+EA103 -> 875 | EB101: =EA101-EB102+EB103 -> 875
B102: Recognised in Sales - qtr | DO102: =DL101-DO101 -> 1500 | DP102: =DO101-DP101 -> 100 | DQ102: =IF(DQ74>DQ100,175*(DQ74-DQ100),0) -> 175 | DR102: =DQ101-DR101 -> 525 | DU102: =IF(DU74>DU100,175*(DU74-DU100),0) -> 350 | DV102: =IF(DV74>DV100,175*(DV74-DV100),0) -> 0 | DW102: =IF(DW74>DW100,175*(DW74-DW100),0) -> 0 | DX102: =IF(DX74>DX100,175*(DX74-DX100),0) -> 0 | EA102: =IF(EA74>EA100,175*(EA74-EA100),0) -> 0 | EB102: =IF(EB74>EB100,175*(EB74-EB100),0) -> 0
B103: Added to carrying amount | DO103: 0 | DP103: =IF(DP74>DP100,0,(DP100-DP74)*175) -> 0 | DQ103: =IF(DQ74>DQ100,0,(DQ100-DQ74)*175) -> 0 | DR103: =IF(DR74>DR100,0,(DR100-DR74)*175) -> 0 | DU103: =IF(DU74>DU100,0,(DU100-DU74)*175) -> 0 | DV103: =IF(DV74>DV100,0,(DV100-DV74)*175) -> 175 | DW103: =IF(DW74>DW100,0,(DW100-DW74)*175) -> 0 | DX103: =IF(DX74>DX100,0,(DX100-DX74)*175) -> 350 | EA103: =IF(EA74>EA100,0,(EA100-EA74)*175) -> 0 | EB103: =IF(EB74>EB100,0,(EB100-EB74)*175) -> 0
A106: ORDER BOOK AND BACKLOG | FA106: =FA$3 -> 2013 | FB106: =FB$3 -> 2014 | FC106: =FC$3 -> 2015 | FD106: =FD$3 -> 2016 | FE106: =FE$3 -> 2017 | FF106: =FF$3 -> 2018 | FG106: =FG$3 -> 2019 | FH106: =FH$3 -> 2020 | ... FR106: =FR$3 -> 2030e
A108: Order Intake (units)
B109: EUV - Low NA | DC109: =ROUND((DC116-DC110*260)/175,0) -> 14 | DD109: =ROUND((DD116-DD110*260)/175,0) -> 25 | DE109: =ROUND((DE116-DE110*260)/175,0) -> 17 | DF109: =ROUND((DF116-DF110*260)/175,0) -> 15 | DG109: =SUM(DC109:DF109) -> 71 | DI109: =ROUND((DI116-DI110*350)/175,0) -> 8 | DJ109: =ROUND((DJ116-DJ110*350)/175,0) -> 25 | DK109: =ROUND((DK116-DK110*350)/180,0) -> 19 | DL109: =ROUND((DL116-DL110*350)/180,0) -> 19 | DM109: =SUM(DI109:DL109) -> 71 | DO109: =DO157 -> 7 | DP109: =DP157 -> 5 | DQ109: =DQ157 -> 1 | DR109: =DR157 -> 25 | DS109: =SUM(DO109:DR109) -> 38 | DU109: =DU157 -> 3 | DV109: =DV157 -> 13 | DW109: =DW157 -> 7 | DX109: =DX157 -> 15 | DY109: =SUM(DU109:DX109) -> 38 | EA109: =EA157 -> 6 | EB109: =EB157 -> 8 | EC109: 16 | ED109: 33 | EE109: =SUM(EA109:ED109) -> 63 | EG109: =EG157 -> 22 | EH109: =EH157 -> 24 | EI109: =EI157 -> 13 | EJ109: =EJ157 -> 7 | EL109: =EL157 -> 52
B110: EUV - High NA | DC110: 0 | DD110: 2 | DE110: 0 | DF110: 0 | DG110: =SUM(DC110:DF110) -> 2 | DI110: 3 | DJ110: 3 | DK110: 1 | DL110: 0 | DM110: =SUM(DI110:DL110) -> 7 | DO110: =DO268 -> 1 | DP110: =DP268 -> 2 | DQ110: =DQ268 -> 1 | DR110: =DR268 -> 3 | DS110: =SUM(DO110:DR110) -> 7 | DU110: =DU268 -> 0 | DV110: =DV268 -> 1 | DX110: =DX268 -> 0 | DY110: =SUM(DU110:DX110) -> 1 | EA110: =EA268 -> 0 | EB110: =EB268 -> 1 | EC110: =EC268 -> 0 | ED110: =ED268 -> 0 | EE110: =SUM(EA110:ED110) -> 1 | EG110: =EG268 -> 1 | EH110: =EH268 -> 0 | EI110: =EI268 -> 2 | EJ110: =EJ268 -> 5 | EL110: =EL268 -> 13
B111: DUV | DC111: =DC112-(DC109+DC110) -> 106 | DD111: =DD112-(DD109+DD110) -> 140 | DE111: =DE112-(DE109+DE110) -> 161 | DF111: =DF112-(DF109+DF110) -> 176 | DG111: =SUM(DC111:DF111) -> 583 | DI111: =DI112-(DI109+DI110) -> 151 | DJ111: =DJ112-(DJ109+DJ110) -> 111 | DK111: =DK112-(DK109+DK110) -> 130 | DL111: =DL112-(DL109+DL110) -> 82 | DM111: =SUM(DI111:DL111) -> 474
B112: Net bookings (units) | AC112: 13 | AD112: 13 | AE112: 31 | AF112: 13 | AG112: 0 | AI112: 8 | AJ112: 15 | AK112: 35 | AL112: 40 | AM112: 98 | AO112: 50 | AP112: 59 | AQ112: 60 | AR112: 117 | AS112: 286 | AU112: 40 | AV112: 34 | AW112: 23 | AX112: 37 | AY112: 134 | BA112: 36 | BB112: 43 | BC112: 33 | BD112: 32 | BE112: 144 | BG112: 25 | BH112: 38 | BI112: 51 | BJ112: 52 | BK112: 166 | BM112: 30 | BN112: 29 | BO112: 47 | BP112: 51 | BQ112: 157 | BS112: 40 | BT112: 46 | BU112: 35 | BV112: 44 | BW112: 165 | BY112: 30 | BZ112: 43 | CA112: 43 | CB112: 44 | CC112: 160 | CE112: 55 | CF112: 55 | CG112: 70 | CH112: 75 | CI112: 255 | CK112: 62 | CL112: 59 | CM112: 67 | CN112: 53 | CO112: 241 | CQ112: 34 | CR112: 61 | CS112: 81 | CT112: 60 | CU112: 236 | CW112: 73 | CX112: 34 | CY112: 73 | CZ112: 123 | DA112: 303 | DC112: 120 | DD112: 167 | DE112: 178 | DF112: 191 | DG112: 656 | DI112: 162 | DJ112: 139 | DK112: 150 | DL112: 101 | DM112: 552
EC114: 225 | ED114: 225 | EG114: 230 | EH114: 230 | EI114: 230 | EJ114: 230
A115: Order Intake (EURm)
B116: Low NA orders | DC116: =50%*DC119 -> 2370 | DD116: 4900 | DE116: 2900 | DF116: 2600 | DG116: =SUM(DC116:DF116) -> 12770 | DI116: 2500 | DJ116: 5400 | DK116: 3800 | DL116: 3400 | DM116: =SUM(DI116:DL116) -> 15100 | DO116: 1600 | DP116: =5*180+2*360 -> 1620 | DQ116: 500 | DR116: =DR109*DR199 -> 4610.5462 | DV116: =DV109*DV199 -> 2398.3034 | DW116: =DW268 -> 0 | DX116: 3000 | EA116: =EA109*EA199 -> 1377.696 | EB116: =EB109*EB199 -> 1948.9024 | EC116: =EC109*EC114 -> 3600 | ED116: =ED109*ED114 -> 7425 | EG116: =EG109*EG114 -> 5060 | EH116: =EH109*EH114 -> 5520 | EI116: =EI109*EI114 -> 2990 | EJ116: =EJ109*EJ114 -> 1610
B117: High NA orders | DR117: =DR110*DR314 -> 1080 | DS117: =SUM(DO117:DR117) -> 1080 | DU117: 656 | DV117: =DV110*DV314 -> 360 | DW117: 1400 | DY117: =SUM(DU117:DX117) -> 2416 | EA117: 0 | EB117: =EB110*EB314 -> 360 | EC117: 0 | ED117: 0 | EE117: =SUM(EA117:ED117) -> 360 | EG117: =EG110*EG314 -> 360 | EH117: =EH110*EH314 -> 0 | EI117: =EI110*EI314 -> 720 | EJ117: =EJ110*EJ314 -> 1800
B118: Implied DUV Order Intake | DC118: =DC119-DC116 -> 2370 | DD118: =DD119-DD116 -> 3371 | DE118: =DE119-DE116 -> 3279 | DF118: =DF119-DF116 -> 4450 | DG118: =SUM(DC118:DF118) -> 13470 | DI118: =DI119-DI116 -> 4477 | DJ118: =DJ119-DJ116 -> 3061 | DK118: =DK119-DK116 -> 5120 | DL118: =DL119-DL116 -> 2916 | DM118: =SUM(DI118:DL118) -> 15574 | DO118: =DO119-DO116 -> 2152 | DP118: =DP119-DP116 -> 2880 | DQ118: =DQ119-DQ116 -> 2102 | DR118: =DR119-DR117 -> 8106 | DS118: =SUM(DO118:DR118) -> 15240 | DU118: =DU119-DU117 -> 2955 | DV118: =DV119-DV117 -> 5207 | DW118: =DW119-DW117 -> 1233 | DX118: =DX119-DX116 -> 4088 | DY118: =SUM(DU118:DX118) -> 13483 | EA118: =EA119-EA116 -> 2558.304 | EB118: =EB119-SUM(EB116:EB117) -> 3232.0976 | EC118: =EC119-SUM(EC116:EC117) -> 1799 | ED118: =ED119-SUM(ED116:ED117) -> 5733 | EE118: =SUM(EA118:ED118) -> 13322.402 | EG118: =EI143+EI144 -> 3300 | EH118: =EJ143+EJ144 -> 3437.995 | EI118: =22%*(EL143+EL144) -> 3416.1925 | EJ118: =25%*(EL143+EL144) -> 3882.0369
B119: Booked systems (EUR m) | AC119: 0 | AD119: 0 | AE119: 498 | AF119: 127 | AG119: 0 | AI119: 224 | AJ119: 394 | AK119: 777 | AL119: 956 | AM119: 2351 | AO119: 1165 | AP119: 1342 | AQ119: 1391 | AR119: 2315 | AS119: 6213 | AU119: 845 | AV119: 840 | AW119: 514 | AX119: 710 | AY119: 2909 | BA119: 865 | BB119: 949 | BC119: 831 | BD119: 667 | BE119: 3312 | BG119: 715 | BH119: 1065 | BI119: 1415 | BJ119: 1449 | BK119: 4644 | BM119: 1070 | BN119: 1048 | BO119: 1397 | BP119: 1387 | BQ119: 4902 | BS119: 1028 | BT119: 1523 | BU119: 904 | BV119: 1184 | BW119: 4639 | BY119: 835 | BZ119: 1566 | CA119: 1415 | CB119: 1580 | CC119: 5396 | CE119: 1894 | CF119: 2375 | CG119: 2154 | CH119: 2935 | CI119: 9358 | CK119: 2442 | CL119: 1952 | CM119: 2200 | CN119: 1587 | CO119: 8181 | CQ119: 1399 | CR119: 2828 | CS119: 5111 | CT119: 2402 | CU119: 11740 | CW119: 3085 | CX119: 1101 | CY119: 2868 | CZ119: 4238 | DA119: 11292 | DC119: 4740 | DD119: 8271 | DE119: 6179 | DF119: 7050 | DG119: 26240 | DI119: 6977 | DJ119: 8461 | DK119: 8920 | DL119: 6316 | DM119: 30674 | DO119: 3752 | DP119: 4500 | DQ119: 2602 | DR119: 9186 | DS119: 20040 | DU119: 3611 | DV119: 5567 | DW119: 2633 | DX119: 7088 | DY119: =SUM(DU119:DX119) -> 18899 | EA119: 3936 | EB119: 5541 | EC119: 5399 | ED119: 13158 | EE119: =SUM(EA119:ED119) -> 28034 | EG119: =SUM(EG116:EG118) -> 8720 | EH119: =SUM(EH116:EH118) -> 8957.995 | EI119: =SUM(EI116:EI118) -> 7126.1925 | EJ119: =SUM(EJ116:EJ118) -> 7292.0369 | EK119: =SUM(EG119:EJ119) -> 32096.224
B120: BtB ratio | AI120: =AI119/AI8 -> 2.2156281 | AJ120: =AJ119/AJ8 -> 2.1499626 | AK120: =AK119/AK8 -> 1.6939508 | AL120: =AL119/AL8 -> 2.2139469 | AM120: =AM119/AM8 -> 2.0010929 | AO120: =AO119/AO8 -> 1.8445218 | AP120: =AP119/AP8 -> 1.4539545 | AQ120: =AQ119/AQ8 -> 1.3544304 | AR120: =AR119/AR8 -> 1.7630036 | AS120: =AS119/AS8 -> 1.5952448 | AU120: =AU119/AU8 -> 0.65789474 | AV120: =AV119/AV8 -> 0.62987403 | AW120: =AW119/AW8 -> 0.40370719 | AX120: =AX119/AX8 -> 0.71522111 | AY120: =AY119/AY8 -> 0.59563054 | BA120: =BA119/BA8 -> 0.82380952 | BB120: =BB119/BB8 -> 0.96364744 | BC120: =BC119/BC8 -> 0.83075077 | BD120: =BD119/BD8 -> 0.87018917 | BE120: =BE119/BE8 -> 0.87121212 | BG120: =BG119/BG8 -> 1.056286 | BH120: =BH119/BH8 -> 1.1632987 | BI120: =BI119/BI8 -> 1.4747264 | BJ120: =BJ119/BJ8 -> 1.0054122 | BK120: =BK119/BK8 -> 1.1630062 | BM120: =BM119/BM8 -> 1.038835 | BN120: =BN119/BN8 -> 0.84312148 | BO120: =BO119/BO8 -> 1.5794234 | BP120: =BP119/BP8 -> 1.2779877 | BQ120: =BQ119/BQ8 -> 1.1553691 | BS120: =BS119/BS8 -> 0.82470919 | BT120: =BT119/BT8 -> 1.3424416 | BU120: =BU119/BU8 -> 0.92689429 | BV120: =BV119/BV8 -> 1.3440799 | BW120: =BW119/BW8 -> 1.0948268 | BY120: =BY119/BY8 -> 0.97115608 | BZ120: =BZ119/BZ8 -> 1.2375533 | CA120: =CA119/CA8 -> 1.1250696 | CB120: =CB119/CB8 -> 1.2256613 | CC120: =CC119/CC8 -> 1.1549658 | CE120: =CE119/CE8 -> 1.557822 | CF120: =CF119/CF8 -> 1.7159165 | CG120: =CG119/CG8 -> 1.1842322 | CH120: =CH119/CH8 -> 1.5013556 | CI120: =CI119/CI8 -> 1.468221 | CK120: =CK119/CK8 -> 1.4642921 | CL120: =CL119/CL8 -> 0.93553798 | CM120: =CM119/CM8 -> 1.0573873 | CN120: =CN119/CN8 -> 0.65462195 | CO120: =CO119/CO8 -> 0.99054376 | CQ120: =CQ119/CQ8 -> 0.82830077 | CR120: =CR119/CR8 -> 1.5279879 | CS120: =CS119/CS8 -> 2.1977124 | CT120: =CT119/CT8 -> 0.76724055 | CU120: =CU119/CU8 -> 1.3050099 | CW120: =CW119/CW8 -> 1.947601 | CX120: =CX119/CX8 -> 0.45148856 | CY120: =CY119/CY8 -> 0.92647629 | CZ120: =CZ119/CZ8 -> 1.3250789 | DA120: =DA119/DA8 -> 1.0945573 | DC120: =DC119/DC8 -> 1.5149578 | DD120: =DD119/DD8 -> 2.804109 | DE120: =DE119/DE8 -> 1.5030041 | DF120: =DF119/DF8 -> 2.0356895 | DG120: =DG119/DG8 -> 1.9219642 | DI120: =DI119/DI8 -> 3.0504547 | DJ120: =DJ119/DJ8 -> 2.043473 | DK120: =DK119/DK8 -> 2.096505 | DL120: =DL119/DL8 -> 1.3302723 | DM120: =DM119/DM8 -> 1.9879069 | DO120: =DO119/DO8 -> 0.70238496 | DP120: =DP119/DP8 -> 0.80269706 | DQ120: =DQ119/DQ8 -> 0.490185 | DR120: =DR119/DR8 -> 1.616542 | DS120: =DS119/DS8 -> 0.91345847 | DU120: =DU119/DU8 -> 0.91051212 | DV120: =DV119/DV8 -> 1.1693167 | DW120: =DW119/DW8 -> 0.4443132 | DX120: =DX119/DX8 -> 0.9960792 | DY120: =DY119/DY8 -> 0.86817311 | EA120: =EA119/EA8 -> 0.6856665 | EB120: =EB119/EB8 -> 0.99015386 | EC120: =EC119/EC8 -> 0.97212719 | ED120: =ED119/ED8 -> 1.7349684 | EE120: =EE119/EE8 -> 1.1454464 | EG120: =EG119/EG8 -> 1.3887562 | EH120: =EH119/EH8 -> 1.5260639 | EI120: =EI119/EI8 -> 0.89863713 | EJ120: =EJ119/EJ8 -> 0.87877094
B122: ASP booked systems (EUR m) | AC122: 0 | AD122: 0 | AE122: 0 | AF122: 20.4 | AG122: 0 | AI122: 13.8 | AJ122: 31.1 | AK122: 23.4 | AL122: 19.7 | AM122: 23.989796 | AO122: 23.3 | AP122: 22.745763 | AQ122: 23.183333 | AR122: 19.786325 | AS122: 21.723776 | AU122: 21.125 | AV122: 24.705882 | AW122: 22.347826 | AX122: 19.189189 | AY122: 21.708955 | BA122: 24.027778 | BB122: 22.069767 | BC122: 25.181818 | BD122: 20.84375 | BE122: 23 | BG122: 28.6 | BH122: 28.026316 | BI122: 27.745098 | BJ122: 27.865385 | BK122: 27.975904 | BM122: 35.666667 | BN122: 36.137931 | BO122: 29.723404 | BP122: 27.196078 | BQ122: 31.22293 | BS122: 25.7 | BT122: 33.108696 | BU122: 25.828571 | BV122: 26.909091 | BW122: 28.115152 | BY122: 27.833333 | BZ122: 36.418605 | CA122: 32.9 | CB122: 35.9 | CC122: 33.725 | CE122: 34.436364 | CF122: 43.181818 | CG122: 30.771429 | CH122: 39.133333 | CI122: 36.698039 | CK122: 39.387097 | CL122: 33.084746 | CM122: 32.835821 | CN122: 29.943396 | CO122: 33.946058 | CQ122: 41.147059 | CR122: 46.360656 | CS122: 63.098765 | CT122: 40.033333 | CU122: 49.745763 | CW122: 42.260274 | CX122: 32.382353 | CY122: 39.287671 | CZ122: 34.455285 | DA122: 37.267327 | DC122: 39.5 | DD122: 49.526946 | DE122: 34.713483 | DF122: 36.910995 | DG122: 40 | DI122: 43.067901 | DJ122: 60.870504 | DK122: 59.466667 | DL122: 62.534653 | DM122: 55.568841
A124: Implied Backlog (units)
B125: EUV - Low NA (# systems) | DD125: =60-DD126 -> 58 | DE125: =DD125+DE109-DE126 -> 73 | DF125: =DE125+DF109-DF126 -> 86 | DG125: =DF125 -> 86 | DI125: =DG125+DI109-DI126 -> 89 | DJ125: =DH125+DJ109-DJ126 -> 17 | DK125: =DI125+DK109-DK126 -> 99 | DL125: =DJ125+DL109-DL126 -> 27 | DM125: =DL125 -> 27 | DO125: =DM125+DO109-DO126 -> 24 | DP125: =DN125+DP109-DP126 -> -7 | DQ125: =DO125+DQ109-DQ126 -> 12 | DR125: =DR188 -> 70 | DS125: =DR125 -> 70 | DU125: =DU188 -> 62 | DV125: =DV188 -> 67 | DW125: =DW188 -> 63 | DX125: =DX188 -> 66 | DY125: =DX125 -> 66 | EA125: =EA188 -> 58 | EB125: =EB188 -> 56 | EC125: =EC188 -> 64 | ED125: =ED188 -> 85 | EE125: =ED125 -> 85 | EG125: =EG188 -> 93 | EH125: =EH188 -> 103 | EI125: =EI188 -> 99 | EJ125: =EJ188 -> 88
...

Sheet Financials
A1: =Cover!$E$12 -> ASML Holdings NV | DO1: =DO58 -> 4.9539007 | DP1: =DP58 -> 4.9281726 | DQ1: =DQ58 -> 4.8129131 | DR1: =DR58 -> 5.2008634 | DS1: =DS58 -> 19.895939 | DU1: =DU58 -> 3.1084582 | DV1: =DV58 -> 4.0099111 | DW1: =DW58 -> 5.2756606 | DX1: =DX58 -> 6.8429878 | DY1: =DY58 -> 19.236789 | EA1: =EA58 -> 6 | EB1: =EB58 -> 5.8967559 | EC1: =EC58 -> 5.4811662 | ED1: =ED58 -> 7.438345 | EE1: =EE58 -> 24.811159 | EG1: =EG58 -> 7.1462276 | EH1: =EH58 -> 6.7336316 | EI1: =EI58 -> 8.2062075 | EJ1: =EJ58 -> 8.4670073 | EK1: =EK58 -> 30.547093 | FU1: =Summary!U28 -> 46.500705
A2: Financials (US GAAP) | EX2: i | EY2: o | EZ2: u | FA2: aa | FB2: ag | FC2: am | FD2: as | FE2: ay | FF2: be | FG2: bk | FH2: bq | FI2: bw | FJ2: cc | FK2: ci | FL2: co | FM2: cu | FN2: da | FO2: dg | FP2: dm | FQ2: ds | FR2: dy | FS2: ee | FT2: ek | GF2: 2025
A3: EURm unless otherwise stated | E3: 1Q04 | F3: 2Q04 | G3: 3Q04 | H3: 4Q04 | I3: 2004 | K3: 1Q05 | L3: 2Q05 | M3: 3Q05 | N3: 4Q05 | O3: 2005 | Q3: 1Q06 | R3: 2Q06 | S3: 3Q06 | T3: 4Q06 | U3: 2006 | W3: 1Q07 | X3: 2Q07 | Y3: 3Q07 | Z3: 4Q07 | AA3: 2007 | AC3: 1Q08 | AD3: 2Q08 | AE3: 3Q08 | AF3: 4Q08 | AG3: 2008 | AI3: 1Q09 | AJ3: 2Q09 | AK3: 3Q09 | AL3: 4Q09 | AM3: 2009 | AO3: 1Q10 | AP3: 2Q10 | AQ3: 3Q10 | AR3: 4Q10 | AS3: 2010 | AU3: 1Q11 | AV3: 2Q11 | AW3: 3Q11 | AX3: 4Q11 | AY3: 2011 | BA3: 1Q12 | BB3: 2Q12 | BC3: 3Q12 | BD3: 4Q12 | BE3: 2012 | BG3: 1Q13 | BH3: 2Q13 | BI3: 3Q13 | BJ3: 4Q13 | BK3: 2013 | BM3: 1Q14 | BN3: 2Q14 | BO3: 3Q14 | BP3: 4Q14 | BQ3: 2014 | BS3: 1Q15 | BT3: 2Q15 | BU3: 3Q15 | BV3: 4Q15 | BW3: 2015 | BY3: 1Q16 | BZ3: 2Q16 | CA3: 3Q16 | CB3: 4Q16 | CC3: 2016 | CE3: 1Q17 | CF3: 2Q17 | CG3: 3Q17 | CH3: 4Q17 | CI3: 2017 | CK3: 1Q18 | CL3: 2Q18 | CM3: 3Q18 | CN3: 4Q18 | CO3: 2018 | CQ3: 1Q19 | CR3: 2Q19 | CS3: 3Q19 | CT3: 4Q19 | CU3: 2019 | CW3: 1Q20 | CX3: 2Q20 | CY3: 3Q20 | CZ3: 4Q20 | DA3: 2020 | DC3: 1Q21 | DD3: 2Q21 | DE3: 3Q21 | DF3: 4Q21 | DG3: 2021 | DI3: 1Q22 | DJ3: 2Q22 | DK3: 3Q22 | DL3: 4Q22 | DM3: 2022 | DO3: 1Q23 | DP3: 2Q23 | DQ3: 3Q23 | DR3: 4Q23 | DS3: 2023 | DU3: 1Q24 | DV3: 2Q24 | DW3: 3Q24 | DX3: 4Q24 | DY3: 2024 | EA3: 1Q25 | EB3: 2Q25 | EC3: 3Q25 | ED3: 4Q25 | EE3: 2025 | EG3: 1Q26 | EH3: 2Q26e | EI3: 3Q26e | EJ3: 4Q26e | EK3: 2026e | ET3: 2000 | EU3: 2001 | EV3: 2002 | EW3: 2003 | EX3: 2004 | EY3: 2005 | EZ3: 2006 | FA3: 2007 | FB3: 2008 | FC3: 2009 | FD3: 2010 | FE3: 2011 | FF3: 2012 | FG3: 2013 | FH3: 2014 | FI3: 2015 | FJ3: 2016 | FK3: 2017 | FL3: 2018 | FM3: 2019 | FN3: 2020 | FO3: 2021 | FP3: 2022 | FQ3: 2023 | FR3: 2024 | FS3: 2025 | FT3: 2026e | FU3: 2027e | FV3: 2028e | FW3: 2029e | FX3: 2030e | GB3: Notes | GF3: Target | GH3: 2030
A6: Income Statement | E6: =E$3 -> 1Q04 | F6: =F$3 -> 2Q04 | G6: =G$3 -> 3Q04 | H6: =H$3 -> 4Q04 | I6: =I$3 -> 2004 | K6: =K$3 -> 1Q05 | L6: =L$3 -> 2Q05 | M6: =M$3 -> 3Q05 | N6: =N$3 -> 4Q05 | O6: =O$3 -> 2005 | Q6: =Q$3 -> 1Q06 | R6: =R$3 -> 2Q06 | S6: =S$3 -> 3Q06 | T6: =T$3 -> 4Q06 | U6: =U$3 -> 2006 | W6: =W$3 -> 1Q07 | X6: =X$3 -> 2Q07 | Y6: =Y$3 -> 3Q07 | Z6: =Z$3 -> 4Q07 | AA6: =AA$3 -> 2007 | AC6: =AC$3 -> 1Q08 | AD6: =AD$3 -> 2Q08 | AE6: =AE$3 -> 3Q08 | AF6: =AF$3 -> 4Q08 | AG6: =AG$3 -> 2008 | AI6: =AI$3 -> 1Q09 | AJ6: =AJ$3 -> 2Q09 | AK6: =AK$3 -> 3Q09 | AL6: =AL$3 -> 4Q09 | AM6: =AM$3 -> 2009 | AO6: =AO$3 -> 1Q10 | AP6: =AP$3 -> 2Q10 | AQ6: =AQ$3 -> 3Q10 | AR6: =AR$3 -> 4Q10 | AS6: =AS$3 -> 2010 | AU6: =AU$3 -> 1Q11 | AV6: =AV$3 -> 2Q11 | AW6: =AW$3 -> 3Q11 | AX6: =AX$3 -> 4Q11 | AY6: =AY$3 -> 2011 | BA6: =BA$3 -> 1Q12 | BB6: =BB$3 -> 2Q12 | BC6: =BC$3 -> 3Q12 | BD6: =BD$3 -> 4Q12 | BE6: =BE$3 -> 2012 | BG6: =BG$3 -> 1Q13 | BH6: =BH$3 -> 2Q13 | BI6: =BI$3 -> 3Q13 | BJ6: =BJ$3 -> 4Q13 | BK6: =BK$3 -> 2013 | BM6: =BM$3 -> 1Q14 | BN6: =BN$3 -> 2Q14 | BO6: =BO$3 -> 3Q14 | BP6: =BP$3 -> 4Q14 | BQ6: =BQ$3 -> 2014 | BS6: =BS$3 -> 1Q15 | BT6: =BT$3 -> 2Q15 | BU6: =BU$3 -> 3Q15 | BV6: =BV$3 -> 4Q15 | BW6: =BW$3 -> 2015 | BY6: =BY$3 -> 1Q16 | BZ6: =BZ$3 -> 2Q16 | CA6: =CA$3 -> 3Q16 | CB6: =CB$3 -> 4Q16 | CC6: =CC$3 -> 2016 | CE6: =CE$3 -> 1Q17 | CF6: =CF$3 -> 2Q17 | CG6: =CG$3 -> 3Q17 | CH6: =CH$3 -> 4Q17 | CI6: =CI$3 -> 2017 | CK6: =CK$3 -> 1Q18 | CL6: =CL$3 -> 2Q18 | CM6: =CM$3 -> 3Q18 | CN6: =CN$3 -> 4Q18 | CO6: =CO$3 -> 2018 | CQ6: =CQ$3 -> 1Q19 | CR6: =CR$3 -> 2Q19 | CS6: =CS$3 -> 3Q19 | CT6: =CT$3 -> 4Q19 | CU6: =CU$3 -> 2019 | CW6: =CW$3 -> 1Q20 | CX6: =CX$3 -> 2Q20 | CY6: =CY$3 -> 3Q20 | CZ6: =CZ$3 -> 4Q20 | DA6: =DA$3 -> 2020 | DC6: =DC$3 -> 1Q21 | DD6: =DD$3 -> 2Q21 | DE6: =DE$3 -> 3Q21 | DF6: =DF$3 -> 4Q21 | DG6: =DG$3 -> 2021 | DI6: =DI$3 -> 1Q22 | DJ6: =DJ$3 -> 2Q22 | DK6: =DK$3 -> 3Q22 | DL6: =DL$3 -> 4Q22 | DM6: =DM$3 -> 2022 | DO6: =DO$3 -> 1Q23 | DP6: =DP$3 -> 2Q23 | DQ6: =DQ$3 -> 3Q23 | DR6: =DR$3 -> 4Q23 | DS6: =DS$3 -> 2023 | DU6: =DU$3 -> 1Q24 | DV6: =DV$3 -> 2Q24 | DW6: =DW$3 -> 3Q24 | DX6: =DX$3 -> 4Q24 | DY6: =DY$3 -> 2024 | EA6: =EA$3 -> 1Q25 | EB6: =EB$3 -> 2Q25 | EC6: =EC$3 -> 3Q25 | ED6: =ED$3 -> 4Q25 | EE6: =EE$3 -> 2025 | EG6: =EG$3 -> 1Q26 | EH6: =EH$3 -> 2Q26e | EI6: =EI$3 -> 3Q26e | EJ6: =EJ$3 -> 4Q26e | EK6: =EK$3 -> 2026e | ET6: 2000 | EU6: 2001 | EV6: 2002 | EW6: 2003 | EX6: =EX$3 -> 2004 | EY6: =EY$3 -> 2005 | EZ6: =EZ$3 -> 2006 | FA6: =FA$3 -> 2007 | FB6: =FB$3 -> 2008 | FC6: =FC$3 -> 2009 | FD6: =FD$3 -> 2010 | FE6: =FE$3 -> 2011 | ... FX6: =FX$3 -> 2030e | GF6: =GF$3 -> Target | GH6: =GH$3 -> 2030
A7: =$A$3 -> EURm unless otherwise stated | FI7: =FI9/FH9-1 -> 0.073613032 | FJ7: =FJ9/FI9-1 -> 0.080701085 | FK7: =FK9/FJ9-1 -> 0.33231295 | FL7: =FL9/FK9-1 -> 0.20890774 | FM7: =FM9/FL9-1 -> 0.080034722 | FN7: =FN9/FM9-1 -> 0.18261576 | FO7: =FO9/FN9-1 -> 0.33141132 | FP7: =FP9/FO9-1 -> 0.13768202 | ... FX7: =FX9/FW9-1 -> 0.17176736
GH8: 0.08
B9: Total Net Sales | E9: =Sales!E10 -> 453.485 | F9: =Sales!F10 -> 616.258 | G9: =Sales!G10 -> 610.472 | H9: =Sales!H10 -> 785.162 | I9: =E9+F9+G9+H9 -> 2465.377 | K9: =Sales!K10 -> 684.68 | L9: =Sales!L10 -> 763.265 | M9: =Sales!M10 -> 533.153 | N9: =Sales!N10 -> 547.869 | O9: =K9+L9+M9+N9 -> 2528.967 | Q9: =Sales!Q10 -> 629.39 | R9: =Sales!R10 -> 941.754 | S9: =Sales!S10 -> 958.433 | T9: =Sales!T10 -> 1067.527 | U9: =Q9+R9+S9+T9 -> 3597.104 | W9: =Sales!W10 -> 960.243 | X9: =Sales!X10 -> 930.222 | Y9: =Sales!Y10 -> 934.374 | Z9: =Sales!Z10 -> 972.887 | AA9: =W9+X9+Y9+Z9 -> 3797.726 | AC9: =Sales!AC10 -> 919.208 | AD9: =Sales!AD10 -> 844.157 | AE9: =Sales!AE10 -> 696.493 | AF9: =Sales!AF10 -> 493.82 | AG9: =AC9+AD9+AE9+AF9 -> 2953.678 | AI9: =Sales!AI10 -> 183.625 | AJ9: =Sales!AJ10 -> 276.6 | AK9: =Sales!AK10 -> 555.272 | AL9: =Sales!AL10 -> 580.566 | AM9: =AI9+AJ9+AK9+AL9 -> 1596.063 | AO9: =Sales!AO10 -> 741.8 | AP9: =Sales!AP10 -> 1068.7 | AQ9: =Sales!AQ10 -> 1176 | AR9: =Sales!AR10 -> 1521.4 | AS9: =AO9+AP9+AQ9+AR9 -> 4507.9 | AU9: =Sales!AU10 -> 1452.2 | AV9: =Sales!AV10 -> 1529.4 | AW9: =Sales!AW10 -> 1458.5 | AX9: =Sales!AX10 -> 1210.9 | AY9: =AU9+AV9+AW9+AX9 -> 5651 | BA9: =Sales!BA10 -> 1251.9 | BB9: =Sales!BB10 -> 1227.7 | BC9: =Sales!BC10 -> 1228.8 | BD9: =Sales!BD10 -> 1023.1 | BE9: =BA9+BB9+BC9+BD9 -> 4731.5 | BG9: =Sales!BG10 -> 892.1 | BH9: =Sales!BH10 -> 1218.7 | BI9: =Sales!BI10 -> 1392.2 | BJ9: =Sales!BJ10 -> 1922.3 | BK9: =BG9+BH9+BI9+BJ9 -> 5425.3 | BM9: =Sales!BM10 -> 1396.5 | BN9: =Sales!BN10 -> 1643.6 | BO9: =Sales!BO10 -> 1322.2 | BP9: =Sales!BP10 -> 1494 | BQ9: =SUM(BM9:BP9) -> 5856.3 | BS9: =Sales!BS10 -> 1649.9 | BT9: =Sales!BT10 -> 1654.1 | BU9: =Sales!BU10 -> 1549.2 | BV9: =Sales!BV10 -> 1434.2 | BW9: =SUM(BS9:BV9) -> 6287.4 | BY9: =Sales!BY10 -> 1333.2 | BZ9: =Sales!BZ10 -> 1739.6 | CA9: =Sales!CA10 -> 1814.6 | CB9: =Sales!CB10 -> 1907.4 | CC9: =SUM(BY9:CB9) -> 6794.8 | CE9: =Sales!CE10 -> 1943.6 | CF9: =Sales!CF10 -> 2101.4 | CG9: =Sales!CG10 -> 2447.4 | CH9: =Sales!CH10 -> 2560.4 | CI9: =SUM(CE9:CH9) -> 9052.8 | CK9: =Sales!CK10 -> 2285 | CL9: =Sales!CL10 -> 2740.4 | CM9: =Sales!CM10 -> 2776.1 | CN9: =Sales!CN10 -> 3142.5 | CO9: =SUM(CK9:CN9) -> 10944 | CQ9: =Sales!CQ10 -> 2229.1 | CR9: =Sales!CR10 -> 2567.9 | CS9: =Sales!CS10 -> 2986.5 | CT9: =Sales!CT10 -> 4036.4 | CU9: =SUM(CQ9:CT9) -> 11819.9 | CW9: =Sales!CW10 -> 2440.6 | CX9: =Sales!CX10 -> 3325.7 | CY9: =Sales!CY10 -> 3958 | CZ9: =Sales!CZ10 -> 4254.1 | DA9: =SUM(CW9:CZ9) -> 13978.4 | DC9: =Sales!DC10 -> 4363.9 | DD9: =Sales!DD10 -> 4020.2 | DE9: =Sales!DE10 -> 5241.3 | DF9: =Sales!DF10 -> 4985.6 | DG9: =SUM(DC9:DF9) -> 18611 | DI9: =Sales!DI10 -> 3534.4 | DJ9: =Sales!DJ10 -> 5430.5 | DK9: =Sales!DK10 -> 5778.3 | DL9: =Sales!DL10 -> 6430.2 | DM9: =SUM(DI9:DL9) -> 21173.4 | DO9: =Sales!DO10 -> 6746.2 | DP9: =Sales!DP10 -> 6902.3 | DQ9: =Sales!DQ10 -> 6673 | DR9: =Sales!DR10 -> 7237 | DS9: =SUM(DO9:DR9) -> 27558.5 | DU9: =Sales!DU10 -> 5290 | DV9: =Sales!DV10 -> 6242.8 | DW9: =Sales!DW10 -> 7467.3 | DX9: =Sales!DX10 -> 9262.8 | DY9: =SUM(DU9:DX9) -> 28262.9 | EA9: =Sales!EA10 -> 7741.5 | EB9: =Sales!EB10 -> 7691.7 | EC9: =Sales!EC10 -> 7516 | ED9: =Sales!ED10 -> 9718 | EE9: =SUM(EA9:ED9) -> 32667.2 | EG9: =Sales!EG10 -> 8766.5 | EH9: =Sales!EH10 -> 8339.4 | EI9: =Sales!EI10 -> 10142.5 | EJ9: =Sales!EJ10 -> 10425.195 | EK9: =SUM(EG9:EJ9) -> 37673.595 | EL9: =EK9/EE9-1 -> 0.15325449 | ET9: 2672630 | EU9: 1589247 | EV9: =1740633+218039 -> 1958672 | EW9: =1279282+263455 -> 1542737 | EX9: =I9 -> 2465.377 | EY9: =O9 -> 2528.967 | EZ9: =U9 -> 3597.104 | FA9: =AA9 -> 3797.726 | FB9: =AG9 -> 2953.678 | FC9: =AM9 -> 1596.063 | FD9: =AS9 -> 4507.9 | FE9: =AY9 -> 5651 | FF9: =BE9 -> 4731.5 | FG9: =BK9 -> 5425.3 | FH9: =BQ9 -> 5856.3 | FI9: =BW9 -> 6287.4 | FJ9: =CC9 -> 6794.8 | FK9: =CI9 -> 9052.8 | FL9: =CO9 -> 10944 | FM9: =CU9 -> 11819.9 | FN9: =DA9 -> 13978.4 | FO9: =DG9 -> 18611 | FP9: =DM9 -> 21173.4 | FQ9: =DS9 -> 27558.5 | FR9: =DY9 -> 28262.9 | FS9: =EE9 -> 32667.2 | FT9: =Sales!FN10 -> 37673.595 | FU9: =Sales!EL10 -> 48011.948 | FV9: =Sales!FP10 -> 41296.421 | FW9: =Sales!FQ10 -> 22137.5 | FX9: =Sales!FR10 -> 25940 | FZ9: =(FX9/FQ9)^(1/7)-1 -> -0.0086091329 | GA9: =(FX9/FS9)^(1/5)-1 -> -0.045069836 | GF9: 35000 | GH9: =FU9*(1+GH8)^3 -> 60481.226 | GI9: guide: €44-60bn
E10: 307.516 | F10: 396.716 | G10: 378.18 | H10: 477.326 | I10: 1559.738 | K10: 410.566 | L10: 464.532 | M10: 335.95 | N10: 343.724 | O10: 1554.772 | Q10: 377.769 | R10: 560.831 | S10: 567.519 | T10: 628.966 | W10: 567.644 | X10: 546.956 | Y10: 549.411 | Z10: 576.752 | AC10: 545.583 | AD10: 506.689 | AE10: 431.062 | AF10: 454.83 | AI10: 171.263 | AJ10: 242.162 | AK10: 364.013 | AL10: 360.233 | AO10: 443.2 | AP10: 609.3 | AQ10: 663.5 | AR10: 836.7 | AU10: 802.6 | AV10: 839.4 | AW10: 845.1 | AX10: 714.5 | BA10: 728.3 | BB10: 697.3 | BC10: 697.8 | BD10: 602.9 | DU10: =DU9/DO9-1 -> -0.21585485 | DV10: =DV9/DP9-1 -> -0.095547861 | DW10: =DW9/DQ9-1 -> 0.11903192 | DX10: =DX9/DR9-1 -> 0.27992262 | DY10: =DY9/DS9-1 -> 0.025560172 | EA10: =EA9/DU9-1 -> 0.46342155 | EB10: =EB9/DV9-1 -> 0.23209137 | EC10: =EC9/DW9-1 -> 0.0065217682 | ED10: =ED9/DX9-1 -> 0.049142808 | EE10: =EE9/DY9-1 -> 0.15583327 | EK10: =EK9/EE9-1 -> 0.15325449
B11: Cost of Sales | E11: =704232-F11 -> 307516 | F11: 396716 | G11: 378180 | H11: =I11-G11-F11-E11 -> 477326 | I11: 1559738 | K11: 410566 | L11: 464532 | M11: 335950 | N11: =O11-M11-L11-K11 -> 343724 | O11: 1554772 | Q11: 377769 | R11: 560831 | S11: 567519 | T11: 628966 | U11: 2135086 | W11: 567644 | X11: 546956 | Y11: 549411 | Z11: 576752 | AA11: 2248335 | AC11: 545583 | AD11: 506689 | AE11: 431062 | AF11: 454830 | AG11: =AD11+AF11+AC11+AE11 -> 1938164 | AI11: 171263 | AJ11: 242162 | AK11: 364013 | AL11: 360233 | AM11: =AJ11+AL11+AI11+AK11 -> 1137671 | AO11: 443200 | AP11: 609300 | AQ11: 663500 | AR11: 836700 | AS11: =AP11+AR11+AO11+AQ11 -> 2552700 | AU11: 802600 | AV11: 839400 | AW11: 845100 | AX11: 714500 | AY11: =AV11+AX11+AU11+AW11 -> 3201600 | BA11: 728.3 | BB11: 697.3 | BC11: 697.8 | BD11: 602.9 | BE11: =BB11+BD11+BA11+BC11 -> 2726.3 | BG11: =Financials!BG73 -> 551.4 | BH11: =Financials!BH73 -> 686.7 | BI11: =Financials!BI73 -> 787.4 | BJ11: =Financials!BJ73 -> 1042.6 | BK11: =BH11+BJ11+BG11+BI11 -> 3068.1 | BM11: =BM73 -> 787 | BN11: =BN73 -> 891.7 | BO11: =BO73 -> 744.1 | BP11: =BP73 -> 837.1 | BQ11: =SUM(BM11:BP11) -> 3259.9 | BS11: =BS73 -> 871.3 | BT11: =BT73 -> 900.3 | BU11: =BU73 -> 845.7 | BV11: =BV73 -> 774.4 | BW11: =SUM(BS11:BV11) -> 3391.7 | BY11: =BY73 -> 765.1 | BZ11: =BZ73 -> 998.2 | CA11: =CA73 -> 980.2 | CB11: =CB73 -> 1006.8 | CC11: =SUM(BY11:CB11) -> 3750.3 | CE11: =CE73 -> 1019 | CF11: =CF73 -> 1154.9 | CG11: =CG73 -> 1397.9 | CH11: =CH73 -> 1404.3 | CI11: =SUM(CE11:CH11) -> 4976.1 | CK11: =CK73 -> 1171.5 | CL11: =CL73 -> 1553.5 | CM11: =CM73 -> 1440.2 | CN11: =CN73 -> 1749.6 | CO11: =SUM(CK11:CN11) -> 5914.8 | CQ11: =CQ73 -> 1301.1 | CR11: =CR73 -> 1462.7 | CS11: =CS73 -> 1680.1 | CT11: =CT73 -> 2096.3 | CU11: =SUM(CQ11:CT11) -> 6540.2 | CW11: =CW73 -> 1339.2 | CX11: =CX73 -> 1722.5 | CY11: =CY73 -> 2076.6 | CZ11: =CZ73 -> 2043 | DA11: =SUM(CW11:CZ11) -> 7181.3 | DC11: =DC73 -> 2011.5 | DD11: =DD73 -> 1975.6 | DE11: =DE73 -> 2529.9 | DF11: =DF73 -> 2285 | DG11: =SUM(DC11:DF11) -> 8802 | DI11: =DI73 -> 1803.4 | DJ11: =DJ73 -> 2766 | DK11: =DK73 -> 2784.6 | DL11: =DL73 -> 3119.3 | DM11: =SUM(DI11:DL11) -> 10473.3 | DO11: =DO73 -> 3333 | DP11: =DP73 -> 3358.3 | DQ11: =DQ73 -> 3211.4 | DR11: =DR73 -> 3519.7 | DS11: =SUM(DO11:DR11) -> 13422.4 | DU11: =DU73 -> 2593.4 | DV11: =DV73 -> 3030.6 | DW11: =DW73 -> 3673.9 | DX11: =DX73 -> 4473 | DY11: =SUM(DU11:DX11) -> 13770.9 | EA11: =EA73 -> 3561.8 | EB11: =EB73 -> 3562.2 | EC11: =EC73 -> 3635.7 | ED11: =ED9-ED13 -> 4610.3605 | EE11: =SUM(EA11:ED11) -> 15370.06 | EG11: =EG73 -> 4121.9 | EH11: =EH9-EH13 -> 3871.7 | EI11: =EI9-EI13 -> 4881.5 | EJ11: =EJ9-EJ13 -> 5005.37 | EK11: =SUM(EG11:EJ11) -> 17880.47 | ET11: 1571816 | EU11: 1558234 | EV11: =1289030+202038 -> 1491068 | EW11: =999003+174952 -> 1173955 | EX11: =I11 -> 1559738 | EY11: =O11 -> 1554772 | EZ11: =U11 -> 2135086 | FA11: =AA11 -> 2248335 | FB11: =AG11 -> 1938164 | FC11: =AM11 -> 1137671 | FD11: =AS11 -> 2552700 | FE11: =AY11 -> 3201600 | FF11: =BE11 -> 2726.3 | FG11: =BK11 -> 3068.1 | FH11: =BQ11 -> 3259.9 | FI11: =BW11 -> 3391.7 | FJ11: =CC11 -> 3750.3 | FK11: =CI11 -> 4976.1 | FL11: =CO11 -> 5914.8 | FM11: =CU11 -> 6540.2 | FN11: =DA11 -> 7181.3 | FO11: =DG11 -> 8802 | FP11: =DM11 -> 10473.3 | FQ11: =DS11 -> 13422.4 | FR11: =DY11 -> 13770.9 | FS11: =EE11 -> 15370.06 | FT11: =EK11 -> 17880.47 | FU11: =FU9-FU13 -> 21358.068 | FV11: =FV9-FV13 -> 18533.733 | FW11: =FW9-FW13 -> 11407.9 | FX11: =FX9-FX13 -> 13324.4 | GF11: =GF9-GF13 -> 15750 | GH11: =GH9-GH13 -> 24192.491
B13: Gross Profit | E13: =E9-E11 -> -307062.52 | F13: =F9-F11 -> -396099.74 | G13: =G9-G11 -> -377569.53 | H13: =H9-H11 -> -476540.84 | I13: =I9-I11 -> -1557272.6 | K13: =K9-K11 -> -409881.32 | L13: =L9-L11 -> -463768.73 | M13: =M9-M11 -> -335416.85 | N13: =N9-N11 -> -343176.13 | O13: =O9-O11 -> -1552243 | Q13: =Q9-Q11 -> -377139.61 | R13: =R9-R11 -> -559889.25 | S13: =S9-S11 -> -566560.57 | T13: =T9-T11 -> -627898.47 | U13: =U9-U11 -> -2131488.9 | W13: =W9-W11 -> -566683.76 | X13: =X9-X11 -> -546025.78 | Y13: =Y9-Y11 -> -548476.63 | Z13: =Z9-Z11 -> -575779.11 | AA13: =AA9-AA11 -> -2244537.3 | AC13: =AC9-AC11 -> -544663.79 | AD13: =AD9-AD11 -> -505844.84 | AE13: =AE9-AE11 -> -430365.51 | AF13: =AF9-AF11 -> -454336.18 | AG13: =AG9-AG11 -> -1935210.3 | AI13: =AI9-AI11 -> -171079.38 | AJ13: =AJ9-AJ11 -> -241885.4 | AK13: =AK9-AK11 -> -363457.73 | AL13: =AL9-AL11 -> -359652.43 | AM13: =AM9-AM11 -> -1136074.9 | AO13: =AO9-AO11 -> -442458.2 | AP13: =AP9-AP11 -> -608231.3 | AQ13: =AQ9-AQ11 -> -662324 | AR13: =AR9-AR11 -> -835178.6 | AS13: =AS9-AS11 -> -2548192.1 | AU13: =AU9-AU11 -> -801147.8 | AV13: =AV9-AV11 -> -837870.6 | AW13: =AW9-AW11 -> -843641.5 | AX13: =AX9-AX11 -> -713289.1 | AY13: =AY9-AY11 -> -3195949 | BA13: =BA9-BA11 -> 523.6 | BB13: =BB9-BB11 -> 530.4 | BC13: =BC9-BC11 -> 531 | BD13: =BD9-BD11 -> 420.2 | BE13: =BE9-BE11 -> 2005.2 | BG13: =BG9-BG11 -> 340.7 | BH13: =BH9-BH11 -> 532 | BI13: =BI9-BI11 -> 604.8 | BJ13: =BJ9-BJ11 -> 879.7 | BK13: =BK9-BK11 -> 2357.2 | BM13: =BM9-BM11 -> 609.5 | BN13: =BN9-BN11 -> 751.9 | BO13: =BO9-BO11 -> 578.1 | BP13: =BP9-BP11 -> 656.9 | BQ13: =BQ9-BQ11 -> 2596.4 | BS13: =BS9-BS11 -> 778.6 | BT13: =BT9-BT11 -> 753.8 | BU13: =BU9-BU11 -> 703.5 | BV13: =BV9-BV11 -> 659.8 | BW13: =BW9-BW11 -> 2895.7 | BY13: =BY9-BY11 -> 568.1 | BZ13: =BZ9-BZ11 -> 741.4 | CA13: =CA9-CA11 -> 834.4 | CB13: =CB9-CB11 -> 900.6 | CC13: =CC9-CC11 -> 3044.5 | CE13: =CE9-CE11 -> 924.6 | CF13: =CF9-CF11 -> 946.5 | CG13: =CG9-CG11 -> 1049.5 | CH13: =CH9-CH11 -> 1156.1 | CI13: =CI9-CI11 -> 4076.7 | CK13: =CK9-CK11 -> 1113.5 | CL13: =CL9-CL11 -> 1186.9 | CM13: =CM9-CM11 -> 1335.9 | CN13: =CN9-CN11 -> 1392.9 | CO13: =CO9-CO11 -> 5029.2 | CQ13: =CQ9-CQ11 -> 928 | CR13: =CR9-CR11 -> 1105.2 | CS13: =CS9-CS11 -> 1306.4 | CT13: =CT9-CT11 -> 1940.1 | CU13: =CU9-CU11 -> 5279.7 | CW13: =CW9-CW11 -> 1101.4 | CX13: =CX9-CX11 -> 1603.2 | CY13: =CY9-CY11 -> 1881.4 | CZ13: =CZ9-CZ11 -> 2211.1 | DA13: =DA9-DA11 -> 6797.1 | DC13: =DC9-DC11 -> 2352.4 | DD13: =DD9-DD11 -> 2044.6 | DE13: =DE9-DE11 -> 2711.4 | DF13: =DF9-DF11 -> 2700.6 | DG13: =DG9-DG11 -> 9809 | DI13: =DI9-DI11 -> 1731 | DJ13: =DJ9-DJ11 -> 2664.5 | DK13: =DK9-DK11 -> 2993.7 | DL13: =DL9-DL11 -> 3310.9 | DM13: =DM9-DM11 -> 10700.1 | DO13: =DO9-DO11 -> 3413.2 | DP13: =DP9-DP11 -> 3544 | DQ13: =DQ9-DQ11 -> 3461.6 | DR13: =DR9-DR11 -> 3717.3 | DS13: =DS9-DS11 -> 14136.1 | DU13: =DU9-DU11 -> 2696.6 | DV13: =DV9-DV11 -> 3212.2 | DW13: =DW9-DW11 -> 3793.4 | DX13: =DX9-DX11 -> 4789.8 | DY13: =DY9-DY11 -> 14492 | EA13: =EA9-EA11 -> 4179.7 | EB13: =EB9-EB11 -> 4129.5 | EC13: =EC9-EC11 -> 3880.3 | ED13: =ED116 -> 5107.6395 | EE13: =EE9-EE11 -> 17297.14 | EG13: =EG9-EG11 -> 4644.6 | EH13: =EH116 -> 4467.7 | EI13: =EI116 -> 5261 | EJ13: =EJ116 -> 5419.825 | EK13: =EK9-EK11 -> 19793.125 | ET13: 1100814 | EU13: 31013 | EV13: 467604 | EW13: 368782 | EX13: =EX9-EX11 -> -1557272.6 | EY13: =EY9-EY11 -> -1552243 | EZ13: =EZ9-EZ11 -> -2131488.9 | FA13: =FA9-FA11 -> -2244537.3 | FB13: =FB9-FB11 -> -1935210.3 | FC13: =FC9-FC11 -> -1136074.9 | FD13: =FD9-FD11 -> -2548192.1 | FE13: =FE9-FE11 -> -3195949 | ... FT13: =FT9-FT11 -> 19793.125 | FU13: =FU116 -> 26653.879 | FV13: =FV116 -> 22762.688 | FW13: =FW116 -> 10729.6 | FX13: =FX116 -> 12615.6 | GF13: =GF14*GF9 -> 19250 | GH13: =GH14*GH9 -> 36288.736
B14: Gross margin | E14: =E13/E9 -> -677.11725 | F14: =F13/F9 -> -642.74986 | G14: =G13/G9 -> -618.48787 | H14: =H13/H9 -> -606.93314 | I14: =I13/I$9 -> -631.65699 | K14: =K13/K9 -> -598.64655 | L14: =L13/L9 -> -607.61169 | M14: =M13/M9 -> -629.11931 | N14: =N13/N9 -> -626.38355 | O14: =O13/O$9 -> -613.7854 | Q14: =Q13/Q9 -> -599.21449 | R14: =R13/R9 -> -594.51751 | S14: =S13/S9 -> -591.13216 | T14: =T13/T9 -> -588.18041 | U14: =U13/U$9 -> -592.55693 | W14: =W13/W9 -> -590.1462 | X14: =X13/X9 -> -586.98437 | Y14: =Y13/Y9 -> -586.99902 | Z14: =Z13/Z9 -> -591.82527 | AA14: =AA13/AA$9 -> -591.02138 | AC14: =AC13/AC9 -> -592.53596 | AD14: =AD13/AD9 -> -599.23076 | AE14: =AE13/AE9 -> -617.90356 | AF14: =AF13/AF9 -> -920.04411 | AG14: =AG13/AG$9 -> -655.18663 | AI14: =AI13/AI9 -> -931.67801 | AJ14: =AJ13/AJ9 -> -874.4953 | AK14: =AK13/AK9 -> -654.558 | AL14: =AL13/AL9 -> -619.48587 | AM14: =AM13/AM$9 -> -711.7983 | AO14: =AO13/AO9 -> -596.46562 | AP14: =AP13/AP9 -> -569.13194 | AQ14: =AQ13/AQ9 -> -563.20068 | AR14: =AR13/AR9 -> -548.95399 | AS14: =AS13/AS$9 -> -565.27254 | AU14: =AU13/AU9 -> -551.67869 | AV14: =AV13/AV9 -> -547.84268 | AW14: =AW13/AW9 -> -578.43092 | AX14: =AX13/AX9 -> -589.05698 | AY14: =AY13/AY$9 -> -565.55459 | BA14: =BA13/BA9 -> 0.41824427 | BB14: =BB13/BB9 -> 0.43202737 | BC14: =BC13/BC9 -> 0.43212891 | BD14: =BD13/BD9 -> 0.41071254 | BE14: =BE13/BE$9 -> 0.42379795 | BG14: =BG13/BG9 -> 0.38190786 | BH14: =BH13/BH9 -> 0.43653073 | BI14: =BI13/BI9 -> 0.43442034 | BJ14: =BJ13/BJ9 -> 0.45762888 | BK14: =BK13/BK9 -> 0.43448289 | BM14: =BM13/BM9 -> 0.43644826 | BN14: =BN13/BN9 -> 0.4574714 | BO14: =BO13/BO9 -> 0.43722584 | BP14: =BP13/BP9 -> 0.4396921 | BQ14: =BQ13/BQ9 -> 0.4433516 | BS14: =BS13/BS9 -> 0.47190739 | BT14: =BT13/BT9 -> 0.4557161 | BU14: =BU13/BU9 -> 0.45410534 | BV14: =BV13/BV9 -> 0.46004741 | BW14: =BW13/BW9 -> 0.46055603 | BY14: =BY13/BY9 -> 0.42611761 | BZ14: =BZ13/BZ9 -> 0.42618993 | CA14: =CA13/CA9 -> 0.45982586 | CB14: =CB13/CB9 -> 0.47216106 | CC14: =CC13/CC9 -> 0.44806322 | CE14: =CE13/CE9 -> 0.47571517 | CF14: =CF13/CF9 -> 0.45041401 | CG14: =CG13/CG9 -> 0.42882242 | CH14: =CH13/CH9 -> 0.45153101 | CI14: =CI13/CI9 -> 0.45032476 | CK14: =CK13/CK9 -> 0.48730853 | CL14: =CL13/CL9 -> 0.43311195 | CM14: =CM13/CM9 -> 0.48121465 | CN14: =CN13/CN9 -> 0.44324582 | CO14: =CO13/CO9 -> 0.45953947 | CQ14: =CQ13/CQ9 -> 0.41631152 | CR14: =CR13/CR9 -> 0.43039059 | CS14: =CS13/CS9 -> 0.43743512 | CT14: =CT13/CT9 -> 0.48065108 | CU14: =CU13/CU9 -> 0.44667891 | CW14: =CW13/CW9 -> 0.45128247 | CX14: =CX13/CX9 -> 0.48206393 | CY14: =CY13/CY9 -> 0.47534108 | CZ14: =CZ13/CZ9 -> 0.51975741 | DA14: =DA13/DA9 -> 0.48625737 | DC14: =DC13/DC9 -> 0.5390591 | DD14: =DD13/DD9 -> 0.50858166 | DE14: =DE13/DE9 -> 0.51731441 | DF14: =DF13/DF9 -> 0.54168004 | DG14: =DG13/DG9 -> 0.52705389 | DI14: =DI13/DI9 -> 0.48975781 | DJ14: =DJ13/DJ9 -> 0.49065464 | DK14: =DK13/DK9 -> 0.51809356 | DL14: =DL13/DL9 -> 0.51489845 | DM14: =DM13/DM9 -> 0.50535578 | DO14: =DO13/DO9 -> 0.50594409 | DP14: =DP13/DP9 -> 0.51345204 | DQ14: =DQ13/DQ9 -> 0.51874719 | DR14: =DR13/DR9 -> 0.51365207 | DS14: =DS13/DS9 -> 0.51294882 | DU14: =DU13/DU9 -> 0.50975425 | DV14: =DV13/DV9 -> 0.51454476 | DW14: =DW13/DW9 -> 0.50800155 | DX14: =DX13/DX9 -> 0.51710066 | DY14: =DY13/DY9 -> 0.51275701 | EA14: =EA13/EA9 -> 0.53990829 | EB14: =EB13/EB9 -> 0.53687741 | EC14: =EC13/EC9 -> 0.51627195 | ED14: =ED13/ED9 -> 0.52558546 | EE14: =EE13/EE9 -> 0.52949563 | EG14: =EG13/EG9 -> 0.52981235 | EH14: =EH13/EH9 -> 0.53573399 | EI14: =EI13/EI9 -> 0.51870841 | EJ14: =EJ13/EJ9 -> 0.51987756 | EK14: =EK13/EK9 -> 0.52538456 | ET14: 0.41188417 | EU14: 0.019514273 | EV14: 0.23873522 | EW14: 0.23904398 | EX14: =EX13/EX9 -> -631.65699 | EY14: =EY13/EY9 -> -613.7854 | EZ14: =EZ13/EZ9 -> -592.55693 | FA14: =FA13/FA9 -> -591.02138 | FB14: =FB13/FB9 -> -655.18663 | FC14: =FC13/FC9 -> -711.7983 | FD14: =FD13/FD9 -> -565.27254 | FE14: =FE13/FE9 -> -565.55459 | ... FX14: =FX13/FX9 -> 0.4863377 | GB14: Any margin expansion is contingent on ASP rise, which in turn relies on productivity gain with new systems] | GF14: 0.55 | GH14: 0.6
B15: Gross Profit (before CIP)
B16: Gross margin
B18: SG&A (Reported) | E18: =98004-F18 -> 47707 | F18: 50297 | G18: 51509 | H18: =I18-G18-F18-E18 -> 52116 | I18: 201629 | K18: 50761 | L18: 54924 | M18: 48234 | N18: =O18-M18-L18-K18 -> 47285 | O18: 201204 | Q18: 50267 | R18: 51023 | S18: 51442 | T18: =U18-S18-R18-Q18 -> 52067 | U18: 204799 | W18: 56330 | X18: 56396 | Y18: 56045 | Z18: 56897 | AA18: 225668 | AC18: 57328 | AD18: 56368 | AE18: 51933 | AF18: 46712 | AG18: =AD18+AF18+AC18+AE18 -> 212341 | AI18: 40995 | AJ18: 40978 | AK18: 37537 | AL18: 37134 | AM18: =AJ18+AL18+AI18+AK18 -> 156644 | AO18: 41400 | AP18: 41700 | AQ18: 47900 | AR18: 50100 | AS18: =AP18+AR18+AO18+AQ18 -> 181100 | AU18: 54400 | AV18: 50900 | AW18: 56300 | AX18: 56300 | AY18: =AV18+AX18+AU18+AW18 -> 217900 | BA18: 55.4 | BB18: 54.7 | BC18: 69.7 | BD18: 79.5 | BE18: =BB18+BD18+BA18+BC18 -> 259.3 | BG18: =Financials!BG169 -> 62.6 | BH18: =Financials!BH169 -> 67.9 | BI18: =Financials!BI169 -> 91.2 | BJ18: =Financials!BJ169 -> 90 | BK18: =BH18+BJ18+BG18+BI18 -> 311.7 | BM18: =BM169 -> 84.9 | BN18: =BN169 -> 79.9 | BO18: =BO169 -> 76.9 | BP18: =BP169 -> 79.4 | BQ18: =SUM(BM18:BP18) -> 321.1 | BS18: =BS169 -> 82.3 | BT18: =BT169 -> 88.3 | BU18: =BU169 -> 85.6 | BV18: =BV169 -> 89.5 | BW18: =SUM(BS18:BV18) -> 345.7 | BY18: =BY169 -> 88.8 | BZ18: =BZ169 -> 90.4 | CA18: =CA169 -> 88.8 | CB18: =CB169 -> 106.8 | CC18: =SUM(BY18:CB18) -> 374.8 | CE18: =CE169 -> 98.6 | CF18: =CF169 -> 102 | CG18: =CG169 -> 103.3 | CH18: =CH169 -> 112.7 | CI18: =SUM(CE18:CH18) -> 416.6 | CK18: =CK169 -> 114.2 | CL18: =CL169 -> 117.4 | CM18: =CM169 -> 121.8 | CN18: =CN169 -> 134.6 | CO18: =SUM(CK18:CN18) -> 488 | CQ18: =CQ169 -> 121 | CR18: =CR169 -> 123.5 | CS18: =CS169 -> 128.5 | CT18: =CT169 -> 147.6 | CU18: =SUM(CQ18:CT18) -> 520.6 | CW18: =CW169 -> 130.7 | CX18: =CX169 -> 131.2 | CY18: =CY169 -> 131.5 | CZ18: =CZ169 -> 151.5 | DA18: =SUM(CW18:CZ18) -> 544.9 | DC18: =DC169 -> 168.4 | DD18: =DD169 -> 171.8 | DE18: =DE169 -> 182.9 | DF18: =DF169 -> 202.5 | DG18: =SUM(DC18:DF18) -> 725.6 | DI18: =DI169 -> 207.7 | DJ18: =DJ169 -> 222 | DK18: =DK169 -> 235.8 | DL18: =DL169 -> 280.4 | DM18: =SUM(DI18:DL18) -> 945.9 | DO18: =DO169 -> 260.3 | DP18: =DP169 -> 281.1 | DQ18: =DQ169 -> 287.8 | DR18: =DR169 -> 284.1 | DS18: =SUM(DO18:DR18) -> 1113.3 | DU18: =DU169 -> 273.3 | DV18: =DV169 -> 277 | DW18: =DW169 -> 297 | DX18: =DX169 -> 318.4 | DY18: =SUM(DU18:DX18) -> 1165.7 | EA18: =EA169 -> 280.7 | EB18: =EB169 -> 298.7 | EC18: =EC169 -> 303.2 | ED18: =ED169 -> 375.2 | EE18: =SUM(EA18:ED18) -> 1257.8 | EG18: =EG169 -> 302.3 | EH18: =EH169 -> 305.298 | EI18: =EI169 -> 320.4379 | EJ18: =EJ169 -> 345.87293 | EK18: =SUM(EG18:EJ18) -> 1273.9088 | ET18: 256513 | EU18: 245962 | EV18: 263243 | EW18: 212609 | EX18: =I18 -> 201629 | EY18: =O18 -> 201204 | EZ18: =U18 -> 204799 | FA18: =AA18 -> 225668 | FB18: =AG18 -> 212341 | FC18: =AM18 -> 156644 | FD18: =AS18 -> 181100 | FE18: =AY18 -> 217900 | FF18: =BE18 -> 259.3 | FG18: =BK18 -> 311.7 | FH18: =BQ18 -> 321.1 | FI18: =BW18 -> 345.7 | FJ18: =CC18 -> 374.8 | FK18: =CI18 -> 416.6 | FL18: =CO18 -> 488 | FM18: =CU18 -> 520.6 | FN18: =DA18 -> 544.9 | FO18: =DG18 -> 725.6 | FP18: =DM18 -> 945.9 | FQ18: =DS18 -> 1113.3 | FR18: =DY18 -> 1165.7 | FS18: =EE18 -> 1257.8 | FT18: =EK18 -> 1273.9088 | FU18: =FU169 -> 1311.8261 | FV18: =FV169 -> 1350.8809 | FW18: =FW169 -> 1391.1073 | FX18: =FX169 -> 1432.5405 | FZ18: =(FX18/FQ18)^(1/7)-1 -> 0.036673748 | GF18: 1300 | GH18: =FX18 -> 1432.5405
B19: R&D (Reported) | E19: =148395-9822-F19 -> 69841 | F19: =73732-5000 -> 68732 | G19: =123293-5726 -> 117567 | H19: =I19-G19-F19-E19 -> 74819 | I19: =352920-21961 -> 330959 | K19: =84971-5472 -> 79499 | L19: 82176 | M19: 79943 | N19: =O19-M19-L19-K19 -> 82256 | O19: =347901-24027 -> 323874 | Q19: 87011 | R19: 92320 | S19: 100321 | T19: 106915 | U19: =413708-27141 -> 386567 | W19: 116442 | X19: 120310 | Y19: 120077 | Z19: 129313 | AA19: =510503-24362 -> 486141 | AC19: 128259 | AD19: 130241 | AE19: 130157 | AF19: 127471 | AG19: =AD19+AF19+AC19+AE19 -> 516128 | AI19: 118315 | AJ19: 117890 | AK19: 115166 | AL19: 115390 | AM19: =AJ19+AL19+AI19+AK19 -> 466761 | AO19: 120300 | AP19: 125300 | AQ19: 136800 | AR19: 141000 | AS19: =AP19+AR19+AO19+AQ19 -> 523400 | AU19: 145400 | AV19: 144700 | AW19: 149800 | AX19: 150400 | AY19: =AV19+AX19+AU19+AW19 -> 590300 | BA19: 145.3 | BB19: 144.6 | BC19: 143.8 | BD19: 155.4 | BE19: =BB19+BD19+BA19+BC19 -> 589.1 | BG19: =Financials!BG178 -> 184.8 | BH19: =Financials!BH178 -> 200 | BI19: =Financials!BI178 -> 244.1 | BJ19: =Financials!BJ178 -> 253.1 | BK19: =BH19+BJ19+BG19+BI19 -> 882 | BM19: =BM178 -> 279.1 | BN19: =BN178 -> 266.9 | BO19: =BO178 -> 260.1 | BP19: =BP178 -> 268 | BQ19: =SUM(BM19:BP19) -> 1074.1 | BS19: =BS178 -> 261.4 | BT19: =BT178 -> 267.4 | BU19: =BU178 -> 266.3 | BV19: =BV178 -> 273 | BW19: =SUM(BS19:BV19) -> 1068.1 | BY19: =BY178 -> 274.7 | BZ19: =BZ178 -> 270.3 | CA19: =CA178 -> 273.4 | CB19: =CB178 -> 287.4 | CC19: =SUM(BY19:CB19) -> 1105.8 | CE19: =CE178 -> 315.1 | CF19: =CF178 -> 312.7 | CG19: =CG178 -> 314.5 | CH19: =CH178 -> 317.4 | CI19: =SUM(CE19:CH19) -> 1259.7 | CK19: =CK178 -> 357.1 | CL19: =CL178 -> 380.1 | CM19: =CM178 -> 396.3 | CN19: =CN178 -> 442.4 | CO19: =SUM(CK19:CN19) -> 1575.9 | CQ19: =CQ178 -> 472.7 | CR19: =CR178 -> 487.4 | CS19: =CS178 -> 492.3 | CT19: =CT178 -> 516.1 | CU19: =SUM(CQ19:CT19) -> 1968.5 | CW19: =CW178 -> 544 | CX19: =CX178 -> 566.9 | CY19: =CY178 -> 534 | CZ19: =CZ178 -> 555.9 | DA19: =SUM(CW19:CZ19) -> 2200.8 | DC19: =DC178 -> 623.4 | DD19: =DD178 -> 633.8 | DE19: =DE178 -> 609.2 | DF19: =DF178 -> 680.6 | DG19: =SUM(DC19:DF19) -> 2547 | DI19: =DI178 -> 738.7 | DJ19: =DJ178 -> 789.1 | DK19: =DK178 -> 819.4 | DL19: =DL178 -> 906.3 | DM19: =SUM(DI19:DL19) -> 3253.5 | DO19: =DO178 -> 947.9 | DP19: =DP178 -> 999.9 | DQ19: =DQ178 -> 991.4 | DR19: =DR178 -> 1041.3 | DS19: =SUM(DO19:DR19) -> 3980.5 | DU19: =DU178 -> 1031.9 | DV19: =DV178 -> 1100.6 | DW19: =DW178 -> 1055.2 | DX19: =DX178 -> 1116 | DY19: =SUM(DU19:DX19) -> 4303.7 | EA19: =EA178 -> 1161.1 | EB19: =EB178 -> 1166.7 | EC19: =EC178 -> 1108.7 | ED19: =ED178 -> 1262.3 | EE19: =SUM(EA19:ED19) -> 4698.8 | EG19: =EG178 -> 1184.9 | EH19: =EH178 -> 1184.9 | EI19: =EI178 -> 1219.997 | EJ19: =EJ178 -> 1244.0969 | EK19: =SUM(EG19:EJ19) -> 4833.8939 | ET19: 302032 | EU19: 331110 | EV19: 298404 | EW19: 286720 | EX19: =I19 -> 330959 | EY19: =O19 -> 323874 | EZ19: =U19 -> 386567 | FA19: =AA19 -> 486141 | FB19: =AG19 -> 516128 | FC19: =AM19 -> 466761 | FD19: =AS19 -> 523400 | FE19: =AY19 -> 590300 | FF19: =BE19 -> 589.1 | FG19: =BK19 -> 882 | FH19: =BQ19 -> 1074.1 | FI19: =BW19 -> 1068.1 | FJ19: =CC19 -> 1105.8 | FK19: =CI19 -> 1259.7 | FL19: =CO19 -> 1575.9 | FM19: =CU19 -> 1968.5 | FN19: =DA19 -> 2200.8 | FO19: =DG19 -> 2547 | FP19: =DM19 -> 3253.5 | FQ19: =DS19 -> 3980.5 | FR19: =DY19 -> 4303.7 | FS19: =EE19 -> 4698.8 | FT19: =EK19 -> 4833.8939 | FU19: =FU178 -> 5072.5886 | FV19: =FV178 -> 5423.4698 | FW19: =FW178 -> 5798.9127 | FX19: =FX178 -> 6200.6366 | FZ19: =(FX19/FQ19)^(1/7)-1 -> 0.065368392 | GF19: 4550 | GH19: =FX19 -> 6200.6366
B20: Other | E20: -5862 | F20: 0 | G20: 0 | H20: =I20-G20-F20-E20 -> 0 | I20: -5862 | K20: 0 | L20: 0 | M20: 0 | N20: =O20-M20-L20-K20 -> 0 | O20: 0 | Q20: 0 | R20: 0 | S20: 0 | T20: =U20-S20-R20-Q20 -> 0 | U20: 0 | W20: 23148 | X20: 0 | Y20: 0 | Z20: =AA20-Y20-X20-W20 -> 0 | AA20: 23148 | AC20: 0 | AD20: 0 | AE20: 0 | AF20: 0 | AG20: =AD20+AF20+AC20+AE20 -> 0 | AI20: 0 | AJ20: 0 | AK20: 0 | AL20: 0 | AM20: =AJ20+AL20+AI20+AK20 -> 0 | AO20: 0 | AP20: 0 | AQ20: 0 | AR20: 0 | AS20: =AP20+AR20+AO20+AQ20 -> 0 | AU20: 0 | AV20: 0 | AW20: 0 | AX20: 0 | AY20: =AV20+AX20+AU20+AW20 -> 0 | BA20: =AW20+AY20+AV20+AX20 -> 0 | BB20: 0 | BC20: 0 | BD20: 0 | BE20: =BB20+BD20+BA20+BC20 -> 0 | BG20: =Financials!BG181 -> -14.2 | BH20: =Financials!BH181 -> -16.3 | BI20: =Financials!BI181 -> -16.7 | BJ20: =Financials!BJ181 -> -17.2 | BK20: =BH20+BJ20+BG20+BI20 -> -64.4 | BM20: =BM181 -> -20.2 | BN20: =BN181 -> -20.3 | BO20: =BO181 -> -20.3 | BP20: =BP181 -> -20.2 | BQ20: =SUM(BM20:BP20) -> -81 | BS20: =BS181 -> -20.8 | BT20: =BT181 -> -20.8 | BU20: =BU181 -> -20.8 | BV20: =BV181 -> -20.8 | BW20: =SUM(BS20:BV20) -> -83.2 | BY20: =BY181 -> -23.4 | BZ20: =BZ181 -> -23.5 | CA20: =CA181 -> -23.4 | CB20: =CB181 -> -23.5 | CC20: =SUM(BY20:CB20) -> -93.8 | CE20: =CE181 -> -23.9 | CF20: =CF181 -> -24 | CG20: =CG181 -> -23.9 | CH20: =CH181 -> -24 | CI20: =SUM(CE20:CH20) -> -95.8 | CK20: =CK181 -> 0 | CL20: =CL181 -> 0 | CM20: =CM181 -> 0 | CN20: =CN181 -> 0 | CO20: =SUM(CK20:CN20) -> 0 | CQ20: =CQ181 -> 0 | CR20: =CR181 -> 0 | CS20: =CS181 -> 0 | CT20: =CT181 -> 0 | CU20: =SUM(CQ20:CT20) -> 0 | CW20: =CW181 -> 0 | CX20: =CX181 -> 0 | CY20: =CY181 -> 0 | CZ20: =CZ181 -> 0 | DA20: =SUM(CW20:CZ20) -> 0 | DC20: =DC181 -> 0 | DD20: =DD181 -> 0 | DE20: =DE181 -> 0 | DF20: =DF181 -> -213.7 | DG20: =SUM(DC20:DF20) -> -213.7 | DI20: =DI181 -> 0 | DJ20: =DJ181 -> 0 | DK20: =DK181 -> 0 | DL20: =DL181 -> 0 | DM20: =SUM(DI20:DL20) -> 0 | DO20: =DO181 -> 0 | DP20: =DP181 -> 0 | DQ20: =DQ181 -> 0 | DR20: =DR181 -> 0 | DS20: =SUM(DO20:DR20) -> 0 | DU20: =DU181 -> 0 | DV20: =DV181 -> 0 | DW20: =DW181 -> 0 | DX20: =DX181 -> 0 | DY20: =SUM(DU20:DX20) -> 0 | EA20: =EA181 -> 0 | EB20: =EB181 -> 0 | EC20: =EC181 -> 0 | ED20: =ED181 -> 0 | EE20: =SUM(EA20:ED20) -> 0 | EG20: =EG181 -> 0 | EH20: =EH181 -> 0 | EI20: =EI181 -> 0 | EJ20: =EJ181 -> 0 | EK20: =SUM(EG20:EJ20) -> 0 | ET20: 0 | EU20: 44559 | EV20: 0 | EW20: 24485 | EX20: =I20 -> -5862 | EY20: =O20 -> 0 | EZ20: =U20 -> 0 | FA20: =AA20 -> 23148 | FB20: =AG20 -> 0 | FC20: =AM20 -> 0 | FD20: =AS20 -> 0 | FE20: =AY20 -> 0 | FF20: =BE20 -> 0 | FG20: =BK20 -> -64.4 | FH20: =BQ20 -> -81 | FI20: =BW20 -> -83.2 | FJ20: =CC20 -> -93.8 | FK20: =CI20 -> -95.8 | FL20: =CO20 -> 0 | FM20: =CU20 -> 0 | FN20: =DA20 -> 0 | FO20: =DG20 -> -213.7 | FP20: =DM20 -> 0 | FQ20: =DS20 -> 0 | FR20: =DY20 -> 0 | FS20: =EE20 -> 0 | FT20: =EK20 -> 0 | FU20: =FU181 -> 0 | FV20: =FV181 -> 0 | FW20: =FW181 -> 0 | FX20: =FX181 -> 0 | GF20: =EE20 -> 0 | GH20: =EG20 -> 0
